Workbook

Sheet 2026 (Year VI Current Season)
A1: Trager * | C1: Jowkar | E1: Delaney | G1: Green | I1: Berke * | J1: 2026 | N1: 2025-26 Fantasy Season | P1: 10/21/25 - 3/22/26 | R1: "The Offseason" : 2026 | T1: (N/A)
E2: 1st Round Delaney | N2: BERK Berke 2030 2nd round | O2: FOR | P2: JOWK Noah Clowney
E3: 1st Round Peterson** (2026 Jowkar FRP owns swap rights) | O3: 45953
E4: 1st Round Green
E5: 2nd Round Delaney | N5: GOLD Neemias Queta | O5: FOR | P5: TRAG Ayo Dosumnu
E6: 2nd Round Trager | O6: 45647
E7: 2nd Round Green
A8: 2026 | N8: PETE Steph Curry | O8: FOR | P8: TRAG Miles Bridges
A9: Gold | C9: Moss * | E9: Baden | G9: Peterson ** | I9: Zujewski | N9: PETE Kawhi Leonard | O9: 46062 | P9: TRAG Bilal Couliably
A10: 1st Round Gold (Trager 2026 FRP owns swap rights) | E10: 1st Round Baden | G10: 1st Round Trager (right to swap with Gold 2026 FRP) | I10: 1st Round Zujewski | P10: TRAG Berke 2026 1st round
E11: 1st Round Jowkar * (owns 2026 Peterson FRP swap rights) | G11: 1st Round Berke | I11: 1st Round Moss | P11: TRAG Trager 2028 1st round
E12: 2nd Round Baden | G12: 2nd Round Gold | I12: 2nd Round Peterson | P12: TRAG Gold 2026 2nd round
E13: 2nd Round Zujewski | G13: 2nd Round Moss | P13: TRAG Gold 2029 2nd round
E14: 2nd Round Berke
E15: 2nd Round Jowkar | J15: Constitution
A16: Draft Pick Protections | H16: Protected Pick
A17: * If Kelvin is lower pick, swap with Jowkar | H17: Locked Pick- Future Protection/swap
A18: ** If Kelvin is higher pick, no swap | H18: Green (*) - Conveyed from past protection
A52: G-league: | C52: 1st call up - Oct 20th 2025 | E52: 2nd call up - Nov 23rd 2025 | G52: 3rd call up - Jan 5th, 2025 | I52: 4th call up - Feb 9th 2026 (Monday)
A53: Trager | C53: Carter Bryant | E53: Carter Bryant | G53: Carter Bryant | I53: Carter Bryant
C54: Tijaun Salaun | E54: Hugo Gonzalez | G54: Hugo Gonzalez | I54: Hugo Gonzalez
A55: Jowkar | C55: Kasparas Jakucionis | E55: Kasparas Jakucionis | G55: Kasparas Jakucionis | I55: Nikola Jovic
C56: Nikola Jovic | E56: Nikola Jovic | G56: Asa Newall | I56: Asa Newall
A57: Delaney | C57: Joan Beringer | E57: Joan Beringer | G57: Joan Beringer | I57: Joan Beringer
C58: Yang Hansen | E58: Yang Hansen | G58: Yang Hansen | I58: Yang Hansen
A59: Green | C59: Rasheer Fleming | E59: Rasheer Fleming | G59: Ryan Dunn | I59: Ryan Dunn
C60: GG Jackson | E60: GG Jackson | G60: GG Jackson | I60: Will Riley
A61: Berke | C61: Kam Jones | E61: Kam Jones | G61: Kam Jones | I61: Kam Jones
A63: Gold | C63: Anthony Black | E63: Cam Whitmore | G63: Cam Whitmore | I63: Cam Whitmore
C64: Noa Essengue | E64: Noa Essengue | G64: Noa Essengue | I64: Noa Essengue
A65: Moss | C65: Ron Holland | E65: Ron Holland | G65: Ron Holland | I65: Ron Holland
C66: Adem Bona | E66: Adem Bona | G66: Adem Bona | I66: Adem Bona
A67: Baden | C67: Rob Dillingham | E67: Bub Carrington | G67: Bub Carrington | I67: Bub Carrington
C68: Dereck Lively | E68: Dereck Lively | G68: Dereck Lively | I68: Dereck Lively
A69: Peterson | C69: Devin Carter | E69: Devin Carter | G69: Devin Carter | I69: Devin Carter
C70: Thomas Sorber | E70: Thomas Sorber | G70: Thomas Sorber | I70: Thomas Sorber
A71: Zujewski | C71: Jeremiah Fears | E71: Sion James | G71: Sion James | I71: Sion James
C72: Liam McNeeley | E72: Liam McNeeley | G72: Liam McNeeley | I72: Liam McNeeley

Sheet 2025 (Last Season)
A1: Trager | C1: Jowkar | E1: Delaney | G1: Green | I1: Berke | J1: 2025 | O1: 2024-25 Fantasy Season | S1: "The Offseason" : 2025 | U1: (N/A)
A2: 2nd Round Zujewski | C2: 2nd Round Moss | E2: 1st Round Delaney* (right to swap w/Jowkar 2025 FRP) | O2: ZJEW Wendall Carter Jr. | P2: FOR | Q2: PETE Peterson 2026 2nd round | S2: BERK Spencer Dinwiddie | T2: FOR | U2: JOWK Jerami Grant
A3: 2nd Round Gold (Jowkar 2025 2nd owns swap rights) | E3: 1st Round Berke (Peterson 2025 1st owns swap rights) | P3: 45525 | Q3: PETE Peterson 2027 2nd round | T3: 45853 | U3: JOWK Jrue Holiday
A4: 2nd Round Kelley | E4: 1st Round Green
E5: 2nd Round Green (right to swap w/Trager 2025 SRP) | O5: KELL Kelley 2025 2nd round | P5: FOR | Q5: JOWK Gold 2027 2nd round | S5: BADEN Berke 2025 1st round | T5: FOR | U5: DELA Peterson 2025 1st round
E6: 2nd Round Berke (Peterson 2025 2nd owns swap rights) | P6: 45560 | Q6: JOWK Gold 2028 2nd round | S6: BADEN Green 2025 1st round | T6: 45863 | U6: DELA Baden 2025 2nd round
E7: 2nd Round Delaney
A8: 2025 | O8: KELL Mikal Bridges | P8: FOR | Q8: PETE Jowkar 2026 1st round | S8: July 26th, 2025
A9: Gold | C9: Moss | E9: Kelley -> Baden | G9: Peterson | I9: Zujewski | O9: KELL Moss 2026 2nd round | Q9: PETE Peterson 2025 2nd round | S9: / / / / / / / / / Draft Day 2025 / / / / / / / / /
A10: 1st Round Gold | E10: 1st Round Kelley | G10: 2nd Round Jowkar (right to swap w/Gold 2025 SRP) | I10: 1st Round Zujewski | P10: 45587 | Q10: PETE Zujewski 2026 2nd round | S10: TRAG Berke 2027 1st round | T10: FOR | U10: BADEN Baden 2025 2nd round
E11: 1st Round Jowkar* (Delaney 2025 1st owns swap rights) | I11: 1st Round Moss | T11: 45864 | U11: BADEN Gold 2025 2nd round
E12: 1st Round Peterson (right to swap w/Berke 2025 1st round) | I12: 1st Round Trager | O12: TRAG Mark Williams | P12: FOR | Q12: GOLD Ivica Zubac | U12: BADEN Gold 2026 2nd round
E13: 2nd Round Peterson (right to swap w/Berke 2025 2nd) | I13: 2nd Round Trager** (Green 2025 2nd owns swap rights) | O13: TRAG Andrew Nembhard | P13: 45594 | Q13: GOLD Gold 2029 2nd round
S14: TRAG Daniel Gafford | T14: FOR | U14: GOLD Gold 2030 2nd round
O15: GREEN Joel Embiid | P15: FOR | Q15: MOSS Bam Adebayo | T15: 45865
A16: Draft Pick Protections | H16: Protected Pick | J16: Constitution | O16: GREEN Green 2029 1st round | P16: 45603
A17: * Swap rights to the owner of Delaney 2025 FRP | H17: Locked Pick- Future Protection
A18: Choose between higher of Delaney 2025 FRP and Jowkar 2025 FRP | H18: Green (*) - Conveyed from past protection | O18: DELA Bobby Portis | P18: FOR | Q18: PETE Zujewski 2027 2nd round
P19: 45656
A20: ** Swap rights to the owner of Green 2025 SRP | I20: Top 2 Scorers Matched up That Week
A21: Choose between higher of Trager 2025 SRP and Green 2025 SRP - if swap doesn't occur, conveys in 2026 | I21: Week | J21: 1st | K21: MOV | L21: 2nd | M21: 3rd | O21: PETE Mikal Bridges | P21: FOR | Q21: BERK James Harden
I22: 1 | J22: Green | K22: 13 | L22: Jowkar | M22: Zujewski | O22: PETE Berke 2027 2nd round | P22: 45679
I23: 2 | J23: Jowkar | K23: 140 | L23: Kelvin | M23: Logan
A24: 2025 Draft Order: | C24: 1st Rd Owner (Rookies) | E24: 2nd Rd Owner (Rookie & FA) | G24: 3rd Rd Owner Comp Round | I24: 3 | J24: Jowkar | K24: 223 | L24: Logan | M24: Kelvin | O24: BERK Paul George | P24: FOR | Q24: JOWK Zach Lavine
A25: #1: Lottery #1 (40% Baden) | C25: Baden | E25: Delaney | G25: Baden | I25: 4 | J25: Jowkar | K25: 93 | L25: Logan | M25: Max | O25: BERK Bradley Beal
A26: #2: Lottery #2 (30% Delaney) | C26: Zujewski | E26: Delaney | G26: Delaney | I26: 5 | J26: Logan | K26: 93 | L26: Kelvin | M26: Jowkar | O26: BERK Jrue Holiday
A27: #3: Lottery #3 (20% Gold) | C27: Delaney | E27: Peterson | G27: Gold | I27: 6 | J27: Jowkar | K27: 113 | L27: Kelvin | M27: Trager | O27: BERK Berke 2027 2nd round | P27: 45683
A28: #4: Lottery #4 (10% Zujewski) | C28: Gold | E28: Trager | G28: Zujewski | I28: 7 | J28: Green | K28: 85 | L28: Jowkar | M28: Trager
A29: #5: Moss | C29: Zujewski | E29: Jowkar | G29: Moss | I29: 8 | J29: Jowkar | K29: 52 | L29: Trager | M29: Green | O29: TRAG Coby White | P29: FOR | Q29: ZJEW Jamal Murray
A30: #6: Berke | C30: Delaney | E30: Baden | G30: Berke | I30: 9 | J30: Jowkar | K30: 53 | L30: Moss | M30: Trager | O30: TRAG Nicolas Claxton
A31: #7: Peterson | C31: Baden | E31: Delaney | G31: Peterson | I31: 10 | J31: Jowkar | K31: =112+144 -> 256 | L31: Max | M31: Trager | O31: TRAG Trager 2025 1st round | P31: 45686
A32: #8: Green | C32: Baden | E32: Delaney | G32: Green | I32: 11 | J32: Jowkar | K32: 5 | L32: Green | M32: Trager
A33: #9: Jowkar | C33: Baden | E33: Baden | G33: Jowkar | I33: 12 | J33: Trager | K33: 200 | L33: Zujewski | M33: Logan | O33: TRAG Yves Missi | P33: FOR | Q33: KELL Daniel Gafford
A34: #10: Trager | C34: Zujewski | E34: Zujewski | G34: Trager | I34: 13 | J34: Green | K34: 176 | L34: Trager | M34: Kelvin | O34: TRAG Jowkar 2026 2nd round | P34: 45698
I35: 14 | J35: Jowkar | K35: 11 | L35: Kelvin | M35: Trager
I36: 15 | J36: Green | K36: 225 | L36: Trager | M36: Moss | O36: TRAG Jordan Poole | P36: FOR | Q36: KELL Kristaps Porzingus
I37: 16 | J37: Trager | K37: 224 | L37: Green | M37: Zujewski | O37: TRAG Berke 2025 1st round | P37: 45698
A39: Punishments: | G39: 1st place finishes | I39: 2nd place finishes | K39: 3rd place finishes | M39: Total | O39: JOWK Kelley 2025 2nd round | P39: FOR | Q39: DELA John Collins
A40: Strike 1: | B40: ! | C40: Warning | G40: Logan | H40: =COUNTIF($J$21:$J$38, G40) -> 1 | I40: Logan | J40: =COUNTIF($L$21:$L$38,I40) -> 2 | K40: Logan | L40: =COUNTIF($M$21:$M$38,K40) -> 2 | M40: =H40+J40+L40 -> 5 | O40: JOWK Jowkar 2028 2nd round | P40: 45698
A41: Strike 2: | B41: !! | C41: Warning #2 | G41: Kelvin | H41: =COUNTIF($J$21:$J$38, G41) -> 0 | I41: Kelvin | J41: =COUNTIF($L$21:$L$38,I41) -> 4 | K41: Kelvin | L41: =COUNTIF($M$21:$M$38,K41) -> 2 | M41: =H41+J41+L41 -> 6
A42: Strike 3: | B42: !!! | C42: Lose furthest out SRP (if you do not own your furthest out one, yours will be preemptively taken for the next available year) | G42: Trager | H42: =COUNTIF($J$21:$J$38, G42) -> 2 | I42: Trager | J42: =COUNTIF($L$21:$L$38,I42) -> 3 | K42: Trager | L42: =COUNTIF($M$21:$M$38,K42) -> 6 | M42: =H42+J42+L42 -> 11
A43: Strike 4: | B43: !!!! | C43: Pick is dropped to #5 and out of the lottery (last of non-playoff teams) if FRP is owned by violater | G43: Green | H43: =COUNTIF($J$21:$J$38, G43) -> 4 | I43: Green | J43: =COUNTIF($L$21:$L$38,I43) -> 2 | K43: Green | L43: =COUNTIF($M$21:$M$38,K43) -> 1 | M43: =H43+J43+L43 -> 7 | O43: Drops from 7/19/25 keeper deadline
G44: Delaney | H44: =COUNTIF($J$21:$J$38, G44) -> 0 | I44: Delaney | J44: =COUNTIF($L$21:$L$38,I44) -> 0 | K44: Delaney | L44: =COUNTIF($M$21:$M$38,K44) -> 0 | M44: =H44+J44+L44 -> 0
A45: Date of Violation: | C45: Violation: | G45: Moss | H45: =COUNTIF($J$21:$J$38, G45) -> 0 | I45: Moss | J45: =COUNTIF($L$21:$L$38,I45) -> 1 | K45: Moss | L45: =COUNTIF($M$21:$M$38,K45) -> 1 | M45: =H45+J45+L45 -> 2 | O45: Quentin Grimes | Q45: Vince Williams | S45: Russell Westbrook | U45: Malik Beasley
A46: 45593 | B46: ! | C46: Logan put Scottie Pippen in g-league after the deadline | G46: Zujewski | H46: =COUNTIF($J$21:$J$38, G46) -> 0 | I46: Zujewski | J46: =COUNTIF($L$21:$L$38,I46) -> 1 | K46: Zujewski | L46: =COUNTIF($M$21:$M$38,K46) -> 2 | M46: =H46+J46+L46 -> 3 | O46: Santi Aldama | Q46: Keldon Johnson | S46: Robert Williams | U46: Obi Toppin
A47: 45641 | B47: ! | C47: Moss didn't set lineup Saturday and Sunday in a matchup | G47: Gold | H47: =COUNTIF($J$21:$J$38, G47) -> 0 | I47: Gold | J47: =COUNTIF($L$21:$L$38,I47) -> 0 | K47: Gold | L47: =COUNTIF($M$21:$M$38,K47) -> 0 | M47: =H47+J47+L47 -> 0 | O47: Noah Clowney | Q47: Klay Thompson | S47: Nick Richards | U47: Justin Champagnie
A48: 45648 | B48: ! | C48: Kelley started 15 players vs everyone else 29+ for the week lol | G48: Kelley | H48: =COUNTIF($J$21:$J$38, G48) -> 0 | I48: Kelley | J48: =COUNTIF($L$21:$L$38,I48) -> 0 | K48: Kelley | L48: =COUNTIF($M$21:$M$38,K48) -> 0 | M48: =H48+J48+L48 -> 0 | Q48: Bol Bol | S48: Julian Champagnie | U48: Dorian Finney-Smith
G49: Jowkar | H49: =COUNTIF($J$21:$J$38, G49) -> 9 | I49: Jowkar | J49: =COUNTIF($L$21:$L$38,I49) -> 2 | K49: Jowkar | L49: =COUNTIF($M$21:$M$38,K49) -> 1 | M49: =H49+J49+L49 -> 12 | O49: Jalen Smith | Q49: Jonas Valunciunas | S49: Zach Collins | U49: Gary Trent
O50: Patrick Williams | Q50: Tre Jones | S50: Jonothan Mogbo | U50: Keon Johnson
O51: Oso Ighodaro | Q51: Jordan Hawkins | S51: Saddiq Bey
A52: G-league: | C52: 1st call up - Oct 21st 2024 | E52: 2nd call up - Nov 24th 2024 | G52: 3rd call up - Dec 29th, 2024 | I52: 4th call up - Feb 9th 2025 | O52: Brandon Boston | S52: DaRon Holmes | U52: Tyus Jones
A53: Trager | C53: Tidjane Salaun | E53: Tidjane Salaun | G53: Tidjane Salaun | I53: Tidjane Salaun | O53: Ja'Kobe Walter | Q53: Day'Ron Sharpe
C54: Kyshawn George | E54: Kyshawn George | G54: Kyshawn George | I54: Kyshawn George | S54: Spencer Dinwiddie
A55: Jowkar | C55: Peyton Watson | E55: Brandin Podziemski | G55: Brandin Podziemski | I55: Peyton Watson | O55: Jonny Juzang | Q55: Justin Edwards
C56: Nikola Jovic | E56: Nikola Jovic | G56: Nikola Jovic | I56: Nikola Jovic | O56: Donte Divencenzo
A57: Delaney | C57: Cason Wallace | E57: Cason Wallace | G57: Cason Wallace | I57: Cason Wallace | O57: Max Strus
C58: Jarace Walker | E58: Jarace Walker | G58: Jarace Walker | I58: Jarace Walker
A59: Green | C59: Kobe Bufkin | E59: Kobe Bufkin | G59: GG Jackson | I59: GG Jackson
C60: Ryan Dunn | E60: Ryan Dunn | G60: Ryan Dunn | I60: Ryan Dunn
A61: Berke | C61: Jett Howard | E61: Jett Howard | G61: Jett Howard | I61: Johnny Juzang
E62: Johnny Juzang | G62: Johnny Juzang
A63: Gold | C63: Andre Jackson | E63: Reed Sheppard | G63: Reed Sheppard | I63: Reed Sheppard
C64: Emoni Bates | E64: Cam Whitmore | G64: Cam Whitmore | I64: Cam Whitmore
A65: Moss | C65: Jared McCain | E65: Ron Holland | G65: Ron Holland | I65: Ron Holland
C66: Donovan Clingan | E66: Donovan Clingan | G66: Donovan Clingan | I66: Donovan Clingan
A67: Kelley | C67: Carlton Carrington | E67: Jordan Hawkins | G67: Jordan Hawkins | I67: Jordan Hawkins
C68: Isaiah Collier | E68: Isaiah Collier | G68: Isaiah Collier | I68: Isaiah Collier
A69: Peterson | C69: Bronny James | E69: Devin Carter | G69: Devin Carter | I69: Devin Carter
C70: Tristan da Silva | E70: Tristan da Silva | G70: Tristan da Silva | I70: Tristan da Silva
A71: Zujewski | C71: Terrance Shannon | E71: Terrance Shannon | G71: Terrance Shannon | I71: Terrance Shannon
C72: Kel'el Ware | E72: Kel'el Ware | G72: Kel'el Ware | I72: Kel'el Ware
A75: 2025 Rookie Draft: July 26 - ___ , 2025 | L75: *** must take g-league eligible player | O75: Injuries for beginning of 25-26 season:
A76: Round 1 (Just Rookies) | D76: Round 2 (FA & Rookies) | H76: Round 3 (Compensatory) | O76: Player | P76: Team | Q76: Injury
A77: #1: Baden: Cooper Flagg | D77: #1: Delaney Baden Trager: Collin Murray-Boyles | H77: #1: Baden: Walter Clayton Jr. | O77: Jayson Tatum | P77: Moss | Q77: Achilles tear in playoffs
A78: #2: Zujewski: Dylan Harper | D78: #2: Delaney: Derik Queen | H78: #2: Delaney*: Hansen Yang | L78: * injury exception | O78: Tyrese Haliburton | P78: Moss | Q78: Achilles tear in playoffs
A79: #3: Delaney: VJ Edgecombe | D79: #3: Kelvin: Thomas Sorber | H79: #3: Gold: Noa Essengue | O79: Damian Lillard | P79: Kelvin | Q79: Achilles tear in playoffs
A80: #4: Gold: Ace Bailey | D80: #4: Trager: Carter Bryant | H80: #4: Zujewski: | O80: Kyrie Irving | P80: Kelvin | Q80: Torn ACL (March 2025)
A81: #5: Zujewski: Kon Knueppel | D81: #5: Jowkar: Kasparas Jakucionis | H81: #5: Moss: Jase Richardson | O81: Dejounte Murray | P81: Kelvin | Q81: Achilles Tear (January 2025)
A82: #6: Delaney Baden: Egor Demin | D82: #6: Baden: Ryan Kalkbrenner | H82: #6: Berke***: Kam Jones | O82: Darius Garland | P82: Delaney | Q82: Toe surgery (expected to miss start of szn)
A83: #7: Baden Delaney: Tre Johnson | D83: #7: Delaney: Nique Clifford | H83: #7: Kelvin*: Quentin Grimes (FA) | O83: Paul George | P83: Jowkar | Q83: Surgery in July on his knee
A84: #8: Baden Delaney: Khaman Maluach | D84: #8: Delaney: Joan Beringer | H84: #8: Green: Davion Mitchell (FA) | O84: Joel Embiid | P84: Moss | Q84: Surgery with unsure timetable
A85: #9: Baden: Cedric Coward | D85: #9: Baden Trager: Santi Aldama (FA) | H85: #9: Jowkar: Noah Clowney (FA) | O85: Derik Queen | P85: Delaney | Q85: Surgery from injury in SL
A86: #10: Zujewski: Jeramiah Fears | D86: #10: Zujewski: Liam McNeeley | H86: #10: Trager: Jay Huff (FA)
A88: Round 4 (Compensatory) | E88: Round 5 (Compensatory) | I88: Round 6 (Compensatory) | O88: Round 7 (Compensatory)
A89: #1: Baden: Day'Ron Sharpe (FA) | E89: #1: Baden: | I89: #1: Baden: | O89: #1: Baden:
A90: #2: Delaney*: Keldon Johnson (FA) | E90: #2: Delaney: | I90: #2: Delaney: | O90: #2: Delaney:
A91: #3: Gold: Asa Newell | E91: #3: Gold: | I91: #3: Gold: | O91: #3: Gold:
A92: #4: Zujewski: | E92: #4: Zujewski: | I92: #4: Zujewski: | O92: #4: Zujewski:
A93: #5: Moss: Adem Bona | E93: #5: Moss*: Dennis Schroder | I93: #5: Moss*: AJ Johnson | O93: #5: Moss*: Mouhamed Gueye
A94: #6: Berke***: *Skipping his pick* | E94: #6: Berke: | I94: #6: Berke: | O94: #6: Berke:
A95: #7: Kelvin*: Ryan Rollins | E95: #7: Kelvin*: Buddy Heild | I95: #7: Kelvin*: | O95: #7: Kelvin*:
A96: #8: Green: Rasheer Fleming | E96: #8: Green: | I96: #8: Green: | O96: #8: Green:
A97: #9: Jowkar: | E97: #9: Jowkar: | I97: #9: Jowkar: | O97: #9: Jowkar:
A98: #10: Trager: | E98: #10: Trager: | I98: #10: Trager: | O98: #10: Trager:
A115: Draft History 2021-2024 & Draft Order based on results
A116: Round 1 | D116: Round 2 | H116: Round 3
A117: #1.1: 40% lottery odds (can't get worse than 3rd overall) 2024: Reed Sheppard 2023: Victor Wembenyama 2022: Chet Holmgren 2021: Cade Cunningham | D117: #2.1: Worst regular season record 2024: Rob Dillingham 2023: Taylor Hendricks 2022: Mark Williams 2021: Moses Moody | H117: #3.1: Worst regular season record 2024: Kyle Filipowski 2023: Brice Sensabaugh 2022: Steven Adams 2021: Onyeka Okongwu
A118: #1.2: 30% lottery odds 2024: Stephon Castle 2023: Scoot Henderson 2022: Paolo Bonchero 2021: Jalen Green | D118: #2.2: 2nd worst regular season record 2024: Kel'El Ware 2023: Keyonte George 2022: Jalen Williams 2021: Marvin Bagley III | H118: #3.2: 2nd worst regular season record 2024: Jared McCain 2023: Peyton Watson 2022: Dorian Finey-Smith 2021: Seth Curry
A119: #1.3: 20% lottery odds 2024: Donovan Clingan 2023: Amen Thompson 2022: Jabari Smith Jr 2021: Jalen Suggs | D119: #2.3: 3rd worst regular season record 2024: Devin Carter 2023: Cason Wallace 2022: Jeremy Sochan 2021: Cam Thomas | H119: #3.3: 3rd worst regular season record 2024: Ayo Dosumnu 2023: Jalen Hood-Schifino 2022: Blake Wesley 2021: Markelle Fultz
A120: #1.4: 10% lottery odds 2024: Zach Edey 2023: Brandon Miller 2022: Jaden Ivey 2021: Evan Mobley | D120: #2.4: 4th worst regular season record 2024: Cody Williams 2023: Jordan Hawkins 2022: Walker Kessler 2021: Jaden McDaniels | H120: #3.4: 4th worst regular season record 2024: Vince Williams 2023: Nick Smith 2022: Jae'Sean Tate 2021: Nerlens Noel
...

Sheet 2027
A1: Trager | C1: Jowkar | E1: Delaney | G1: Green | I1: Berke | J1: 2027 | N1: 2026-27 Fantasy Season | R1: "The Offseason" : 2026 | T1: (N/A)
A2: 1st Round Trager (right to swap w/Baden 2027 FRP*) | C2: 1st Round Delaney | E2: 1st Round Peterson | G2: 1st Round Green | O2: FOR
A3: 2nd Round Trager | C3: 2nd Round Berke | E3: 2nd Round Delaney
E4: 2nd Round Zujewski
A8: 2027
A9: Gold | C9: Moss | E9: Baden | G9: Peterson | I9: Zujewski
A10: 1st Round Gold | C10: 1st Round Moss (Baden 2027 FRP owns swap rights) | E10: 1st Round Baden* (Trager 2027 FRP owns swap rights) (right to swap w/Moss 2027 FRP) | I10: 1st Round Zujewski
E11: 1st Round Jowkar | I11: 2nd Round Peterson
E12: 1st Round Berke
E13: 2nd Round Baden
E14: 2nd Round Jowkar
E15: 2nd Round Moss | J15: Constitution
A16: Draft Pick Protections | E16: 2nd Round Green | H16: Protected Pick
A17: * Protected Top 3, conveys to Baden 2028 FRP if it doesn't convey | E17: 2nd Round Gold | H17: Locked Pick- Future Protection/swap
H18: Swap rights

Sheet 2028
A1: Trager | C1: Jowkar | E1: Delaney | G1: Green | I1: Berke | J1: 2028 | N1: 2026-27 Fantasy Season | R1: "The Offseason" : 2026 | T1: (N/A)
A2: 2nd Round Trager | C2: 1st Round Jowkar | E2: 1st Round Delaney | G2: 1st Round Green | O2: FOR
C3: 2nd Round Berke | E3: 1st Round Berke | G3: 2nd Round Green
E4: 2nd Round Delaney
E5: 2nd Round Jowkar
A8: 2028
A9: Gold | C9: Moss | E9: Baden | G9: Peterson | I9: Zujewski
A10: 1st Round Gold | E10: 1st Round Baden* | G10: 1st Round Peterson | I10: 1st Round Zujewski
E11: 1st Round Moss | G11: 1st Round Trager | I11: 2nd Round Zujewski
E12: 2nd Round Moss | G12: 2nd Round Peterson
E13: 2nd Round Kelley
E14: 2nd Round Gold
J15: Constitution
A16: Draft Pick Protections | H16: Protected Pick
A17: * Conveys to Trager if Kelley 2027 FRP swap connected to Trager FRP becomes 1-3 | H17: Locked Pick- Future Protection/swap
A18: *Conveys to Moss if Kelley 2027 FRP swap connected to Trager FRP becomes 4-10 | H18: Green (*) - Conveyed from past protection

Sheet 2029
A1: Trager | C1: Jowkar | E1: Delaney | G1: Green | I1: Berke | J1: 2029 | N1: 2026-27 Fantasy Season | R1: "The Offseason" : 2026 | T1: (N/A)
A2: 1st Round Trager | C2: 1st Round Jowkar | E2: 1st Round Delaney | G2: 2nd Round Green | O2: FOR
A3: 2nd Round Trager | C3: 2nd Round Jowkar | E3: 2nd Round Delaney
C4: 2nd Round Berke
A8: 2029
A9: Gold | C9: Moss | E9: Baden | G9: Peterson | I9: Zujewski
A10: 1st Round Gold | C10: 1st Round Moss | E10: 1st Round Baden* | G10: 1st Round Peterson | I10: 1st Round Zujewski
C11: 1st Round Green | E11: 2nd Round Baden | G11: 1st Round Berke | I11: 2nd Round Zujewski
C12: 2nd Round Moss | G12: 2nd Round Peterson
G13: 2nd Round Gold
J15: Constitution
A16: Draft Pick Protections | H16: Protected Pick
A17: * Conveys to Moss if Baden 2027 FRP swap connected to Trager FRP becomes 1-3 | H17: Locked Pick- Future Protection/swap
H18: Green (*) - Conveyed from past protection

Sheet 2030
A1: Trager | C1: Jowkar | E1: Delaney | G1: Green | I1: Berke | J1: 2030 | N1: 2029-30 Fantasy Season | R1: "The Offseason" : 2030 | T1: (N/A)
A2: 1st Round Trager | C2: 1st Round Jowkar | E2: 1st Round Delaney | G2: 1st Round Green | I2: 1st Round Berke | O2: FOR
A3: 2nd Round Trager | C3: 2nd Round Jowkar | E3: 2nd Round Delaney | G3: 2nd Round Green
A4: 2nd Round Gold | C4: 2nd Round Berke
A8: 2030
A9: Gold | C9: Moss | E9: Baden | G9: Peterson | I9: Zujewski
A10: 1st Round Gold | C10: 1st Round Moss | E10: 1st Round Baden | G10: 1st Round Peterson | I10: 1st Round Zujewski
C11: 2nd Round Moss | E11: 2nd Round Baden | G11: 2nd Round Peterson | I11: 2nd Round Zujewski
A16: Draft Pick Protections | H16: Protected Pick
H17: Locked Pick- Future Protection/swap
H18: Green (*) - Conveyed from past protection

Sheet All Picks (26-30)
B2: Twin Towers | C2: Ball Don't Lie | D2: Washed Kings | E2: Ice Trae | F2: Logan | G2: Giddey Up | H2: Pure Sweat Fam | I2: Flaming Flaggs | J2: Droppin Dimes | K2: Only Franz
A3: 2026 | B3: {=INDIRECT("'2026 (Year VI: Current Season)'!A2")} | C3: {=INDIRECT("'2026 (Year VI: Current Season)'!C2")} | D3: {=INDIRECT("'2026 (Year VI: Current Season)'!E2")} -> 1st Round Delaney | E3: {=INDIRECT("'2026 (Year VI: Current Season)'!G2")} | F3: {=INDIRECT("'2026 (Year VI: Current Season)'!I2")} | G3: {=INDIRECT("'2026 (Year VI: Current Season)'!A10")} -> 1st Round Gold (Trager 2026 FRP owns swap rights) | H3: {=INDIRECT("'2026 (Year VI: Current Season)'!C10")} | I3: {=INDIRECT("'2026 (Year VI: Current Season)'!E10")} -> 1st Round Baden | J3: {=INDIRECT("'2026 (Year VI: Current Season)'!G10")} -> 1st Round Trager (right to swap with Gold 2026 FRP) | K3: {=INDIRECT("'2026 (Year VI: Current Season)'!I10")} -> 1st Round Zujewski
B4: {=INDIRECT("'2026 (Year VI: Current Season)'!A3")} | C4: {=INDIRECT("'2026 (Year VI: Current Season)'!C3")} | D4: {=INDIRECT("'2026 (Year VI: Current Season)'!E3")} -> 1st Round Peterson** (2026 Jowkar FRP owns swap rights) | E4: {=INDIRECT("'2026 (Year VI: Current Season)'!G3")} | F4: {=INDIRECT("'2026 (Year VI: Current Season)'!I3")} | G4: {=INDIRECT("'2026 (Year VI: Current Season)'!A11")} | H4: {=INDIRECT("'2026 (Year VI: Current Season)'!C11")} | I4: {=INDIRECT("'2026 (Year VI: Current Season)'!E11")} -> 1st Round Jowkar * (owns 2026 Peterson FRP swap rights) | J4: {=INDIRECT("'2026 (Year VI: Current Season)'!G11")} -> 1st Round Berke | K4: {=INDIRECT("'2026 (Year VI: Current Season)'!I11")} -> 1st Round Moss
B5: {=INDIRECT("'2026 (Year VI: Current Season)'!A4")} | C5: {=INDIRECT("'2026 (Year VI: Current Season)'!C4")} | D5: {=INDIRECT("'2026 (Year VI: Current Season)'!E4")} -> 1st Round Green | E5: {=INDIRECT("'2026 (Year VI: Current Season)'!G4")} | F5: {=INDIRECT("'2026 (Year VI: Current Season)'!I4")} | G5: {=INDIRECT("'2026 (Year VI: Current Season)'!A12")} | H5: {=INDIRECT("'2026 (Year VI: Current Season)'!C12")} | I5: {=INDIRECT("'2026 (Year VI: Current Season)'!E12")} -> 2nd Round Baden | J5: {=INDIRECT("'2026 (Year VI: Current Season)'!G12")} -> 2nd Round Gold | K5: {=INDIRECT("'2026 (Year VI: Current Season)'!I12")} -> 2nd Round Peterson
B6: {=INDIRECT("'2026 (Year VI: Current Season)'!A5")} | C6: {=INDIRECT("'2026 (Year VI: Current Season)'!C5")} | D6: {=INDIRECT("'2026 (Year VI: Current Season)'!E5")} -> 2nd Round Delaney | E6: {=INDIRECT("'2026 (Year VI: Current Season)'!G5")} | F6: {=INDIRECT("'2026 (Year VI: Current Season)'!I5")} | G6: {=INDIRECT("'2026 (Year VI: Current Season)'!A13")} | H6: {=INDIRECT("'2026 (Year VI: Current Season)'!C13")} | I6: {=INDIRECT("'2026 (Year VI: Current Season)'!E13")} -> 2nd Round Zujewski | J6: {=INDIRECT("'2026 (Year VI: Current Season)'!G13")} -> 2nd Round Moss | K6: {=INDIRECT("'2026 (Year VI: Current Season)'!I13")}
B7: {=INDIRECT("'2026 (Year VI: Current Season)'!A6")} | C7: {=INDIRECT("'2026 (Year VI: Current Season)'!C6")} | D7: {=INDIRECT("'2026 (Year VI: Current Season)'!E6")} -> 2nd Round Trager | E7: {=INDIRECT("'2026 (Year VI: Current Season)'!G6")} | F7: {=INDIRECT("'2026 (Year VI: Current Season)'!I6")} | G7: {=INDIRECT("'2026 (Year VI: Current Season)'!A14")} | H7: {=INDIRECT("'2026 (Year VI: Current Season)'!C14")} | I7: {=INDIRECT("'2026 (Year VI: Current Season)'!E14")} -> 2nd Round Berke | J7: {=INDIRECT("'2026 (Year VI: Current Season)'!G14")} | K7: {=INDIRECT("'2026 (Year VI: Current Season)'!I14")}
B8: {=INDIRECT("'2026 (Year VI: Current Season)'!A7")} | C8: {=INDIRECT("'2026 (Year VI: Current Season)'!C7")} | D8: {=INDIRECT("'2026 (Year VI: Current Season)'!E7")} -> 2nd Round Green | E8: {=INDIRECT("'2026 (Year VI: Current Season)'!G7")} | F8: {=INDIRECT("'2026 (Year VI: Current Season)'!I7")} | G8: {=INDIRECT("'2026 (Year VI: Current Season)'!A15")} | H8: {=INDIRECT("'2026 (Year VI: Current Season)'!C15")} | I8: {=INDIRECT("'2026 (Year VI: Current Season)'!E15")} -> 2nd Round Jowkar | J8: {=INDIRECT("'2026 (Year VI: Current Season)'!G15")} | K8: {=INDIRECT("'2026 (Year VI: Current Season)'!I15")}
A9: 2027 | B9: {=INDIRECT("'2027'!A2")} -> 1st Round Trager (right to swap w/Baden 2027 FRP*) | C9: {=INDIRECT("'2027'!C2")} -> 1st Round Delaney | D9: {=INDIRECT("'2027'!E2")} -> 1st Round Peterson | E9: {=INDIRECT("'2027'!G2")} -> 1st Round Green | F9: {=INDIRECT("'2027'!I2")} | G9: {=INDIRECT("'2027'!A10")} -> 1st Round Gold | H9: {=INDIRECT("'2027'!C10")} -> 1st Round Moss (Baden 2027 FRP owns swap rights) | I9: {=INDIRECT("'2027'!E10")} -> 1st Round Baden* (Trager 2027 FRP owns swap rights) (right to swap w/Moss 2027 FRP) | J9: {=INDIRECT("'2027'!G10")} | K9: {=INDIRECT("'2027'!I10")} -> 1st Round Zujewski
B10: {=INDIRECT("'2027'!A3")} -> 2nd Round Trager | C10: {=INDIRECT("'2027'!C3")} -> 2nd Round Berke | D10: {=INDIRECT("'2027'!E3")} -> 2nd Round Delaney | E10: {=INDIRECT("'2027'!G3")} | F10: {=INDIRECT("'2027'!I3")} | G10: {=INDIRECT("'2027'!A11")} | H10: {=INDIRECT("'2027'!C11")} | I10: {=INDIRECT("'2027'!E11")} -> 1st Round Jowkar | J10: {=INDIRECT("'2027'!G11")} | K10: {=INDIRECT("'2027'!I11")} -> 2nd Round Peterson
B11: {=INDIRECT("'2027'!A4")} | C11: {=INDIRECT("'2027'!C4")} | D11: {=INDIRECT("'2027'!E4")} -> 2nd Round Zujewski | E11: {=INDIRECT("'2027'!G4")} | F11: {=INDIRECT("'2027'!I4")} | G11: {=INDIRECT("'2027'!A12")} | H11: {=INDIRECT("'2027'!C12")} | I11: {=INDIRECT("'2027'!E12")} -> 1st Round Berke | J11: {=INDIRECT("'2027'!G12")} | K11: {=INDIRECT("'2027'!I12")}
B12: {=INDIRECT("'2027'!A5")} | C12: {=INDIRECT("'2027'!C5")} | D12: {=INDIRECT("'2027'!E5")} | E12: {=INDIRECT("'2027'!G5")} | F12: {=INDIRECT("'2027'!I5")} | G12: {=INDIRECT("'2027'!A13")} | H12: {=INDIRECT("'2027'!C13")} | I12: {=INDIRECT("'2027'!E13")} -> 2nd Round Baden | J12: {=INDIRECT("'2027'!G13")} | K12: {=INDIRECT("'2027'!I13")}
B13: {=INDIRECT("'2027'!A6")} | C13: {=INDIRECT("'2027'!C6")} | D13: {=INDIRECT("'2027'!E6")} | E13: {=INDIRECT("'2027'!G6")} | F13: {=INDIRECT("'2027'!I6")} | G13: {=INDIRECT("'2027'!A14")} | H13: {=INDIRECT("'2027'!C14")} | I13: {=INDIRECT("'2027'!E14")} -> 2nd Round Jowkar | J13: {=INDIRECT("'2027'!G14")} | K13: {=INDIRECT("'2027'!I14")}
B14: {=INDIRECT("'2027'!A7")} | C14: {=INDIRECT("'2027'!C7")} | D14: {=INDIRECT("'2027'!E7")} | E14: {=INDIRECT("'2027'!G7")} | F14: {=INDIRECT("'2027'!I7")} | G14: {=INDIRECT("'2027'!A15")} | H14: {=INDIRECT("'2027'!C15")} | I14: {=INDIRECT("'2027'!E15")} -> 2nd Round Moss | J14: {=INDIRECT("'2027'!G15")} | K14: {=INDIRECT("'2027'!I15")}
I15: {=INDIRECT("'2027'!E16")} -> 2nd Round Green
I16: {=INDIRECT("'2027'!E17")} -> 2nd Round Gold
A17: 2028 | B17: {=INDIRECT("'2028'!A2")} -> 2nd Round Trager | C17: {=INDIRECT("'2028'!C2")} -> 1st Round Jowkar | D17: {=INDIRECT("'2028'!E2")} -> 1st Round Delaney | E17: {=INDIRECT("'2028'!G2")} -> 1st Round Green | F17: {=INDIRECT("'2028'!I2")} | G17: {=INDIRECT("'2028'!A10")} -> 1st Round Gold | H17: {=INDIRECT("'2028'!C10")} | I17: {=INDIRECT("'2028'!E10")} -> 1st Round Baden* | J17: {=INDIRECT("'2028'!G10")} -> 1st Round Peterson | K17: {=INDIRECT("'2028'!I10")} -> 1st Round Zujewski
B18: {=INDIRECT("'2028'!A3")} | C18: {=INDIRECT("'2028'!C3")} -> 2nd Round Berke | D18: {=INDIRECT("'2028'!E3")} -> 1st Round Berke | E18: {=INDIRECT("'2028'!G3")} -> 2nd Round Green | F18: {=INDIRECT("'2028'!I3")} | G18: {=INDIRECT("'2028'!A11")} | H18: {=INDIRECT("'2028'!C11")} | I18: {=INDIRECT("'2028'!E11")} -> 1st Round Moss | J18: {=INDIRECT("'2028'!G11")} -> 1st Round Trager | K18: {=INDIRECT("'2028'!I11")} -> 2nd Round Zujewski
B19: {=INDIRECT("'2028'!A4")} | C19: {=INDIRECT("'2028'!C4")} | D19: {=INDIRECT("'2028'!E4")} -> 2nd Round Delaney | E19: {=INDIRECT("'2028'!G4")} | F19: {=INDIRECT("'2028'!I4")} | G19: {=INDIRECT("'2028'!A12")} | H19: {=INDIRECT("'2028'!C12")} | I19: {=INDIRECT("'2028'!E12")} -> 2nd Round Moss | J19: {=INDIRECT("'2028'!G12")} -> 2nd Round Peterson | K19: {=INDIRECT("'2028'!I12")}
B20: {=INDIRECT("'2028'!A5")} | C20: {=INDIRECT("'2028'!C5")} | D20: {=INDIRECT("'2028'!E5")} -> 2nd Round Jowkar | E20: {=INDIRECT("'2028'!G5")} | F20: {=INDIRECT("'2028'!I5")} | G20: {=INDIRECT("'2028'!A13")} | H20: {=INDIRECT("'2028'!C13")} | I20: {=INDIRECT("'2028'!E13")} -> 2nd Round Kelley | J20: {=INDIRECT("'2028'!G13")} | K20: {=INDIRECT("'2028'!I13")}
B21: {=INDIRECT("'2028'!A6")} | C21: {=INDIRECT("'2028'!C6")} | D21: {=INDIRECT("'2028'!E6")} | E21: {=INDIRECT("'2028'!G6")} | F21: {=INDIRECT("'2028'!I6")} | G21: {=INDIRECT("'2028'!A14")} | H21: {=INDIRECT("'2028'!C14")} | I21: {=INDIRECT("'2028'!E14")} -> 2nd Round Gold | J21: {=INDIRECT("'2028'!G14")} | K21: {=INDIRECT("'2028'!I14")}
B22: {=INDIRECT("'2028'!A7")} | C22: {=INDIRECT("'2028'!C7")} | D22: {=INDIRECT("'2028'!E7")} | E22: {=INDIRECT("'2028'!G7")} | F22: {=INDIRECT("'2028'!I7")} | G22: {=INDIRECT("'2028'!A15")} | H22: {=INDIRECT("'2028'!C15")} | I22: {=INDIRECT("'2028'!E15")} | J22: {=INDIRECT("'2028'!G15")} | K22: {=INDIRECT("'2028'!I15")}
A23: 2029 | B23: {=INDIRECT("'2029'!A2")} -> 1st Round Trager | C23: {=INDIRECT("'2029'!C2")} -> 1st Round Jowkar | D23: {=INDIRECT("'2029'!E2")} -> 1st Round Delaney | E23: {=INDIRECT("'2029'!G2")} -> 2nd Round Green | F23: {=INDIRECT("'2029'!I2")} | G23: {=INDIRECT("'2029'!A10")} -> 1st Round Gold | H23: {=INDIRECT("'2029'!C10")} -> 1st Round Moss | I23: {=INDIRECT("'2029'!E10")} -> 1st Round Baden* | J23: {=INDIRECT("'2029'!G10")} -> 1st Round Peterson | K23: {=INDIRECT("'2029'!I10")} -> 1st Round Zujewski
B24: {=INDIRECT("'2029'!A3")} -> 2nd Round Trager | C24: {=INDIRECT("'2029'!C3")} -> 2nd Round Jowkar | D24: {=INDIRECT("'2029'!E3")} -> 2nd Round Delaney | E24: {=INDIRECT("'2029'!G3")} | F24: {=INDIRECT("'2029'!I3")} | G24: {=INDIRECT("'2029'!A11")} | H24: {=INDIRECT("'2029'!C11")} -> 1st Round Green | I24: {=INDIRECT("'2029'!E11")} -> 2nd Round Baden | J24: {=INDIRECT("'2029'!G11")} -> 1st Round Berke | K24: {=INDIRECT("'2029'!I11")} -> 2nd Round Zujewski
B25: {=INDIRECT("'2029'!A4")} | C25: {=INDIRECT("'2029'!C4")} -> 2nd Round Berke | D25: {=INDIRECT("'2029'!E4")} | E25: {=INDIRECT("'2029'!G4")} | F25: {=INDIRECT("'2029'!I4")} | G25: {=INDIRECT("'2029'!A12")} | H25: {=INDIRECT("'2029'!C12")} -> 2nd Round Moss | I25: {=INDIRECT("'2029'!E12")} | J25: {=INDIRECT("'2029'!G12")} -> 2nd Round Peterson | K25: {=INDIRECT("'2029'!I12")}
B26: {=INDIRECT("'2029'!A5")} | C26: {=INDIRECT("'2029'!C5")} | D26: {=INDIRECT("'2029'!E5")} | E26: {=INDIRECT("'2029'!G5")} | F26: {=INDIRECT("'2029'!I5")} | G26: {=INDIRECT("'2029'!A13")} | H26: {=INDIRECT("'2029'!C13")} | I26: {=INDIRECT("'2029'!E13")} | J26: {=INDIRECT("'2029'!G13")} -> 2nd Round Gold | K26: {=INDIRECT("'2029'!I13")}
B27: {=INDIRECT("'2029'!A6")} | C27: {=INDIRECT("'2029'!C6")} | D27: {=INDIRECT("'2029'!E6")} | E27: {=INDIRECT("'2029'!G6")} | F27: {=INDIRECT("'2029'!I6")} | G27: {=INDIRECT("'2029'!A14")} | H27: {=INDIRECT("'2029'!C14")} | I27: {=INDIRECT("'2029'!E14")} | J27: {=INDIRECT("'2029'!G14")} | K27: {=INDIRECT("'2029'!I14")}
B28: {=INDIRECT("'2029'!A7")} | C28: {=INDIRECT("'2029'!C7")} | D28: {=INDIRECT("'2029'!E7")} | E28: {=INDIRECT("'2029'!G7")} | F28: {=INDIRECT("'2029'!I7")} | G28: {=INDIRECT("'2029'!A15")} | H28: {=INDIRECT("'2029'!C15")} | I28: {=INDIRECT("'2029'!E15")} | J28: {=INDIRECT("'2029'!G15")} | K28: {=INDIRECT("'2029'!I15")}
A29: 2030 | B29: {=INDIRECT("'2030'!A2")} -> 1st Round Trager | C29: {=INDIRECT("'2030'!C2")} -> 1st Round Jowkar | D29: {=INDIRECT("'2030'!E2")} -> 1st Round Delaney | E29: {=INDIRECT("'2030'!G2")} -> 1st Round Green | F29: {=INDIRECT("'2030'!I2")} -> 1st Round Berke | G29: {=INDIRECT("'2030'!A10")} -> 1st Round Gold | H29: {=INDIRECT("'2030'!C10")} -> 1st Round Moss | I29: {=INDIRECT("'2030'!E10")} -> 1st Round Baden | J29: {=INDIRECT("'2030'!G10")} -> 1st Round Peterson | K29: {=INDIRECT("'2030'!I10")} -> 1st Round Zujewski
B30: {=INDIRECT("'2030'!A3")} -> 2nd Round Trager | C30: {=INDIRECT("'2030'!C3")} -> 2nd Round Jowkar | D30: {=INDIRECT("'2030'!E3")} -> 2nd Round Delaney | E30: {=INDIRECT("'2030'!G3")} -> 2nd Round Green | F30: {=INDIRECT("'2030'!I3")} | G30: {=INDIRECT("'2030'!A11")} | H30: {=INDIRECT("'2030'!C11")} -> 2nd Round Moss | I30: {=INDIRECT("'2030'!E11")} -> 2nd Round Baden | J30: {=INDIRECT("'2030'!G11")} -> 2nd Round Peterson | K30: {=INDIRECT("'2030'!I11")} -> 2nd Round Zujewski
B31: {=INDIRECT("'2030'!A4")} -> 2nd Round Gold | C31: {=INDIRECT("'2030'!C4")} -> 2nd Round Berke | D31: {=INDIRECT("'2030'!E4")} | E31: {=INDIRECT("'2030'!G4")} | F31: {=INDIRECT("'2030'!I4")} | G31: {=INDIRECT("'2030'!A12")} | H31: {=INDIRECT("'2030'!C12")} | I31: {=INDIRECT("'2030'!E12")} | J31: {=INDIRECT("'2030'!G12")} | K31: {=INDIRECT("'2030'!I12")}
B32: {=INDIRECT("'2030'!A5")} | C32: {=INDIRECT("'2030'!C5")} | D32: {=INDIRECT("'2030'!E5")} | E32: {=INDIRECT("'2030'!G5")} | F32: {=INDIRECT("'2030'!I5")} | G32: {=INDIRECT("'2030'!A13")} | H32: {=INDIRECT("'2030'!C13")} | I32: {=INDIRECT("'2030'!E13")} | J32: {=INDIRECT("'2030'!G13")} | K32: {=INDIRECT("'2030'!I13")}
B33: {=INDIRECT("'2030'!A6")} | C33: {=INDIRECT("'2030'!C6")} | D33: {=INDIRECT("'2030'!E6")} | E33: {=INDIRECT("'2030'!G6")} | F33: {=INDIRECT("'2030'!I6")} | G33: {=INDIRECT("'2030'!A14")} | H33: {=INDIRECT("'2030'!C14")} | I33: {=INDIRECT("'2030'!E14")} | J33: {=INDIRECT("'2030'!G14")} | K33: {=INDIRECT("'2030'!I14")}
B34: {=INDIRECT("'2030'!A7")} | C34: {=INDIRECT("'2030'!C7")} | D34: {=INDIRECT("'2030'!E7")} | E34: {=INDIRECT("'2030'!G7")} | F34: {=INDIRECT("'2030'!I7")} | G34: {=INDIRECT("'2030'!A15")} | H34: {=INDIRECT("'2030'!C15")} | I34: {=INDIRECT("'2030'!E15")} | J34: {=INDIRECT("'2030'!G15")} | K34: {=INDIRECT("'2030'!I15")}
B37: Twin Towers | C37: Ball Don't Lie | D37: Washed Kings | E37: Ice Trae | F37: Logan | G37: Giddey Up | H37: Pure Sweat Fam | I37: Flaming Flaggs | J37: Droppin Dimes | K37: Only Franz
A38: 1st Round Picks | B38: =SUM(COUNTIF(B3:B34, "*1st Round*")) -> 3 | C38: =SUM(COUNTIF(C3:C34, "*1st Round*")) -> 4 | D38: =SUM(COUNTIF(D3:D34, "*1st Round*")) -> 8 | E38: =SUM(COUNTIF(E3:E34, "*1st Round*")) -> 3 | F38: =SUM(COUNTIF(F3:F34, "*1st Round*")) -> 1 | G38: =SUM(COUNTIF(G3:G34, "*1st Round*")) -> 5 | H38: =SUM(COUNTIF(H3:H34, "*1st Round*")) -> 4 | I38: =SUM(COUNTIF(I3:I34, "*1st Round*")) -> 9 | ... K38: =SUM(COUNTIF(K3:K34, "*1st Round*")) -> 6
A39: 2nd Round Picks | B39: =SUM(COUNTIF(B3:B34, "*2nd Round*")) -> 5 | C39: =SUM(COUNTIF(C3:C34, "*2nd Round*")) -> 6 | D39: =SUM(COUNTIF(D3:D34, "*2nd Round*")) -> 9 | E39: =SUM(COUNTIF(E3:E34, "*2nd Round*")) -> 3 | F39: =SUM(COUNTIF(F3:F34, "*2nd Round*")) -> 0 | G39: =SUM(COUNTIF(G3:G34, "*2nd Round*")) -> 0 | H39: =SUM(COUNTIF(H3:H34, "*2nd Round*")) -> 2 | I39: =SUM(COUNTIF(I3:I34, "*2nd Round*")) -> 14 | ... K39: =SUM(COUNTIF(K3:K34, "*2nd Round*")) -> 5
A40: Total Picks | B40: =COUNTA(B3:B34) -> 8 | C40: =COUNTA(C3:C34) -> 10 | D40: =COUNTA(D3:D34) -> 17 | E40: =COUNTA(E3:E34) -> 6 | F40: =COUNTA(F3:F34) -> 1 | G40: =COUNTA(G3:G34) -> 5 | H40: =COUNTA(H3:H34) -> 6 | I40: =COUNTA(I3:I34) -> 23 | ... K40: =COUNTA(K3:K34) -> 11

Sheet 2031
A1: Trager | C1: Jowkar | E1: Delaney | G1: Green | I1: Berke | J1: 2031 | N1: 2030-31 Fantasy Season | R1: "The Offseason" : 2031 | T1: (N/A)
A2: 1st Round Trager | C2: 1st Round Jowkar | E2: 1st Round Delaney | G2: 1st Round Green | I2: 1st Round Berke | O2: FOR
A3: 2nd Round Trager | C3: 2nd Round Jowkar | E3: 2nd Round Delaney | G3: 2nd Round Green | I3: 2nd Round Berke
A8: 2031
A9: Gold | C9: Moss | E9: Baden | G9: Peterson | I9: Zujewski
A10: 1st Round Gold | C10: 1st Round Moss | E10: 1st Round Baden | G10: 1st Round Peterson | I10: 1st Round Zujewski
A11: 2nd Round Gold | C11: 2nd Round Moss | E11: 2nd Round Baden | G11: 2nd Round Peterson | I11: 2nd Round Zujewski
A16: Draft Pick Protections | H16: Protected Pick
H17: Locked Pick- Future Protection/swap
H18: Green (*) - Conveyed from past protection

Sheet League Records
B2: Min 24000 | C2: Min 25000
E3: Most Points In a Day
A4: Rank | B4: Most Points For In a Season | C4: Most Points Against In a Season | D4: Most Points in a Week | E4: Date | F4: Team | G4: Score | H4: Most Top 50 Points Days
A5: 1 | B5: Kelvin - 34645 (2022-23) | C5: Green - 28338 (2021-22) | D5: Kelvin - 2437 (23-24 Week 12) | E5: 46009 | F5: Jowkar | G5: 544 | H5: Kelvin | I5: =COUNTIF(F5:F54, "Kelvin") -> 15
A6: 2 | B6: Kelvin - 31260 (2023-24) | C6: Kelvin - 27752 (2021-22) | D6: Kelvin - 2430 (22-23 Week 14) | E6: 3/11/23 | F6: Logan | G6: 510 | H6: Logan | I6: =COUNTIF(F5:F54, "Logan") -> 9
A7: 3 | B7: Moss - 30725 (2022-23) | C7: Spencer - 27534 (2021-22) | D7: Kelvin - 2416 (22-23 Week 12) | E7: 45252 | F7: Jowkar | G7: 503 | H7: Moss | I7: =COUNTIF(F5:F54, "Moss") -> 7
A8: 4 | B8: Kelvin - 30042 (2021-22) | C8: Zujewski - 27301 (2021-22) | D8: Kelvin - 2401 (22-23 Week 16) | E8: 12/14/22 | F8: Kelvin | G8: 501 | H8: Jowkar | I8: =COUNTIF(F5:F54, "Jowkar") -> 11
A9: 5 | B9: Trager - 29711 (2021-22) | C9: Gold - 27275 (2022-23) | D9: Kelvin - 2395 (22-23 Week 13) | E9: 1/2/23 | F9: Delaney | G9: 501 | H9: Trager | I9: =COUNTIF(F5:F54, "Trager") -> 4
A10: 6 | B10: Logan - 29620 (2021-22) | C10: Green - 26967 (2022-23) | D10: Moss - 2346 (22-23 Week 11) | E10: 45253 | F10: Jowkar | G10: 499 | H10: Green | I10: =COUNTIF(F5:F54, "Green") -> 3
A11: 7 | B11: Moss - 29128 (2021-22) | C11: Jowkar - 26914 (2022-23) | D11: Kelvin - 2322 (23-24 Week 8) | E11: 12/18/23 | F11: Green | G11: 495 | H11: Delaney | I11: =COUNTIF(F5:F54, "Delaney") -> 1
A12: 8 | B12: Jowkar - 28877 (2023-24) | C12: Delaney - 26862 (2022-23) | D12: Trager - 2316 (24-25 Week 16) | E12: 1/15/23 | F12: Kelvin | G12: 495 | H12: Kelley | I12: =COUNTIF(F5:F54, "Kelley") -> 0
A13: 9 | B13: Jowkar - 28688 (2024-25) | C13: Trager - 26555 (2022-23) | D13: Jowkar - 2267 (23-24 Week 15) | E13: 3/10/24 | F13: Kelvin | G13: 495 | J13: =SUM(I5:I12) -> 50
A14: 10 | B14: Delaney - 28416 (2022-23) | C14: Spencer - 26500 (2022-23) | D14: Kelvin - 2256 (23-24 Week 10) | E14: 10/30/23 | F14: Kelvin | G14: 493
A15: 11 | B15: Green - 28274 (2024-25) | C15: Logan - 26128 (2022-23) | D15: Kelvin - 2255 (22-23 Week 17) | E15: 45289 | F15: Kelvin | G15: 491
A16: 12 | B16: Green - 28050 (2023-24) | C16: Zujewski - 25667 (2023-24) | D16: Kelvin - 2224 (22-23 Week 11) | E16: 11/6/24 | F16: Jowkar | G16: 487
A17: 13 | B17: Logan - 27782 (2023-24) | C17: Zujewski - 25641 (2022-23) | D17: Green - 2211 (24-25 Week 14) | E17: 2/4/23 | F17: Logan | G17: 483 | H17: Highest single game scoring all time
A18: 14 | B18: Trager - 27702 (2024-25) | C18: Gold - 25154 (2023-24) | D18: Logan - 2206 (23-24 Week 15) | E18: 45294 | F18: Logan | G18: 482
A19: 15 | B19: Kelvin - 26734 (2024-25) | C19: Peterson - 25008 (2024-25) | D19: Kelvin - 2205 (23-24 Week 15) | E19: 45294 | F19: Kelvin | G19: 476 | H19: Player | I19: Score | J19: Date
A20: 16 | B20: Spencer - 26515 (2022-23) | D20: Kelvin - 2201 (23-24 Week 16) | E20: 44191 | F20: Trager | G20: 475
A21: 17 | B21: Logan - 26180 (2022-23) | D21: Kelvin - 2201 (22-23 Week 15) | E21: 44244 | F21: Moss | G21: 474 | H21: Doncic | I21: 119 | J21: 45285
A22: 18 | B22: Logan - 25127 (2024-25) | D22: Moss - 2199 (20-21 Week 14) | E22: 2/4/23 | F22: Kelvin | G22: 473 | H22: Luka | I22: 117 | J22: 45317
A23: 19 | B23: Moss - 24703 (2024-25) | D23: Green - 2166 (23-24 Week 15) | E23: 3/1/24 | F23: Logan | G23: 470 | H23: Embiid | I23: 115 | J23: 44878
A24: 20 | B24: Logan - 24391 (2020-21) | D24: Jowkar - 2155 (24-25 Week 6) | E24: 45352 | F24: Logan | G24: 470 | H24: Doncic | I24: 112 | J24: 44922
A25: 21 | B25: Zujewski - 24273 (2024-25) | D25: Logan - 2150 (21-22 Week 7) | E25: 45260 | F25: Kelvin | G25: 469 | H25: Embiid | I25: 110 | J25: 45313
A26: 22 | B26: Green - 24191 (2022-23) | D26: Jowkar - 2138 (24-25 Week 3) | E26: 45320 | F26: Jowkar | G26: 466 | H26: Giannis | I26: 109 | J26: 45609
A27: 23 | B27: Kelvin - 24115 (2020-21) | D27: Jowkar - 2131 (24-25 Week 2) | E27: 45322 | F27: Logan | G27: 464 | H27: Mitchell | I27: 109 | J27: 44928
A28: 24 | B28: Moss - 24054 (2020-21) | D28: Kelvin - 2128 (23-24 Week 11) | E28: 45303 | F28: Jowkar | G28: 462 | H28: Brunson | I28: 108 | J28: 45275
A29: 25 | D29: Kelvin - 2127 (23-24 Week 13) | E29: 45275 | F29: Green | G29: 461 | H29: Lillard | I29: 108 | J29: 44951
A30: 26 | D30: Logan - 2124 (21-22 Chip Week 1) | E30: 45247 | F30: Logan | G30: 461 | H30: Lillard | I30: 104 | J30: 44983
A31: 27 | D31: Jowkar - 2121 (23-24 Week 8) | E31: 2/25/24 | F31: Jowkar | G31: 461 | H31: Luka | I31: 102 | J31: 44926
A32: 28 | D32: Jowkar - 2112 (24-25 Week 10) | E32: 2/22/24 | F32: Jowkar | G32: 460 | H32: Giannis | I32: 100 | J32: 45273
A33: 29 | D33: Logan - 2109 (23-24 Week 8) | E33: 44555 | F33: Logan | G33: 460
A34: 30 | D34: Kelvin - 2095 (22-23 Week 9) | E34: 11/9/22 | F34: Moss | G34: 460
A35: 31 | D35: Green - 2092 (24-25 Week 16) | E35: 1/16/23 | F35: Kelvin | G35: 460
A36: 32 | D36: Trager - 2087 (24-25 Week 12) | E36: 45621 | F36: Jowkar | G36: 459
A37: 33 | D37: Jowkar - 2082 (23-24 Week 10) | E37: 44284 | F37: Moss | G37: 458
A38: 34 | D38: Jowkar - 2078 (23-24 Week 14) | E38: 12/23/22 | F38: Kelvin | G38: 458
A39: 35 | D39: Jowkar - 2063 (23-24 Week 11) | E39: 44626 | F39: Trager | G39: 456
A40: 36 | D40: Kelvin - 2063 (22-23 Week 3) | E40: 44188 | F40: Moss | G40: 454
A41: 37 | D41: Logan - 2050 (23-24 Week 4) | E41: 11/25/22 | F41: Moss | G41: 453
A42: 38 | D42: Logan - 2046 (20-21 Week 12) | E42: 44624 | F42: Logan | G42: 452
A43: 39 | D43: Green - 2043 (23-24 Week 8) | E43: 44510 | F43: Moss | G43: 452
A44: 40 | D44: Kelvin - 2042 (24-25 Week 6) | E44: 45632 | F44: Jowkar | G44: 450
A45: 41 | D45: Kelvin - 2035 (23-24 Week 14) | E45: 44657 | F45: Trager | G45: 450
A46: 42 | D46: Kelvin - 2032 (22-23 Week 2) | E46: 45692 | F46: Trager | G46: 449
A47: 43 | D47: Jowkar - 2028 (24-25 Week 11) | E47: 45278 | F47: Kelvin | G47: 449
A48: 44 | D48: Moss - 2026 (22-23 Week 4) | E48: 44218 | F48: Kelvin | G48: 448
A49: 45 | D49: Green - 2023 (24-25 Week 11) | E49: 11/16/22 | F49: Moss | G49: 448
A50: 46 | D50: Trager - 2021 (21-22 Week 7) | E50: 45276 | F50: Green | G50: 447
A51: 47 | D51: Delaney - 2019 (22-23 Week 12) | E51: 44299 | F51: Kelvin | G51: 447
A52: 48 | D52: Kelley - 2009 (23-24 Week 2) | E52: 2/1/23 | F52: Kelvin | G52: 446
A53: 49 | D53: Logan - 2005 (23-24 Week 6) | E53: 45604 | F53: Jowkar | G53: 444
A54: 50 | E54: 44269 | F54: Kelvin | G54: 444
E55: 11/28/22 | F55: Moss | G55: 443
D56: Kelvin - 18/38 | E56: 45271 | F56: Logan | G56: 443
D57: Logan - 7/38 | E57: 45262 | F57: Kelley | G57: 442
D58: Jowkar - 5/38
D59: Moss - 3/38
D60: Green - 2/38
D61: Trager - 1/38
D62: Delaney - 1/38
D63: Kelley - 1/38
B89: 2022-23 Top Scoring Days
B90: Date | C90: Team | D90: Score
A92: 1 | B92: 3/11/23 | C92: Logan | D92: 510 | F92: Kelvin | G92: =COUNTIF(M14:M66, "Kelvin") -> 0
A93: 2 | B93: 12/14/22 | C93: Kelvin | D93: 501 | F93: Moss | G93: =COUNTIF(M16:M68, "Moss") -> 0
A94: 3 | B94: 1/2/23 | C94: Delaney | D94: 501 | F94: Delaney | G94: =COUNTIF(M18:M70, "Delaney") -> 0
A95: 4 | B95: 1/15/23 | C95: Kelvin | D95: 495 | F95: Trager | G95: =COUNTIF(M20:M72, "Trager") -> 0
A96: 5 | B96: 2/4/23 | C96: Logan | D96: 483 | F96: Logan | G96: =COUNTIF(M17:M69, "Logan") -> 0
A97: 6 | B97: 2/4/23 | C97: Kelvin | D97: 473 | F97: Spencer | G97: =COUNTIF(M16:M68, "spencer") -> 0
A98: 7 | B98: 11/9/22 | C98: Moss | D98: 460 | F98: Jowkar | G98: =COUNTIF(#REF!, "Jowkar") -> 0
A99: 8 | B99: 1/16/23 | C99: Kelvin | D99: 460 | F99: Green | G99: =COUNTIF(#REF!, "Green") -> 0
A100: 9 | B100: 12/23/22 | C100: Kelvin | D100: 458 | F100: Gold | G100: =COUNTIF(M20:M72, "Gold") -> 0
A101: 10 | B101: 11/25/22 | C101: Moss | D101: 453 | F101: Zujewski | G101: =COUNTIF(M19:M71, "Zujewski") -> 0
A102: 11 | B102: 11/16/22 | C102: Moss | D102: 448
A103: 12 | B103: 2/1/23 | C103: Kelvin | D103: 446
A104: 13 | B104: 11/28/22 | C104: Moss | D104: 443
A105: 14 | B105: 1/28/23 | C105: Delaney | D105: 442
A106: 15 | B106: 2/13/23 | C106: Delaney | D106: 442
A107: 16 | B107: 2/10/23 | C107: Kelvin | D107: 441
A108: 17 | B108: 10/31/22 | C108: Delaney | D108: 438
A109: 18 | B109: 11/7/22 | C109: Jowkar | D109: 438
A110: 19 | B110: 12/31/22 | C110: Moss | D110: 438
A111: 20 | B111: 1/4/23 | C111: Kelvin | D111: 435
A112: 21 | B112: 1/16/23 | C112: Moss | D112: 435
A113: 22 | B113: 3/3/23 | C113: Moss | D113: 435
... A137: 46 | B137: 10/21/22 | C137: Moss | D137: 401

Sheet Offseason Schedule
A1: Dynasty/NBA Event 2025 | B1: Date | D1: Dynasty/NBA Event 2024 | E1: Date | G1: Dynasty/NBA Event 2023 | H1: Date | J1: Dynasty/NBA Event 2022 | K1: Date | M1: Dynasty/NBA Event 2021 | N1: Date
A2: End of Championship Round | B2: March 23rd, 2025 | D2: End of Championship Round | E2: March 24th, 2024 | G2: End of Championship Round | H2: March 26th, 2023 | J2: End of Championship Round | K2: April 10th, 2022 | M2: End of Championship Round | N2: May 16th, 2021
A3: Trading Reopens | B3: March 24th, 2025 | D3: Trading Reopens | E3: March 25th, 2024 | G3: Trading Reopens | H3: March 27th, 2023 | J3: Trading Reopens | K3: April 11th, 2022 | M3: Trading Reopens | N3: May 17th, 2021
A4: Free Agency Locks | B4: March 24th, 2025 | D4: Free Agency Locks | E4: March 25th, 2024 | G4: Free Agency Locks | H4: April 9th, 2023 | J4: Dynasty Draft Lottery Free Agency Locks | K4: April 18th, 2022 | M4: Dynasty Draft Lottery Free Agency Locks | N4: May 23rd, 2021
A5: NBA Lottery | B5: May 12th, 2025 | D5: NBA Lottery | E5: May 12th, 2024 | G5: NBA Lottery | H5: May 16th, 2023 | J5: NBA Lottery | K5: May 17th, 2022 | M5: NBA Lottery | N5: June 22nd, 2021
A6: Dynasty Draft Lottery | B6: March 24th, 2025 | D6: Dynasty Draft Lottery | E6: April 15th, 2024 | G6: Dynasty Draft Lottery | J6: NBA Draft | K6: June 23rd, 2022 | M6: League Meeting #1 | N6: Sometime in July
A7: NBA Draft | B7: June 25th, 2025 | D7: NBA Draft | E7: June 26th, 2024 | G7: NBA Draft | H7: June 22rd, 2023 | J7: NBA Summer League | K7: July 7-17th, 2022 | M7: NBA Draft | N7: July 29th, 2021
A8: NBA Free Agency | B8: June 30th, 2025 | D8: NBA Free Agency | E8: June 30th, 2024 | G8: NBA Free Agency | H8: June 30th, 2023 | J8: NBA Free Agency | K8: August 2nd, 2022 | M8: NBA Free Agency | N8: August 2nd, 2021
A9: NBA Summer League | B9: July 10th-20th, 2025 | D9: NBA Summer League | E9: July 12th-22nd, 2024 | G9: NBA Summer League | H9: July 7-17th, 2023 | J9: Keeper Deadline | K9: August 15th, 2022 | M9: NBA Summer League | N9: August 8th - August 17th, 2021
A10: Keeper Deadline | B10: July 19th, 2025 | D10: Keeper Deadline | E10: July 28th, 2024 | G10: Keeper Deadline | H10: July 30th, 2023 | J10: Dynasty Draft League Meeting | M10: Keeper Deadline | N10: August 16th, 2021
A11: Dynasty Draft League Meeting | D11: Dynasty Draft League Meeting | E11: August 4th, 2024 | G11: Dynasty Draft League Meeting | J11: Start of NBA Training Camps | M11: Dynasty Draft League Meeting #2 | N11: August 29th
A12: Dynasty Draft | B12: July 26th, 2025 | D12: Dynasty Draft | E12: August 4th, 2024 (after league meeting) | G12: Start of NBA Training Camps | J12: Start of NBA Season | K12: October 18th, 2022 | M12: Start of NBA Training Camps | N12: September 28th
A13: Start of NBA Training Camps | D13: Start of NBA Training Camps | E13: September 27th, 2024 | G13: Start of NBA Season | H13: October 24th | J13: NBA All Star Game | K13: 44976 | M13: Start of NBA Season | N13: October 19th
A14: Start of NBA Season | D14: Start of NBA Season | E14: October 22nd, 2024 | G14: 16 regular season weeks (?) | J14: 15 Regular season weeks ends
A15: ___ regular season weeks | D15: 15 regular season weeks | E15: October 22nd, 2024 - Feb 10, 2025 | G15: Play-in Round | H15: Feb 12 - 24, 2024 | J15: Play-in Round | K15: Feb 13 - 26, 2023
A16: NBA Cup double week | D16: NBA Cup double week | E16: December 9 -22, 2024 | G16: Semifinals round | H16: Feb 25 - March 10, 2024 | J16: Semifinals round | K16: Feb 27 - March 12, 2023
A17: Play-in Round | D17: Play-in Round | E17: Feb 10 - 23, 2025 | G17: Championship round | H17: March 11 - 24, 2024 | J17: Chamionship round | K17: Mach 13 - 26, 2023
A18: Semifinals round | D18: Semifinals round | E18: Feb 24 - March 9, 2025 | G18: Playoffs end (according to Lloyd) | H18: 45375 | J18: Playoffs end | K18: March 27th, 2023
A19: Championship round | D19: Championship round | E19: March 10 - 23, 2025 | G19: Regular Season End | H19: 45396 | J19: Regular season ends | K19: April 9th, 2023
A20: Regular season ends | D20: Regular season ends
G21: 1 week back in schedule from last year for start of NBA season
A22: Need to be sure I actually do the NBA cup double week (manual on Fantrax) | D22: Added NBA cup double week | G22: Lloyd suggests 3 weeks before season end. We did 2 weeks last year | J22: May need to discuss 1-2 weeks depending on the all-star game and how it falls that year
A23: Considering changing playoffs timing given NBA starts to sit players | D23: 3 days of rest between games this year makes this easier to have as a double week (2 last year)

Sheet Trades - All Time

Sheet 2024
A1: Twin Towers | C1: Ball Don't Lie | E1: Washed Kings | G1: Ice Trae | I1: Logan | J1: 2024 | N1: 2023-24 Fantasy Season | P1: 10/24/23 - 3/24/23 | T1: "The Offseason" : 2024 | V1: (N/A)
A2: 2nd Round Trager (Owns swap rights w/Jowkar 2024 2nd) | E2: 1st Round Green (right to swap with Berke 2024 1st) | N2: KELL Kelley 2028 1st round | O2: FOR | P2: MOSS Kristaps Porzingus | T2: KELL Kelley 2028 FRP, conveys to Kelley 2029 FRP if Kelley 2027 FRP falls 1-3 in 2027 | U2: FOR | V2: MOSS Moss 2025 2nd round
A3: 2nd Round Jowkar (Trager 2024 2nd owns swap rights) (Owns swap rights w/Kelley 2024 2nd) | E3: 1st Round Delaney | N3: KELL Khris Middleton | O3: 45224
E4: 2nd Round Delaney | N4: KELL Jakob Poeltl | T4: KELL Desmond Bane | U4: FOR | V4: TRAG Trager 2024 1st round
U5: 45469 | V5: TRAG Kelley 2026 1st round
N6: PETE Coby White | O6: FOR | P6: TRAG Delaney 2025 2nd round | V6: TRAG Gold 2025 2nd round
A7: 2024 | O7: 45225
A8: No Shaime | C8: Pure Sweat Fam | E8: BK's Whoppers | G8: Droppin Dimes | I8: Only Franz | T8: DELA Jaylen Brown | U8: FOR | V8: ZJEW Jaime Jaquez
A9: 1st Round Gold (right to swap with Kelley 2024 1st) | C9: 1st Round Peterson | E9: 1st Round Trager | G9: 2nd Round Kelley (Jowkar 2024 2nd owns swap rights) | I9: 1st Round Zujewski | N9: MOSS De'Aaron Fox | O9: FOR | P9: KELL CJ McCollum | T9: DELA Cam Johnson | U9: 45475 | V9: ZJEW Taylor Hendricks
C10: 1st Round Moss*^ | E10: 1st Round Jowkar | G10: 2nd Round Moss | I10: 2nd Round Zujewski | N10: MOSS Bam Adebayo | O10: 45244 | P10: KELL Jonas Valanciunas | V10: ZJEW Delaney 2026 1st round
E11: 1st Round Berke (1st round Green owns swap rights) | I11: 2nd Round Peterson | N11: MOSS Myles Turner | P11: KELL Dario Saric | V11: ZJEW Delaney 2024 2nd round (#16 overall)
E12: 1st Round Kelley (Gold 2024 1st owns swap rights) | N12: MOSS Rudy Gobert | P12: KELL Nicolas Batum | V12: ZJEW Zujewski 2025 2nd round
E13: 2nd Round Green | N13: MOSS Russell Westbrook | P13: KELL Bismack Biyombo
E14: 2nd Round Berke | P14: KELL Jowkar 2024 1st round | T14: PETE Mitchell Robinson | U14: FOR | V14: KELL Clint Capela
E15: 2nd Round Gold | H15: Protected Pick | P15: KELL Kelley 2024 1st round | T15: PETE Berke 2026 2nd round | U15: 45496 | V15: KELL Moss 2024 2nd round (#13 overall)
A16: Draft Pick Protections | H16: Locked Pick- Future Protection/swap | P16: KELL Berke 2024 1st round | T16: PETE Green 2024 2od round (#17 overall)
A17: * top 3 protected - conveys to (locked) pete 2024 frp or moss 2025 frp | H17: Swap rights | P17: KELL Kelley 2025 1st round
A18: ^ swap rights to Pete 2024 FRP | P18: KELL Green 2025 1st round | T18: TRAG Darius Garland | U18: FOR | V18: DELA Devin Booker
I19: Week | J19: 1st | K19: MOV | L19: 2nd | P19: KELL Berke 2024 2nd round | T19: TRAG Keegan Murray | U19: 45498 | V19: DELA Kelley 2024 2nd round (#15 overall)
A20: Kelley receives #11 overall in this draft as a compensatory pick per summer 2023 new owner negotiations | I20: 1 | J20: Kelvin | K20: 309 | L20: Logan | P20: KELL Moss 2024 2nd round | T20: TRAG Delaney 2024 1st round (#6 overall) | V20: DELA Zujewski 2025 2nd round
A21: Kelley has lost #11 overall in this drast as a compensatory pick per league tanking policy | I21: 2 | J21: Kelvin | K21: 34 | L21: Green | T21: TRAG Peterson 2025 1st round right to swap w/Berke 2025 1st round
I22: 3 | J22: Jowkar | K22: 75 | L22: Green | N22: BERK Shai Gilgeous-Alexander | O22: FOR | P22: DELA Kevin Durant | T22: TRAG Lonzo Ball
A23: 2024 Draft Order: | C23: 1st Rd Owner (Rookies) | E23: 2nd Rd Owner (Rookie & FA) | G23: 3rd Rd Owner Comp Round | I23: 4 | J23: Logan | K23: 247 | L23: Kelley | N23: BERK Berke 2028 1st round | O23: 45246 | P23: DELA Demar Derozan
A24: #1: Lottery #1 (40% Gold) | C24: Gold | E24: Kelley | G24: Gold | I24: 5 | J24: Green | K24: 4 | L24: Kelvin | P24: DELA James Harden | T24: KELL Jerami Grant | U24: FOR | V24: JOWK Daniel Gafford
A25: #2: Lottery #2 (30% Zujewski) | C25: Zujewski | E25: Zujewski | G25: Zujewski | I25: 6 | J25: Logan | K25: 236 | L25: Jowkar | P25: DELA Kyrie Irving | T25: KELL Moss 2025 2nd round | U25: 45501
A26: #3: Lottery #3 (20% Moss) | C26: Moss | E26: Peterson | G26: Moss | I26: 7 | J26: Logan | K26: 18 | L26: Kelvin
A27: #4: Lottery #4 (10% Trager) | C27: Kelley | E27: Trager | G27: Trager | I27: 8 | J27: Kelvin | K27: =2322-2121 -> 201 | L27: Jowkar | N27: DELA Bradley Beal | O27: FOR | P27: PETE Peterson 2025 1st round | T27: August 4th 2024
A28: #5: Kelley | C28: Kelley | E28: Trager | G28: Kelley | I28: 9 | J28: Kelvin | K28: =2048-1884 -> 164 | L28: Jowkar | N28: DELA Terry Rozier | O28: 45246 | P28: PETE Peterson 2026 1st round | T28: / / / / / / / / / Draft Day 2024 / / / / / / / / /
A29: #6: Delaney | C29: Delaney | E29: Delaney | G29: Delaney | I29: 10 | J29: Kelvin | K29: =2256-2082 -> 174 | L29: Jowkar | P29: PETE Peterson 2027 1st round
A30: #7: Green | C30: Delaney | E30: Kelley | G30: Green | I30: 11 | J30: Kelvin | K30: =2128-2063 -> 65 | L30: Jowkar | T30: JOWK Donte Divincenzo | U30: FOR | V30: BERK Berke 2029 2nd round
A31: #8: Berke | C31: Kelley | E31: Kelley | G31: Berke | I31: 12 | J31: Kelvin | K31: =2437-1858 -> 579 | L31: Jowkar | N31: DELA Kyle Kuzma | O31: FOR | P31: GREEN Dyson Daniels
A32: #9: Jowkar | C32: Kelley | E32: Peterson | G32: Jowkar | I32: 13 | J32: Kelvin | K32: =2127-1885 -> 242 | L32: Green | N32: DELA Spencer Dinwiddie | O32: 45260 | P32: GREEN Jeremy Sochan | T32: DELA Delaney 2024 1st round (#6 overall) | U32: FOR | V32: KELL Kelley 2024 1st round (#5 overall)
A33: #10: Kelvin | C33: Moss | E33: Zujewski | G33: Kelvin | I33: 14 | J33: Jowkar | K33: =2078-2035 -> 43 | L33: Kelvin | P33: GREEN Green 2026 1st round | T33: DELA Green 2024 1st round (#7 overall) | U33: 45509 | V33: KELL Berke 2024 1st round (#8 overall)
I34: 15 | J34: Jowkar | K34: =2267-2206 -> 61 | L34: Logan | P34: GREEN Green 2025 2nd round | T34: DELA Green 2027 2nd round
I35: 16 | J35: Kelvin | K35: =2201-1850 -> 351 | L35: Jowkar | P35: GREEN Green 2027 2nd round
T36: PETE Clint Capela | U36: FOR | V36: BERK Kawhi Leonard
N37: DELA Klay Thompson | O37: FOR | P37: JOWK Luguentz Dort | T37: PETE Bradley Beal | U37: 45509 | V37: BERK Berke 2029 1st round
A38: Punishments: | I38: 1st place finishes | K38: 2nd place finishes | O38: 45279 | P38: JOWK Green 2026 2nd round | T38: PETE Jrue Holiday
A39: Strike 1: | B39: ! | C39: Warning | I39: Logan | J39: =COUNTIF($J$20:$J$37, I39) -> 3 | K39: Logan | L39: =COUNTIF($L$20:$L$37,K39) -> 2
A40: Strike 2: | B40: !! | C40: Warning #2 | I40: Kelvin | J40: =COUNTIF($J$20:$J$37, I40) -> 9 | K40: Kelvin | L40: =COUNTIF($L$20:$L$37,K40) -> 3 | N40: DELA Shai Gilgeous-Alexander | O40: FOR | P40: GOLD Devin Booker | T40: DELA Delaney 2024 2nd round (#16 overall) | U40: FOR | V40: TRAG Trager 2024 2nd round (#14 overall)
A41: Strike 3: | B41: !!! | C41: Lose furthest out SRP (if you do not own your furthest out one, yours will be preemptively taken for the next available year) | I41: Trager | J41: =COUNTIF($J$20:$J$37, I41) -> 0 | K41: Trager | L41: =COUNTIF($L$20:$L$37,K41) -> 0 | O41: 45282 | P41: GOLD Jaylen Brown | T41: DELA Jowkar 2026 2nd round | U41: 45510
A42: Strike 4: | B42: !!!! | C42: Pick is dropped to #5 and out of the lottery (last of non-playoff teams) if pick is owned by violater | I42: Green | J42: =COUNTIF($J$20:$J$37, I42) -> 1 | K42: Green | L42: =COUNTIF($L$20:$L$37,K42) -> 3 | P42: GOLD Josh Giddey
I43: Delaney | J43: =COUNTIF($J$20:$J$37, I43) -> 0 | K43: Delaney | L43: =COUNTIF($L$20:$L$37,K43) -> 0 | P43: GOLD Green 2024 1st round
A44: Date of Violation: | C44: Violation: | I44: Moss | J44: =COUNTIF($J$20:$J$37, I44) -> 0 | K44: Moss | L44: =COUNTIF($L$20:$L$37,K44) -> 0
A45: 45249 | B45: ! | C45: Moss didn't set lineup on Sunday of a close matchup | I45: Zujewski | J45: =COUNTIF($J$20:$J$37, I45) -> 0 | K45: Zujewski | L45: =COUNTIF($L$20:$L$37,K45) -> 0 | N45: PETE Brandon Podziemski | O45: FOR | P45: JOWK Jowkar 2026 1st round
A46: 45310 | B46: ! | C46: Kelley didn't set his lineup 2 days in a row | I46: Gold | J46: =COUNTIF($J$20:$J$37, I46) -> 0 | K46: Gold | L46: =COUNTIF($L$20:$L$37,K46) -> 0 | O46: 45290 | P46: JOWK Jowkar 2025 2nd round
A47: 45330 | B47: !! | C47: Kelley didn't set his lineup 2 days in a row | I47: Kelley | J47: =COUNTIF($J$20:$J$37, I47) -> 0 | K47: Kelley | L47: =COUNTIF($L$20:$L$37,K47) -> 1
A48: 45332 | B48: !!! | C48: Kelley didn't set his lineup for the 3rd day in a week after already getting a strike | I48: Jowkar | J48: =COUNTIF($J$20:$J$37, I48) -> 3 | K48: Jowkar | L48: =COUNTIF($L$20:$L$37,K48) -> 7 | N48: PETE Jusuf Nurkic | O48: FOR | P48: BERK Kyrie Irving
N49: PETE Nikola Vucevic | O49: 45297 | P49: BERK Kelley 2024 2nd round
A51: G-league: | C51: 1st - Oct 23rd 2023 | E51: 2nd - Nov 19th 2023 | G51: 3rd - Dec 17th 2023 | I51: 4th - Jan 14th, 2024 | J51: 5th - Feb 11th, 2024 | N51: DELA Draymond Green | O51: FOR | P51: PETE Jowkar 2024 2nd round
A52: Trager | C52: Leonard Miller | E52: Leonard Miller | G52: Leonard Miller | I52: Leonard Miller | J52: Leonard Miller | O52: 45297
C53: Brice Sensabaugh | E53: Trayce Jackson-Davis | G53: Brice Sensabaugh | I53: Brice Sensabaugh | J53: Brice Sensabaugh
A54: Jowkar | C54: Nikola Jovic | E54: Nikola Jovic | G54: Nikola Jovic | I54: Nikola Jovic | J54: Nikola Jovic | N54: DELA Bojan Bogdanovic | O54: FOR | P54: BERK De'Andre Hunter
C55: Peyton Watson | E55: Peyton Watson | G55: Peyton Watson | I55: Peyton Watson | J55: Peyton Watson | N55: DELA Mike Conley | O55: 45326 | P55: BERK Berke 2025 2nd round
A56: Delaney | C56: Cason Wallace | E56: Cason Wallace | G56: Cason Wallace | I56: Cason Wallace | J56: Cason Wallace | N56: DELA Chris Paul | P56: BERK Berke 2028 2nd round
C57: Jarace Walker | E57: Jarace Walker | G57: Jarace Walker | I57: Jarace Walker | J57: Jarace Walker
A58: Green | C58: Dyson Daniels | E58: GG Jackson | G58: GG Jackson | I58: Kobe Bufkin | J58: Kobe Bufkin | N58: DELA Tyus Jones | O58: FOR | P58: PETE Delaney 2025 2nd round
C59: Kobe Bufkin | E59: Jaden Springer | G59: Jaden Springer | I59: GG Jackson | J59: Julian Champagnie | O59: 45330 | P59: PETE Jowkar 2024 2nd round right to swap with Kelley 2024 2nd round
A60: Berke | C60: Jett Howard | E60: Jett Howard | G60: Jett Howard | I60: Jett Howard | J60: Jett Howard
C61: James Nnaji | E61: James Nnaji | G61: James Nnaji | I61: Miles McBride | J61: Miles McBride | N61: DELA Berke 2028 2nd round | O61: FOR | P61: JOWK Saddiq Bey
A62: Gold | C62: BJ Boston | E62: BJ Boston | G62: BJ Boston | I62: BJ Boston | J62: BJ Boston | O62: 45332 | P62: JOWK Zach Collins
C63: Emoni Bates | E63: Emoni Bates | G63: Emoni Bates | I63: Emoni Bates | J63: Emoni Bates
A64: Moss | C64: Malaki Branham | E64: Malaki Branham | G64: Malaki Branham | I64: Malaki Branham | J64: Malaki Branham | N64: KELL De'Aaron Fox | O64: FOR | P64: MOSS Jonas Valanciunas
C65: Paul Reed | E65: Paul Reed | G65: Paul Reed | I65: Paul Reed | J65: Paul Reed | N65: KELL Bam Adebayo | O65: 45333 | P65: MOSS Isaiah Jackson
A66: Kelley | C66: Gradey Dick | E66: Gradey Dick | G66: Gradey Dick | I66: Gradey Dick | J66: Gradey Dick | N66: KELL Myles Turner | P66: MOSS Jared Vanderbilt
C67: Noah Clowney | E67: Noah Clowney | G67: Jordan Hawkins | I67: Jordan Hawkins | J67: Jordan Hawkins | N67: KELL Rudy Gobert | P67: MOSS Jowkar 2024 1st round
A68: Peterson | C68: Bones Hyland | E68: Bones Hyland | G68: Bones Hyland | I68: Ziaire Williams | J68: Corey Kispert | N68: KELL Kelley 2026 2nd round | P68: MOSS Kelley 2024 1st round
C69: Brandin Podziemski | E69: Brandin Podziemski | G69: Brandin Podziemski | I69: Ayo Dosunmu | J69: Ayo Dosunmu | P69: MOSS Berke 2024 1st round
A70: Zujewski | C70: Keyonte George | E70: Ochai Agbaji | G70: Ochai Agbaji | I70: Ochai Agbaji | J70: Marcus Sasser | P70: MOSS Kelley 2025 1st round
C71: Taylor Hendricks | E71: Taylor Hendricks | G71: Taylor Hendricks | I71: Taylor Hendricks | J71: Taylor Hendricks | P71: MOSS Green 2025 1st round
P72: MOSS Moss 2028 1st round
P73: MOSS Kelle 2027 FRP right to swap w/Moss 2027 FRP
A74: 2024 Rookie Draft Recap: August 6th, 2024 | P74: MOSS Berke 2024 2nd round
A75: Round 1 (Just Rookies) | D75: Round 2 (FA & Rookies) | H75: Round 3 (Compensatory) | P75: MOSS Moss 2024 2nd round
A76: #1: Gold: Reed Sheppard | D76: #1: Kelley: Rob Dillingham | H76: #1: Gold: | P76: MOSS Moss 2025 2nd round
A77: #2: Zujewski: Stephon Castle | D77: #2: Zujewski: Kel'El Ware | H77: #2: Zujewski: | P77: MOSS Moss 2028 2nd round
A78: #3: Moss: Donovan Clingan | D78: #3: Kelvin: Devin Carter | H78: #3: Moss:
A79: #4: Kelley: Zach Edey | D79: #4: Delaney: Cody Williams | H79: #4: Trager: | N79: KELL D'Angelo Russell | O79: FOR | P79: JOWK Marvin Bagley
A80: #5: Delaney: Alex Sarr | D80: #5: Trager: Tidjane Salaun | H80: #5: Kelley: | N80: KELL Zach Lavine | O80: 45333 | P80: JOWK Klay Thompson
A81: #6: Kelley: Matas Buzelis | D81: #6: Trager: Yves Missi | H81: #6: Delaney: | P81: JOWK Jowkar 2025 1st round
A82: #7: Kelley: Carlton "Bub" Carrington | D82: #7: Kelley: Isaiah Collier | H82: #7: Green: | P82: JOWK Jowkar 2027 1st round
A83: #8: Delaney: Nikola Topic | D83: #8: Kelley: Dalton Knecht | H83: #8: Berke: | P83: JOWK Gold 2024 2nd round
A84: #9: Kelley: Zaccharie Risacher | D84: #9: Kelvin: Kelly Oubre | H84: #9: Jowkar: | P84: JOWK Moss 2027 2nd round
A85: #10: Moss: Ron Holland | D85: #10: Zujewski: Terrence Shannon Jr. | H85: #10: Kelvin:
N86: Drops from 7/29/24 Keeper Deadline:
A88: IR Eligible players for 2024 offseason | N88: Isaac Okoro | P88: Isaiah Stewart | R88: Tre Jones | T88: Marcus Sasser
N89: Rui Hachimura | P89: Tre Mann | R89: Bruce Brown | T89: Markelle Fultz
A90: Kristaps Porzingus | N90: Jake Laravia | R90: Jordan Clarkson
A91: Devin Carter | N91: Dalano Banton | P91: Kyle Lowry | R91: Brandon Clarke
A92: Nikola Topic | N92: Tristan Vukcevic | P92: Sam Hauser | R92: Richaun Holmes
A93: Lonzo Ball | R93: Malaki Branham
A94: Saddiq Bey | N94: Malcolm Brogdon | P94: TJ McConnell
A95: DaRon Holmes II | N95: Russell Westbrook | P95: Lugentz Dort | R95: Quentin Grimes
A96: Ben Simmons | N96: Kelly Oubre Jr. | P96: Kelly Olynyk | R96: Kevin Huerter
N97: Jarred Vanderbilt | P97: Toumani Camara | R97: Vince Williams
A98: Round 3 (Compensatory) | E98: Round 4 (Compensatory) | I98: Round 5 (Compensatory) | N98: Dennis Schroder | R98: Brice Sensabaugh
A99: #1: Gold: Kyle Filipowski | E99: #9: Gold: Jakobe Walter | I99: #13: Gold: Dillon Jones | N99: Caris Levert | P99: Talen Horten-Tucker
P100: Ousmane Dieng | R100: Ayo Dosumnu
A101: #2: Moss: Jared McCain | N101: Marjon Beauchamp | P101: Lonnie Walker | R101: Corey Kispert
A102: #3: Trager: Ayo Dosumnu | N102: James Wiseman | P102: Olivier-Maxence Prosper | R102: Nickeil Alexander-Walker
...

Sheet 2023
A1: uce | C1: Jowkar (!) | E1: Delaney (!) | G1: Green | I1: Berke | J1: 2023 | N1: 2022-23 Fantasy Season | P1: 10/18/22 - 2/12/23 | T1: "The Offseason" : 2023 | V1: 2/13/23 - 8/14/23 | X1: 2023 Drops
A2: 1st Round Trager | C2: 1st Round Jowkar | E2: 1st Round Berke | G2: 1st Round Green | I2: 2nd Round Moss | N2: DELA Peterson 2025 1st Round | O2: FOR | P2: JOWK Klay Thompson | R2: 18 Regular Season Trades | T2: KELL Karl Anthony-Towns | U2: FOR | V2: JOWK Michael Porter Jr.
A3: 1st Round Vlandis* (Delaney 2023 1st owns swap rights) | C3: 2nd Round Vlandis | E3: 2nd Round Green | G3: 1st Round Peterson | N3: DELA Jowkar 2023 2nd Round | T3: KELL Jusuf Nurkic | V3: JOWK Cam Thomas | X3: Norman Powell | Y3: Isaac Okoro | Z3: Keon Johnson
A4: 1st Round Zujewski | C4: 2nd Round Gold | G4: 1st Round Delaney** (Right to swap with Vlandis 2023 1st) | V4: JOWK Kris Dunn | X4: TJ McConnell | Y4: Marcus Morris
A5: 2nd Round Zujewski | N5: HALE Brandom Ingram | O5: FOR | P5: BERK Green 2024 1st Round | V5: JOWK Jowkar 2024 1st round | X5: Drew Eubanks | Y5: Christian Koloko | Z5: Larry Nance
N6: HALE Berke 2025 2nd Round | P6: BERK Berke 2026 1st Round | V6: JOWK Berke 2025 1st round | X6: Nick Richard’s | Y6: Brandon Clarke | Z6: Royce O’neale
A7: 2023 (Year III) | P7: BERK Berke 2027 1st Round | V7: JOWK Gold 2026 2nd round | X7: Aaron Nesmith
A8: Gold (!) | C8: Moss | E8: Vlandis | G8: Peterson | I8: Zujewski (!) | V8: JOWK Kelley 2027 2nd round | Z8: JRE
A9: 1st Round Moss | C9: 1st Round Gold | E9: 2nd Round Delaney | G9: 2nd Round Berke | I9: 2nd Round Trager | N9: PETE Paul George | O9: FOR | P9: BERK Dejounte Murray | X9: Ziaire Williams
I10: 2nd Round Jowkar | N10: PETE Jimmy Butler | P10: BERK Jrue Holiday | T10: DELA Pascal Siakam | U10: FOR | V10: JOWK Berke 2023 1st round (#6 overall) | X10: Malik Beasley | Y10: Killian Hayes | Z10: NAW
I11: 2nd Round Peterson | N11: PETE Tobias Harris | P11: BERK Bones Hyland | V11: JOWK Peterson 2025 1st round | X11: Blake Wesley | Y11: Jonathan Isaac
P12: BERK Collin Sexton | V12: JOWK Jowkar 2023 2nd round (#13 overall) | X12: Ochai Agbaji | Y12: Isaiah Jackson | Z12: Marvin Bagley (Bagels)
V13: JOWK Moses Moody | X13: Jordan Nowara
A14: Draft Pick Protections | N14: PETE Jarred Vanderbilt | O14: FOR | P14: GREEN Nicolas Claxton | X14: Jalen Smith | Y14: Josh Richardson | Z14: Isaiah Hartenstein
H15: Protected Pick | T15: TRAG John Collins | U15: FOR | V15: DELA Peterson 2025 1st round | X15: John Wall
A16: * Swap rights w/Delaney FRP, swap if Vlandis FRP is higher pick | H16: Locked Pick- Future Protection | N16: GOLD Kristaps Porzingis | O16: FOR | P16: MOSS Moss 2023 1st round | T16: TRAG Green 2023 2nd round (#14 overall) | V16: DELA Jowkar 2023 2nd round (#13 overall) | Y16: Lu Dort
A17: ** Swap rights w/Vlandis FRP, swap if Vlandis FRP is higher pick | H17: Green (*) - Conveyed from past protection | P17: MOSS Vlandis 2024 1st round | X17: Jevon Carter | Y17: Santi Aldama
P18: MOSS Moss 2024 2nd round | T18: PETE Nicholas Claxton | U18: FOR | V18: TRAG Peterson 2025 1st round | X18: John Konchar | Y18: Bol Bol
I19: Week | J19: 1st | K19: MOV | L19: 2nd | T19: PETE Delaney 2025 2nd round | V19: TRAG Trager 2026 1st round | X19: Mo Wagner | Y19: Jalen McDaniels
A20: 2023 Draft Order: | C20: 1st Rd Owner | E20: 2nd Rd Owner | G20: 3rd Rd Owner Compensatory Round | I20: 1 | J20: Delaney | K20: 41 | L20: Kelvin | N20: JOWK De'Andre Hunter | O20: FOR | P20: VLAND Vlandis 2027 2nd round | V20: TRAG Kelley 2023 2nd round (#19 overall) | X20: Saddiq Bey | Y20: Isaiah Joe
A21: #1: Lottery #1 (40% Trager) | C21: Jowkar | E21: Trager | G21: Trager | I21: 2 | J21: Delaney | K21: 32 | L21: Kelvin | X21: Doug McDermott | Y21: Tyty Washington
A22: #2: Lottery #2 (30% Jowkar) | C22: Green | E22: Trager | G22: Jowkar | I22: 3 | J22: Delaney | K22: 93 | L22: Kelvin | N22: MOSS Brandon Clarke | O22: FOR | P22: GOLD Kyle Anderson | T22: PETE Derrick White | U22: FOR | V22: JOWK Jusuf Nurkic | X22: Davion Mitchell
A23: #3: Lottery #3 (30% Green) | C23: Trager | E23: Delaney | G23: Green | I23: 4 | J23: Moss | K23: 225 | L23: Kelvin | T23: PETE Kelley 2023 2nd round (#19 overall) | V23: JOWK Berke 2023 2nd round (#17 overall) | X23: Corey Kispert | Y23: Dillon Brooks
A24: #4 Gold | C24: Moss | E24: Kelley | G24: Gold | I24: 5 | J24: Kelvin | K24: 80 | L24: Moss | N24: HALE Marcus Smart | O24: FOR | P24: PETE Green 2023 2nd round | Y24: Jaylen Nowell
A25: #5: Zujewski | C25: Zujewski | E25: Trager | G25: Zujewski | I25: 6 | J25: Moss | K25: 222 | L25: Kelvin | N25: HALE Will Barton | P25: PETE Jowkar 2024 2nd round swap rights (connected to Trager 2024 SRP) | T25: GOLD Kyle Kuzma | U25: FOR | V25: DELA Green 2024 1st round | X25: Caleb Martin | Y25: Chris Duarte
A26: #6: Berke | C26: Delaney | E26: Peterson | G26: Berke | I26: 7 | J26: Kelvin | K26: 157 | L26: Green | T26: GOLD Tyus Jones | V26: DELA Green 2023 2nd round (#14 overall) | X26: Trey Lyles | Y26: Darius Bazley
A27: #7: Delaney | C27: Kelley | E27: Green | G27: Delaney | I27: 8 | J27: Moss | K27: 157 | L27: Kelvin | N27: Kelvin Receives | P27: Trager Receives | R27: Jowkar Receives | T27: GOLD Cole Anthony | X27: Tre Mann | Y27: Xavier Tillman
A28: #8: Vlandis/Kelley | C28: Trager | E28: Jowkar | G28: Kelley | I28: 9 | J28: Kelvin | K28: 107 | L28: Moss | N28: JOWK Buddy Hield | P28: PETE KJ Martin | R28: PETE Berke 2023 2nd round
A29: #9: Moss | C29: Gold | E29: Berke | G29: Moss | I29: 10 | J29: Kelvin | K29: 254 | L29: Delaney | R29: HALE Green 2026 2nd round | T29: Kelley Receives | V29: Gold Recieves | X29: Green receives | Z29: Trager receives
A30: #10: Kelvin | C30: Kelley | E30: Zujewski | G30: Kelvin | I30: 11 | J30: Moss | K30: 122 | L30: Kelvin | T30: GREEN Mikal Bridges | V30: GREEN Jalen Duren | X30: KELL Jalen Brunson | Z30: KELL Berke 2025 1st round
A31: #11: Compensatory | C31: Kelley | I31: 12 | J31: Kelvin | K31: 397 | L31: Delaney | N31: VLAND Gold 2023 2nd round | O31: FOR | P31: BERK Kelly Oubre Jr. | T31: GREEN Delaney 2023 1st round (#7 overall) | V31: KELL Green 2024 1st round receives right to swap with Berke 2024 1st round | X31: KELL Donovan Mitchell | Z31: KELL swap rights to Kelley 2027 1st round (connected to Trager 2027 1st round, top 3 protected, convey to Kelley 2028 1st round)
I32: 13 | J32: Kelvin | K32: 326 | L32: Spencer | N32: VLAND Moss 2023 2nd round | T32: GREEN Peterson 2023 1st round (#10 overall) | V32: KELL Gold 2024 1st round receives right to swap with Kelley 2024 1st round | X32: KELL Delaney 2023 2nd round (#18 overall)
I33: 14 | J33: Kelvin | K33: 507 | L33: Trager | N33: VLAND De'Andre Hunter | T33: GREEN Berke 2024 1st round
I34: 15 | J34: Kelvin | K34: 271 | L34: Delaney | T34: GOLD Kelley 2024 1st round
I35: 16 | J35: Kelvin | K35: 459 | L35: Logan | N35: DELA Vlandis 2026 1st round | O35: FOR | P35: HALE Green 2024 1st round | T35: GOLD Moss 2024 2nd round
I36: 17 | J36: Kelvin | K36: 534 | L36: Delaney | P36: HALE Jowkar 2026 2nd round | T36: TRAG Kelley 2025 1st round
P37: HALE Trager 2026 2nd round | T37: GREEN Green 2025 1st round
T38: GREEN rescinds top 1 protection of 2024 1st round pick, allows Green 2025 1st round to be traded
A39: Punishments: | I39: 1st place finishes | K39: 2nd place finishes | N39: DELA Wendall Carter Jr. | O39: FOR | P39: ZJEW Kyrie Irving
A40: Strike 1: | B40: ! | C40: Warning | I40: Logan | J40: =COUNTIF($J$20:$J$37, I40) -> 0 | K40: Logan | L40: =COUNTIF($L$20:$L$37,K40) -> 1 | N40: DELA Dennis Smith Jr. | T40: GOLD Cam Johnson | U40: FOR | V40: DELA Delaney 2027 1st round
A41: Strike 2: | B41: !! | C41: Warning #2 | I41: Kelvin | J41: =COUNTIF($J$20:$J$37, I41) -> 10 | K41: Kelvin | L41: =COUNTIF($L$20:$L$37,K41) -> 7 | N41: DELA Delaney 2026 1st round | T41: GOLD Green 2023 2nd round (#14 overall)
A42: Strike 3: | B42: !!! | C42: Lose furthest out SRP (if you do not own your furthest out one, yours will be preemptively taken for the next available year) | I42: Trager | J42: =COUNTIF($J$20:$J$37, I42) -> 0 | K42: Trager | L42: =COUNTIF($L$20:$L$37,K42) -> 1
A43: Strike 4: | B43: !!!! | C43: Pick is dropped to #5 and out of the lottery (last of non-playoff teams) if pick is owned by violater | I43: Green | J43: =COUNTIF($J$20:$J$37, I43) -> 0 | K43: Green | L43: =COUNTIF($L$20:$L$37,K43) -> 1 | N43: BERK Delaney 2024 1st round | O43: FOR | P43: ZJEW Kawhi Leonard | T43: August 13th 2023
I44: Delaney | J44: =COUNTIF($J$20:$J$37, I44) -> 3 | K44: Delaney | L44: =COUNTIF($L$20:$L$37,K44) -> 4 | N44: BERK Moss 2024 1st round | T44: / / / / / / / / / Draft Day 2023 / / / / / / / / /
A45: Date of Violation: | C45: Violation: | I45: Moss | J45: =COUNTIF($J$20:$J$37, I45) -> 4 | K45: Moss | L45: =COUNTIF($L$20:$L$37,K45) -> 2
A46: 44899 | C46: Jowkar benched Jaden Ivey over Jericho Sims AND Cam Reddish | I46: Zujewski | J46: =COUNTIF($J$20:$J$37, I46) -> 0 | K46: Zujewski | L46: =COUNTIF($L$20:$L$37,K46) -> 0 | N46: PETE Jaren Jackson Jr | O46: FOR | P46: ZJEW Anthony Davis | T46: KELL Cam Whitmore | U46: FOR | V46: JOWK Gold 2023 2nd round (#15 overall)
A47: 44922 | C47: Zujewski benched Jalen Williams over Chris Duarte AND Romeo Langford | I47: Gold | J47: =COUNTIF($J$20:$J$37, I47) -> 0 | K47: Gold | L47: =COUNTIF($L$20:$L$37,K47) -> 0 | N47: PETE Moss 2026 1st round | P47: ZJEW Josh Hart | V47: JOWK Moss 2026 2nd round
A48: 44931 | C48: Gold benched Paolo Banchero over Christian Koloko AND Precious Achiuwa | I48: Vlandis | J48: =COUNTIF($J$20:$J$37, I48) -> 0 | K48: Vlandis | L48: =COUNTIF($L$20:$L$37,K48) -> 0 | N48: PETE Peterson 2023 2nd round | P48: ZJEW Zujewski 2026 2nd round | V48: JOWK Jowkar 2027 2nd round
A49: 1/14/23 & 1/15/23 | C49: Delaney didn't set lineup consecutive weekend days | I49: Jowkar | J49: =COUNTIF($J$20:$J$37, I49) -> 0 | K49: Jowkar | L49: =COUNTIF($L$20:$L$37,K49) -> 0 | N49: PETE Delaney 2024 2nd round | P49: ZJEW Zujewski 2027 2nd round
T50: JOWK Cam Whitmore | U50: FOR | V50: GOLD Delaney 2027 1st round
N51: BERK Gold 2023 2nd round | O51: FOR | P51: JOWK Donte DiVincenzo | V51: GOLD Gold 2027 2nd round
A52: G-league: | C52: 1st call up - Oct 17th 2022 | E52: 2nd call up - Nov 20th 2022 | G52: 3rd call up - Jan 1st 2023 | I52: 4th call up - Feb 12th 2023 | P52: JOWK Cam Reddish | V52: GOLD Gold 2028 2nd round
A53: Trager | C53: Tyty Washington | E53: Tyty Washington | G53: Tyty Washington | I53: Tyty Washington
C54: Mark Williams | E54: Mark Williams | G54: Mark Williams | I54: Mark Williams | N54: BERK Jordan Clarkson | O54: FOR | P54: JOWK Mo Bamba | T54: TRAG Deandre Ayton | U54: FOR | V54: ZJEW Ausar Thompson
A55: Jowkar | C55: Blake Wesley | E55: Walker Kessler | G55: Walker Kessler | I55: Walker Kessler | T55: TRAG Taylor Hendricks | V55: ZJEW Delaney 2024 1st round
C56: Jalen Johnson | E56: Nikola Jovic | G56: Nikola Jovic | I56: Nikola Jovic | N56: JOWK Jordan Clarkson | O56: FOR | P56: MOSS Moss 2026 2nd round | T56: TRAG Keyonte George | V56: ZJEW Zujewski 2023 2nd round (#15 overall)
A57: Delaney | C57: Tre Mann | E57: Tre Mann | G57: Tre Mann | P57: MOSS Moss 2027 2nd round | T57: TRAG Trager 2025 2nd round
C58: Nickeil Alexander-Walker | E58: Nickeil Alexander-Walker | G58: Nickeil Alexander-Walker
A59: Green | C59: Killian Hayes | E59: Dalen Terry | G59: Isaiah Jackson | N59: BERK Tobias Harris | O59: FOR | P59: Josh Hart
C60: Onyeka Okongwu | E60: Onyeka Okongwu | G60: Patrick Williams | N60: BERK Berke 2026 2nd round | P60: Harrison Barnes
A61: Berke | C61: James Bouknight | E61: James Bouknight | G61: James Bouknight | I61: De'Andre Hunter | N61: BERK Berke 2027 2nd round
C62: Johnny Davis | E62: Johnny Davis | G62: Johnny Davis | I62: Cam Reddish | N62: BERK swap rights to Berke 2025 2nd round (connected to Peterson 2025 2nd round)
A63: Gold | C63: MarJon Beauchamp | E63: Jaden Hardy | G63: Jaden Hardy
C64: BJ Boston | E64: BJ Boston | G64: BJ Boston
A65: Moss | C65: Malaki Branham | E65: Malaki Branham | G65: Malaki Branham
C66: Paul Reed | E66: Paul Reed | G66: Paul Reed
A67: Vlandis | C67: Jake LaRavia | E67: Jake LaRavia | G67: Corey Kispert
C68: Obi Toppin | E68: Obi Toppin | G68: Davion Mitchell
A69: Peterson | C69: Talen Horton-Tucker | E69: Talen Horton-Tucker | G69: Bones Hyland | I69: Bones Hyland
C70: Kenyon Martin | E70: Chuma Okeke | G70: Aaron Nesmith | I70: Aaron Nesmith
A71: Zujewski | C71: Keon Johnson | E71: Keon Johnson | G71: Keon Johnson
C72: Ousmane Dieng | E72: Ousmane Dieng | G72: Ousmane Dieng
A75: 2023 Rookie Draft Recap: August 13th, 2023
A76: Round 1 (Just Rookies) | D76: Round 2 (FA & Rookies) | H76: Round 3 (Compensatory)
A77: #1: Jowkar: Victor Wembenyama | D77: #1: Trager: Taylor Hendricks -> Traded to Zujewski | H77: #1: Trager: Lonzo to IR -> Brice Sensabaugh
A78: #2: Green: Scoot Henderson | D78: #2: Trager: Keyonte George -> Traded to Zujewski | H78: #2: Jowkar: Lamelo to IR -> Peyton Watson
A79: #3: Trager: Amen Thompson | D79: #3: Delaney: Cason Wallace | H79: #3: Green: Jalen Hood-Schifino
A80: #4: Moss: Brandon Miller | D80: #4: Jowkar: Jordan Hawkins -> Traded to Kelley | H80: #4: Gold: Nick Smith
A81: #5: Zujewski: Ausar Thompson -> Traded to Trager | D81: #5: Zujewski: Leonard Miller - > Traded to Trager | H81: #5: ZujewskI: Dennis Smith to IR -> Olivier-Maxence Prosper
A82: #6: Delaney: Jarace Walker | D82: #6: Kelvin: Brandin Podziemski | H82: #6: Berke: Steven Adams to IR - > James Nnaji
A83: #7: Kelley: Derek Lively II | D83: #7: Green: Kobe Bufkin | H83: #7: Delaney:
A84: #8: Trager: Bilal Coulibaly | D84: #8: Jowkar: Saddiq Bey | H84: #8: Kelley: Oubre to IR -> Dennis Schroder
A85: #9: Gold: Anthony Black | D85: #9: Berke: Jett Howard | H85: #9: Moss: Ja to IR -> Isaac
A86: #10: Kelley: Gradey Dick | D86: #10: Zujewski: Jaime Jacquez | H86: #10: Kelvin: Sabonis to IR -> Caleb Martin
A87: #11: (Compensation) Kelley: Cam Whitmore -> Traded to Jowkar -> Traded to Gold
A89: Round 4 (Compensatory) | E89: Round 5 (Compensatory) | I89: Round 6 (Compensatory)
A90: #1: Trager: Bridges to IR -> Grant Williams | E90: #1: Trager: roster spot from Ayton trade -> Kris Murray | I90: #1: Trager: Mark Williams to IR -> Dariq Whitehead
A91: #2: Jowkar: Zion Williamson to IR -> Lu Dort | E91: #2: Jowkar: Zach Collins to IR -> Corey Kispert | I91: #2: Jowkar: Deni Avdija to IR -> Matisse Thybulle
A92: #3: Green: Jaden McDaniels to IR -> Brooks | E92: #3: Green: | I92: #3: Green:
A93: #4: Gold: Jaden Hardy to IR -> Emoni Bates | E93: #4: Gold: Bol Bol | I93: #4: Gold: Colin Castleon
A94: #5: ZujewskI: Naz Reid to IR -> Andre Jackson Jr. | E94: #5: ZujewskI: | I94: #5: ZujewskI:
A95: #6: Berke: Victor Oladipo to IR -> Killian Hayes | E95: #6: Berke: | I95: #6: Berke:
A96: #7: Delaney: | E96: #7: Delaney: | I96: #7: Delaney:
A97: #8: Kelley: Malcolm Brogdon to IR -> Noah Clowney | E97: #8: Kelley: Middleton to IR -> Gabe Vincent | I97: #8: Kelley: CJ Mccollum to IR -> Amari Bailey
A98: #9: Moss: Jonathan Isaac to IR -> RIchaun Holmes | E98: #9: Moss: | I98: #9: Moss:
A99: #10: Kelvin: Julius Randle to IR -> Max Strus | E99: #10: Kelvin: | I99: #10: Kelvin:
A101: Round 7 (Compensatory) | E101: Round 6 (Compensatory)
A102: #1: Trager: Brice Sensebaugh to IR -> Norman Powell | E102: #1: Trager: PJ Washington to IR -> Isaiah Jackson
A103: #2: Jowkar: Walker Kessler to IR -> Keita Bates-Diop | E103: #2: Jowkar:
A104: #3: Green: | E104: #3: Green:
...

Sheet 2022
A1: Lob Land (HALE) | C1: Herro Ball (NJ) | E1: Washed Kings (DELA) | G1: Ice Trae (MAX) | I1: Magic City Hot Wingz (BERK) | J1: 2022 | N1: 2021-22 Fantasy Season | P1: (08/30/21 - 1/10/22 [TBD]) | T1: "The Offseason" : 2022 (April 11th - August ___) | W1: |
A2: 1st Round Jowkar | C2: 1st Round Green | G2: 1st Round Berke^ | I2: 2nd Round Peterson | N2: BERK Berke 2022 1st Round | O2: FOR | P2: HALE Mitchell Robinson | R2: 17 Regular Season Trades | T2: BERK Gordon Hayward | U2: FOR | V2: JOWK Donte Divencenzo
A3: 2nd Round Gold | C3: 1st Round Trager^^ | G3: 1st Round Vlandis* | N3: BERK Berke 2025 2nd Round | V3: JOWK Peterson 2022 2nd round
A4: 2nd Round Vlandis | C4: 2nd Round Delaney | G4: 2nd Round Green | V4: JOWK Delaney 2024 2nd round
A5: 2nd Round Trager | N5: BERK Fred Vanvleet | O5: FOR | P5: DELA Lebron James
A6: 2nd Round Berke | N6: BERK Montrezl Harrell | P6: DELA Draymond Green | T6: GOLD Gold 2023 1st round | U6: FOR | V6: MOSS Vlandis 2022 1st round (swap rights)
A7: 2022 (Year II) | N7: BERK Berke 2024 1st Round | T7: GOLD Kelvin 2024 1st round | V7: MOSS Kelvin 2022 1st round
A8: Deepwater Suggs (GOLD) | C8: Morey Ball (MOSS) | E8: Charlotte Wobnets (MT) | G8: Always Droppin Dimes (DIME) | I8: Z Man the Juice (Zman) | T8: GOLD Brook Lopez | V8: MOSS Jonathan Kuminga
A9: 1st Round Gold | C9: 2nd Round Moss | E9: 2nd Round Jowkar | I9: 1st Round Zujewski | N9: ZJEW Pascal Siakam | O9: FOR | P9: JOWK Saddiq Bey | T9: GOLD Seth Curry
A10: 1st Round Moss** | I10: 2nd Round Zujewski | N10: ZJEW Kemba Walker | P10: JOWK Kevin Porter Jr.
A11: 1st Round Delaney | N11: ZJEW John Wall | P11: JOWK Aaron Gordon | T11: MOSS Dejounte Murray | U11: FOR | V11: PETE Paul George
A12: 1st Round Peterson | T12: MOSS Moss 2024 FRP top 3 protected w/swap rights on Kelvin FRP - conveys to PETE 2024 FRP or Moss 2025 FRP | U12: 44769 | V12: PETE Rudy Gobert
N13: Kelvin Receives | P13: Zujewski Receives | R13: Gold Receives
N14: GOLD Caris Levert | P14: GOLD Jamal Murray | R14: PETE Jerami Grant | T14: VLAND Green 2022 1st round (#4 overall) | U14: FOR | V14: JOWK Caris Levert
A15: Draft Pick Protections & Swaps | H15: Protected Pick | N15: ZJEW Mo Bamba | P15: PETE Chris Duarte | R15: ZJEW Josh Giddey | T15: VLAND Vlandis 2023 2nd round | V15: JOWK Saddiq Bey
A16: * - (Moss owns swap rights, swap if Vlandis is higher pick) | H16: Locked Pick- Future Protection | N16: GOLD Gold 2024 2nd Round | P16: PETE Mason Plumlee | R16: PETE Kelvin 2024 FRP
A17: **- (Swap with Vlandis if Vlandis is higher pick) | H17: Green (*) - Conveyed from past protection | N17: ZJEW Bobby Portis | T17: DELA Fred VanVleet | U17: FOR | V17: PETE Dejounte Murray
T18: DELA D'Angelo Russell | V18: PETE Wendall Carter Jr
A19: ^ - (Trager owns swap rights, swap if Trager is higher pick) | I19: Week | J19: Winner | K19: Victory Margin | L19: 2nd place | N19: DELA Terry Rozier | O19: FOR | P19: JOWK D'Angelo Russell | T19: DELA Nikola Vucevic | V19: PETE Bobby Portis
A20: ^^ - (Swap with Berke FRP if Berke is higher pick) | I20: 1 | J20: Logan | K20: 2 | L20: Moss | N20: DELA Delaney 2022 1st Round | T20: DELA Delaney 2025 2nd round | V20: PETE Gold 2024 2nd round
I21: 2 | J21: Kelvin | K21: 33 | L21: Moss | N21: DELA Berke 2024 1st Round
I22: 3 | J22: Kelvin | K22: 241 | L22: Logan | T22: TRAG Cj McCollum | U22: FOR | V22: VLAND Jowkar 2022 1st round (#5 overall)
A23: 2022 Draft Order: | C23: 1st Rd Owner | E23: 2nd Rd Owner | G23: 3rd Rd Owner Compensatory Round | I23: 4 | J23: Kelvin | K23: 167 | L23: Delaney | N23: JOWK Tyler Herro | O23: FOR | P23: VLAND Lamelo Ball | V23: VLAND Vlandis 2025 1st round
A24: #1: Lottery #1 (40% Gold) | C24: Zujewski | E24: Trager | G24: Gold | I24: 5 | J24: Kelvin | K24: 184 | L24: Delaney | N24: JOWK Jaren Jackson Jr. | P24: VLAND Nassir Little
A25: #2: Lottery #2 (30% Zujewski) | C25: Gold | E25: ZUjewski | G25: Zujewski | I25: 6 | J25: Logan | K25: 29 | L25: Kelvin | N25: JOWK Jakob Poeltl | T25: JOWK 2023 Green 2nd round | U25: FOR | V25: GREEN De'andre Hunter
A26: #3: Lottery #3 (30% Moss via Vlandis) | C26: Gold | E26: Trager | G26: Vlandis | I26: 7 | J26: Trager | K26: 227 | L26: Delaney | N26: JOWK Delaney 2022 1st Round
A27: #4: Green | C27: Jowkar | E27: Green | G27: Green | I27: 8 | J27: Green | K27: 5 | L27: Logan | N27: JOWK Delaney 2023 2nd Round | T27: JOWK Jae'Sean Tate | U27: FOR | V27: VLAND Malik Beasley
A28: #5: Jowkar | C28: Trager | E28: Vlandis | G28: Jowkar | I28: 9 | J28: Trager | K28: 30 | L28: Jowkar | T28: JOWK Gordon Hayward | V28: VLAND Jowkar 2025 1st round
A29: #6: Moss | C29: Green | E29: Moss | G29: Moss | I29: 10 | J29: Logan | K29: 123 | L29: Moss | N29: PETE Caris Levert | O29: FOR | P29: JOWK Dennis Schroeder | T29: JOWK Alex Caruso | V29: VLAND Vlandis 2023 2nd round
A30: #7: Delaney | C30: Gold | E30: Jowkar | G30: Delaney | I30: 11 | J30: Logan | K30: 234 | L30: Green | N30: PETE 2026 Jowkar FRP Swap w/Kelvin 2026 FRP (if swap doesn't happen, protection is Kelvin 2026 SRP) | P30: JOWK Jordan Clarkson | V30: VLAND Vlandis 2026 2nd round
A31: #8: Kelvin | C31: Gold | E31: Berke | G31: Kelvin | I31: 12 | J31: Moss | K31: 15 | L31: Green | N31: PETE Jae Crowder
A32: #9: Trager | C32: Jowkar | E32: Trager | G32: Trager | I32: 13 | J32: Trager | K32: 6 | L32: Green | T32: JOWK Jusuf Nurkic | U32: FOR | V32: VLAND Reggie Jackson
A33: #10: Berke | C33: Green | E33: Trager | G33: Berke | I33: 14 | J33: Kelvin | K33: 240 | L33: Green | N33: JOWK Delaney 2023 1st round | O33: FOR | P33: GREEN Bradley Beal | V33: VLAND Jowkar 2023 1st round
I34: 15 | J34: Moss | K34: 23 | L34: Green | N34: JOWK Berke 2024 1st round | P34: GREEN Jusuf Nurkic | V34: VLAND Vlandis 2026 1st round
I35: 16 | J35: Delaney | K35: 12 | L35: Kelvin | N35: JOWK Berke 2022 2nd round
I36: 17 | J36: Delaney | K36: 46 | L36: Jowkar | N36: JOWK Nassir Little | T36: VLAND Vlandis 2022 2nd round (#13 overall) | U36: FOR | V36: TRAG Mo Bamba
I37: 18 | J37: Trager | K37: 114 | L37: Kelvin | N37: JOWK Nicolas Claxton | T37: VLAND Vlandis 2024 2nd round | V37: TRAG Trager 2022 2nd round (#19 overall)
N39: BERK Harrison Barnes | O39: FOR | P39: PETE Jordan Clarkson | T39: VLAND Tyler Herro | U39: FOR | V39: MOSS Jonas Valanciunas
I40: 1st place finishes | K40: 2nd place finishes | P40: PETE Quentin Grimes | T40: VLAND Vlandis 2024 1st round | V40: MOSS Khris Middleton
I41: Logan | J41: =COUNTIF($J$20:$J$37, I41) -> 4 | K41: Logan | L41: =COUNTIF($L$20:$L$37,K41) -> 2 | V41: MOSS Moss 2023 2nd round
I42: Kelvin | J42: =COUNTIF($J$20:$J$37, I42) -> 5 | K42: Kelvin | L42: =COUNTIF($L$20:$L$37,K42) -> 3 | N42: PETE Mike Conley | O42: FOR | P42: DELA Lauri Markkanen
I43: Trager | J43: =COUNTIF($J$20:$J$37, I43) -> 4 | K43: Trager | L43: =COUNTIF($L$20:$L$37,K43) -> 0 | P43: DELA Delaney 2022 2nd round | T43: JOWK Kemba Walker | U43: FOR | V43: BERK Berke 2024 2nd round
I44: Green | J44: =COUNTIF($J$20:$J$37, I44) -> 1 | K44: Green | L44: =COUNTIF($L$20:$L$37,K44) -> 5
I45: Delaney | J45: =COUNTIF($J$20:$J$37, I45) -> 2 | K45: Delaney | L45: =COUNTIF($L$20:$L$37,K45) -> 3 | N45: JOWK Dillon Brooks | O45: FOR | P45: ZJEW Saddiq Bey | T45: PETE Joel Embiid | U45: FOR | V45: GREEN Domantas Sabonis
I46: Moss | J46: =COUNTIF($J$20:$J$37, I46) -> 2 | K46: Moss | L46: =COUNTIF($L$20:$L$37,K46) -> 3 | N46: JOWK Isaac Okoro | P46: ZJEW Andre Drummond | T46: PETE Berke 2022 1st round (#10 overall) | V46: GREEN Zach Lavine
I47: Zujewski | J47: =COUNTIF($J$20:$J$37, I47) -> 0 | K47: Zujewski | L47: =COUNTIF($L$20:$L$37,K47) -> 0 | N47: JOWK Luke Kennard | P47: ZJEW Kelly Olynyk | V47: GREEN Jarred Vanderbilt
I48: Gold | J48: =COUNTIF($J$20:$J$37, I48) -> 0 | K48: Gold | L48: =COUNTIF($L$20:$L$37,K48) -> 0 | V48: GREEN Derrick White
I49: Vlandis | J49: =COUNTIF($J$20:$J$37, I49) -> 0 | K49: Vlandis | L49: =COUNTIF($L$20:$L$37,K49) -> 0 | N49: GREEN Green 2022 1st round | O49: FOR | P49: VLAND Vlandis 2022 1st round | V49: GREEN Delaney 2022 1st (#7 overall)
I50: Jowkar | J50: =COUNTIF($J$20:$J$37, I50) -> 0 | K50: Jowkar | L50: =COUNTIF($L$20:$L$37,K50) -> 2 | P50: VLAND Delaney 2022 1st round | V50: GREEN Green 2023 2nd round
V51: GREEN Jowkar 2024 2nd round
N52: Kelvin Receives | P52: Trager Receives | R52: Delaney Receives | V52: GREEN Green 2024 2nd round
A53: 2022 Rookie Draft Recap: August 7th, 2022 | N53: TRAG Christian Wood | P53: PETE CJ McCollum | R53: PETE Al Horford
A54: Round 1 (Just Rookies) | D54: Round 2 (FA & Rookies) | H54: Round 3 (Compensatory) | N54: TRAG Wendall Carter Jr | P54: PETE Mo Bamba | T54: DELA Luka Doncic | U54: FOR | V54: JOWK Bradley Beal
A55: #1: Zujewski: Chet Holmgren | D55: #1: Trager: Mark Williams | H55: #1: Gold: Ben Simmons to IR -> Steven Adams | N55: TRAG Collin Sexton | P55: PETE Kevin Huerter | T55: DELA Ziaire Williams | U55: 44753 | V55: JOWK Pascal Siakam
A56: #2: Gold: Paolo Bonchero | D56: #2: Zujewski: Jalen Williams | H56: #2: Zujewski: Didn't pick up | N56: TRAG Berke 2022 1st round | P56: PETE Delaney 2022 2nd round | T56: DELA Gold 2024 2nd round | V56: JOWK Terry Rozier
A57: #3: Gold: Jabari Smith Jr | D57: #3: Green: Jeremy Sochan | H57: #3: Vlandis: Didn't pick up | N57: DELA Lamarcus Aldridge | P57: PETE Berke 2021 1st round swap rights (conveys to Trager 2021 1st round | T57: DELA Delaney 2026 2nd round | V57: JOWK Green 2024 1st round
A58: #4: Jowkar: Jaden Ivey | D58: #4: Jowkar: Walker Kessler | H58: #4: Green: Embiid to IR -> Dorian Finney-Smith | V58: JOWK Peterson 2025 1st round
A59: #5: Trager: Keegan Murray | D59: #5: Vlandis: Jake Laravia | H59: #5: Jowkar: Michael Porter Jr to IR -> Blake Wesley | N59: GREEN Spencer Dinwiddie | O59: FOR | P59: DELA Jarred Vanderbilt | V59: JOWK Vladnis 2026 1st round
A60: #6: Green: Jalen Duren | D60: #6: Moss: Malaki Branham | H60: #6: Moss: Rubio to IR -> Jae'Sean Tate | N60: GREEN Thomas Bryant | V60: JOWK Jowkar 2025 1st round swap rights (w/Delaney 2025 1st round)
A61: #7: Gold: Bennedict Mathurin | D61: #7: Trager: TyTy Washington | H61: #7: Delaney: Joe Harris to IR -> Bojan Bogdonavic
A62: #8: Gold: Shaedon Sharpe | D62: #8: Berke: Johnny Davis | H62: #8: Kelvin: Didn't pick up | N62: BERK Julius Randle | O62: FOR | P62: PETE Christian Wood | T62: TRAG Desmond Bane | U62: FOR | V62: VLAND Vlandis 2023 1st round (lower swap of Vlandis and Delaney
A63: #9: Jowkar: Tari Eason | D63: #9: Trager: AJ Griffin | H63: #9: Trager: Ball to IR -> Daniel Gafford | T63: TRAG Vlandis 2024 2nd round | V63: VLAND PJ Washington
A64: #10: Green: Dyson Daniels | D64: #10: Trager: Quentin Grimes | H64: #10: Berke: Alec Burks to IR -> Kevon Looney | N64: DELA Alec Burks | O64: FOR | P64: JOWK Patrick Beverly | T64: TRAG Delaney 2022 2nd round (#17 overall) | V64: VLAND Trager 2022 2nd round (#19 overall)
N65: DELA Kelvin 2022 2nd round | V65: VLAND Alex Caruso
A66: Round 4 (Compensatory) | E66: Round 5 (Compensatory) | I66: Round 6 (Compensatory)
A67: #1: Gold: Jalen Suggs to IR -> Chris Boucher | E67: #1: Gold: Drop Darius Bazley -> Christian Koloko | I67: #1: Gold: N/A | N67: PETE Gabe Vincent | O67: FOR | P67: ZJEW Aaron Gordon | T67: VLAND De'Aaron Fox | U67: FOR | V67: MOSS Tobias Harris
A68: #2: Zujewski: N/A | E68: #2: Zujewski: N/A | I68: #2: Zujewski: N/A | N68: PETE Amir Coffey | P68: ZJEW Evan Fournier | V68: MOSS Paul George
A69: #3: Vlandis: Lavine to IR -> Rui Hachimura | E69: #3: Vlandis: N/A | I69: #3: Vlandis: N/A | N69: PETE Zujewski 2023 2nd round | V69: MOSS Moss 2026 1st round
A70: #4: Green: Isaac to IR -> Jaden Hardy | E70: #4: Green: Dyson to IR -> Nikola Jovic | I70: #4: Green: N/A | N70: PETE Peterson 2024 2nd round
A71: #5: Jowkar: Josh Christopher to IR -> Jeremiah Robinson-Earl | E71: #5: Jowkar: Jalen Johnson to IR -> Ochai Ajbaji | I71: #5: Jowkar: Drop Ochai Ajbaji -> Dayron Sharpe | T71: VLAND Tobias Harris | U71: FOR | V71: PETE De'Angelo Russell
A72: #6: Moss: Seth Curry to IR -> Kyle Anderson | E72: #6: Moss: Bogdan Bogdonavic to IR -> Evan Fournier | I72: #6: Moss: N/A | T72: VLAND Paul George | V72: PETE Zach Lavine
A73: #7: Delaney: N/A | E73: #7: Delaney: N/A | I73: #7: Delaney: N/A | T73: VLAND Moss 2026 1st round | V73: PETE Malcolm Brogdon
A74: #8: Kelvin: N/A | E74: #8: Kelvin: N/A | I74: #8: Kelvin: N/A | T74: VLAND Jaren Jackson Jr. | V74: PETE Delaney 2022 1st round (#7 overall)
A75: #9: Trager: Ingram to IR -> Cody Martin | E75: #9: Trager: Dort to IR -> Jae Crowder | I75: #9: Trager: AJ Griffin to IR -> Paul Reed
A76: #10: Berke: Drop Tyus Jones -> James Bouknight | E76: #10: Berke: | I76: #10: Berke: | T76: VLAND Delaney 2022 1st round (#7 overall) | U76: FOR | V76: GOLD Peterson 2022 1st round (#8 overall)
T77: VLAND Vlandis 2024 2nd round | V77: GOLD Gold 2023 2nd round
A78: Kelvin: Pickup Tim Hardaway put on IR -> Terrance Mann
A79: Kelvin: Lillard to IR -> Royce O'Neale | T79: VLAND Mo Bamba | U79: FOR | V79: GOLD Jemai Grant
A80: Kelvin: JJJ to IR -> D'evonte Graham
T81: VLAND Coby White | U81: FOR | V81: JOWK Clint Capela
T82: VLAND Peterson 2022 1st round (#8 overall) | V82: JOWK Jowkar 2022 2nd round (#15 overall)
T83: VLAND Delaney 2022 2nd round (#17 overall) | V83: JOWK Berke 2024 2nd round
V84: JOWK Vlandis 2026 2nd round
T86: GREEN 2022 Berke 2nd round (#20 overall) | U86: FOR | V86: TRAG Right to swap Green 2025 2nd round Trager 2025 2nd round (if it doesn't convey, right to swap Green 2026 2nd round with Trager 2026 2nd round)
T88: Gold Receives | V88: Trager Receives | X88: Jowkar Receives
T89: JOWK Peterson 2022 1st round (#8 overall) | V89: GOLD Gold 2022 2nd round (#11 overall) | X89: TRAG Trager 2022 1st round (#9 overall)
V90: GOLD Gold 2026 1st round Swap rights (connected to Trager 2026 FRP) | X90: GOLD Vlandis 2024 2nd round
V91: GOLD Gold 2025 2nd round | X91: GOLD Gold 2026 2nd round
T95: JOWK Andre Drummond | U95: FOR | V95: BERK Berke 2025 1st round
T96: JOWK Reggie Jackson | V96: BERK Ayo Dosunmu
T97: JOWK Victor Oladipo | V97: BERK Deni Avdija
T98: JOWK Vlandis 2024 2nd round
T100: PETE Collin Sexton | U100: FOR | V100: BERK Christian Wood
T101: PETE Moss 2024 1st round | V101: BERK Mitch Robinson
V102: BERK Berke 2023 2nd round
V103: BERK Delaney 2024 2nd round
T105: BERK James Harden | U105: FOR | V105: DELA Dejounte Murray
T106: BERK Chris Paul | V106: DELA Kelly Oubre
T107: BERK Draymond Green | V107: DELA Green 2024 1st round
V108: DELA Delaney 2024 1st round
...

Sheet 2021
A1: Sex Land (TRAG) | C1: Herro Ball (JOWK) | E1: Washed Kings (DELA) | G1: Ice Trae (GREEN) | I1: Magic city Hot Wingz (BERK) | J1: 2021 | N1: 2020-21 Fantasy Season | P1: (12/22/20 - 3/15/21) | S1: "The Offseason" : 2021 (May 17th - August 28th)
A2: 1st Round Trager | C2: 2nd Round Jowkar | E2: 2nd Round Trager | G2: 1st Round Green | I2: 2nd Round Berke | N2: JOWK SF/PF Deandre Hunter | O2: FOR | P2: GREEN PF/C Jaren Jackson Jr | R2: 19 Regular Season Trades | S2: JOWK Kendrick Nunn | T2: FOR | U2: VLAND Klay Thompson
A3: 1st Round Peterson | E3: 2nd Round Delaney | G3: 1st Round Jowkar | I3: 2nd Round Vlandis | N3: JOWK C Mason Plumlee | P3: GREEN SF/SG Will Barton | S3: JOWK Jowkar 2022 1st Round | U3: VLAND Vlandis 2023 1st Round Swap Rights (connect to Delaney 2023 1st)
I4: 2nd Round Green | N4: JOWK SF/SG Cameron Johnson | P4: GREEN SG/SF Justin Holiday | S4: JOWK Jowkar 2025 1st Round
N5: JOWK Jowkar 2021 1st Round | P5: GREEN Green 2024 1st Round (top 1 protected, conveys to 2025 GREEN first)
N6: JOWK Jowkar 2024 2nd Round | S6: BERK Berke 2021 1st round | T6: FOR | U6: VLAND Vlandis 2021 2nd round
A7: 2021 (Year I) | U7: VLAND Green 2021 2nd round
A8: Deepwater Bogdanovic (SG) | C8: Morey Ball (MOSS) | E8: Minnesota TimberWobs (MT) | G8: Always Droppin Dimes (DIME) | I8: Z man the Juice (ZMAn) | N8: TRAG Joel Embiid | O8: FOR | P8: DIME Deandre Ayton
A9: 1st Round Gold | C9: 1st Round Moss | E9: 1st Round Delaney | G9: 2nd Round Peterson | I9: 1st Round Zujewski | N9: TRAG De'Aaron Fox | P9: DIME Victor Oladipo
A10: 2nd Round Gold | C10: 1st Round Vlandis | E10: 1st Round Berke | G10: 2nd Round Zujewski | P10: DIME Kelvin 2021 1st Round | T10: August 29th 2021
C11: 2nd Round Moss | S11: / / / / / / / / / Draft Day 2021 / / / / / / / / /
N12: TRAG Demar Derozan | O12: FOR | P12: DELA Collin Sexton | S12: TRAG Berke 2023 1st | T12: FOR | U12: JOWK Jowkar 2021 2nd (#14)
N13: TRAG Trager 2021 2nd Round | S13: TRAG Berke 2022 2nd
A14: Draft Pick Protections
H15: Protected Pick | N15: Kelvin Receives | P15: Delaney Receives | R15: Jowkar Receives | S15: JOWK Peterson 2022 2nd | T15: FOR | U15: DELA Delaney 2021 2nd (#17)
H16: Locked Pick- Future Protection | N16: DELA Jerami Grant | P16: JOWK Lauri Markanen | R16: DIME Clint Capela | S16: JOWK Jowkar 2023 2nd
H17: Green (*) - Conveyed from past protection | N17: JOWK Mike Conley | P17: DIME Kemba Walker | R17: DELA Dela 2024 2nd Round
N20: DELA Kemba Walker | O20: FOR | P20: ZJEW Draymond Green
N21: DELA Bobby Portis | P21: ZJEW Joe Harris
A23: 2021 Draft Order: | C23: 1st Rd Owner | E23: 2nd Rd Owner | G23: 3rd Rd Owner Compensatory Round | K23: 2nd round is Compensatory, thus you can pick from other free agents | N23: BERK Andrew Wiggins | O23: FOR | P23: JOWK Montrezl Harrell
A24: #1: Lottery #1 (40% Green) | C24: Green | E24: Vlandis Berke | G24: Green | K24: 1st round picks must all be rookies
A25: #2: Lottery #2 (30% Gold) | C25: Moss | E25: Gold | G25: Gold | N25: MOSS Malcolm Brogdon | O25: FOR | P25: DIME Donovan Mitchell
A26: #3: Lottery #3 (30% Moss via Vlandis) | C26: Gold | E26: Vlandis Berke | G26: Vlandis | N26: MOSS Rudy Gobert | P26: DIME Myles Turner
A27: #4: Jowkar | C27: Green | E27: Jowkar | G27: Jowkar | N27: MOSS Al Horford | P27: DIME Kelvin 2022 1st Round
A28: #5: Zujewski | C28: Zujewski | E28: Kelvin | G28: Zujewski
A29: #6: Trager | C29: Trager | E29: Delaney | G29: Trager | N29: GREEN Mason Plumlee | O29: FOR | P29: DIME Kelvin 2023 1st Round
A30: #7: Delaney | C30: Vlandis | E30: Delaney | G30: Delaney | N30: GREEN Green 2021 2nd round | P30: DIME Kelvin 2022 2nd Round
A31: #8: Kelvin | C31: Trager | E31: Kelvin | G31: Kelvin
A32: #9: Berke | C32: Berke Vlandis | E32: Berke | G32: Berke | N32: VLAND Steph Curry | O32: FOR | P32: DIME De'Aaron Fox
A33: #10: Moss | C33: Moss | E33: Moss | G33: Moss | N33: VLAND Jeremy Lamb | P33: DIME Devonte Graham
N34: VLAND Dillon Brooks | P34: DIME Keldon Johnson
P35: DIME Green 2021 2nd round
N37: TRAG James Harden | O37: FOR | P37: BERK Brandon Ingram
A38: 2021 Rookie Draft Recap: August 29th, 2021 | P38: BERK 2023 Berke 1st round
A39: Round 1 (Just Rookies) | D39: Round 2 (FA & Rookies) | H39: Round 3 (Compensatory) | P39: BERK 2022 Berke 2nd round
A40: #1: Ice Trae: Cade Cunningham | D40: #1: Magic City Hot Wingz: Moses Moody | H40: #1: Ice Trae: Isaac IR ---> Onyeka Okongwu
A41: #2: Morey Ball: Jalen Green | D41: #2: Deepwater: Marvin Bagley | H41: #2: Deepwater: Murray IR ---> Seth Curry | N41: MOSS Donovan Mitchell | O41: FOR | P41: VLAND Russell Westbrook
A42: #3: Deepwater: Jalen Suggs | D42: #3: Magic City Hot Wingz: Cam Thomas | H42: #3: Minnesota TimberWobs: Coby White IR ---> Steven Adams | P42: VLAND 2021 Vlandis 1st round
A43: #4: Ice Trae: Evan Mobley | D43: #4: Herro Ball: ---> HaleTrager : Jaden McDaniels | H43: #4: Herro Ball: Klay Thompson IR ---> Markelle Fultz IR | P43: VLAND 2022 Vlandis 1st round swap right
A44: #5: Z man the Juice: Josh Giddey | D44: #5: Always Droppin Dimes: Chris Duarte | H44: #5: Z Man the Juice: N/A
A45: #6: SexLand: Scottie Barnes | D45: #6: Washed Kings: Zaire Williams | H45: #6: SexLand: Mitch Robinson IR ---> Nerlens Noel | N45: JOWK Damian Lillard | O45: FOR | P45: DIME Nikola Jokic
A46: #7: Minnesota TimberWobs: James Bouknight | D46: #7: Washed Kings ---> Jowkar Victor Oladipo | H46: #7: Washed Kings: Doug Mcdermott | N46: JOWK Kyrie Irving | P46: DIME Dillon Brooks
A47: #8: SexLand: Alperen Sengun | D47: #8: Always Droppin Dimes: Chuma Okeke | H47: #8: Always Droppin Dimes: N/A | P47: DIME Kelvin 2025 1st round
A48: #9: Minnesota TimberWobs: Davion Mitchell | D48: #9: Magic City Hot Wingz: Lonnie Walker IV | H48: #9: Magic City Hot Wingz: Drop Ricky Rubio ---> Bones Hyland
A49: #10: Morey Ball: Jonathan Kuminga | D49: #10: Morey Ball: Josh Christopher | H49: #10: Morey Ball: N/A | N49: DIME Kyrie Irving | O49: FOR | P49: ZJEW Paul George
N50: DIME Josh Jackson | P50: ZJEW Terry Rozier
A51: Round 4 (Compensatory) | E51: Round 5 (Compensatory) | I51: Round 6 (Compensatory) | P51: ZJEW Zujewski 2021 2nd round
A52: #1: Ice Trae: Isaiah Stewart ---> Devin Vassell | E52: #1: Ice Trae: Thomas Bryant IR ---> Kira Lewis | I52: #1: Ice Trae: Patrick Williams IR ---> Trey Murphy III | P52: ZJEW Zujewski 2023 2nd round
A53: #2: Deepwater: TJ Warren IR ---> Cameron Johsnon | E53: #2: Deepwater: James Wiseman IR ---> Malik Monk | I53: #2: Deepwater: N/A
A54: #3: Minnesota TimberWobs: N/A | E54: #3: Minnesota TimberWobs: N/A | I54: #3: Minnesota TimberWobs: N/A | N54: DELA Richaun Holmes | O54: FOR | P54: DIME Terry Rozier
A55: #4: Herro Ball: Markelle Fultz IR ---> Nicholas Claxton | E55: #4: Herro Ball: Victor Oladipo IR ---> Jalen Johnson | I55: #4: Herro Ball: N/A | N55: DELA Norman Powell | P55: DIME TJ McConnell
A56: #5: Z Man the Juice: N/A | E56: #5: Z Man the Juice: N/A | I56: #5: Z Man the Juice: N/A
A57: #6: SexLand: Donte Divencenzo IR ---> Demond Bane | E57: #6: SexLand: N/A | I57: #6: SexLand: N/A | N57: JOWK Thaddeus Young | O57: FOR | P57: DELA Dennis Schroeder
A58: #7: Washed Kings: Payton Pritchard | E58: #7: Washed Kings: N/A | I58: #7: Washed Kings: N/A | P58: DELA Delaney 1st round 2021
A59: #8: Always Droppin Dimes: N/A | E59: #8: Always Droppin Dimes: N/A | I59: #8: Always Droppin Dimes: N/A | P59: DELA Delaney 2nd round 2023
A60: #9: Magic City Hot Wingz: Drop Kontavious Caldwell Pope ---> Shariife Cooper | E60: #9: Magic City Hot Wingz: Drop Alec Burks --> Pickup Carmelo Anthony | I60: #9: Magic City Hot Wingz:
A61: #10: Morey Ball: Myles Turner IR ---> Kevin Love | E61: #10: Morey Ball: N/A | I61: #10: Morey Ball: N/A | N61: JOWK Klay Thompson | O61: FOR | P61: VLAND D'Angelo Russell
N62: JOWK Andrew Wiggins
A63: 7th Round for Ice Trae: Okongwu to IR ---> Pickup Usman Garuba | N63: JOWK Delaney 1st round 2021
N64: JOWK Jowkar 1st round 2023
N66: JOWK Onyeka Okongwu | O66: FOR | P66: GREEN Saddiq Bey
P67: GREEN Kelvin 2022 2nd round
P68: GREEN Green 2023 2nd round
N70: JOWK Derrick Rose | O70: FOR | P70: DELA Lou Williams
P71: DELA Delaney 2023 1st round
N73: JOWK Kendrick Nunn | O73: FOR | P73: VLAND Klay Thompson
N74: JOWK Jowkar 1st round 2022 | P74: VLAND Vlandis 2023 1st round swap rights with Delaney 2023 1st round
N75: JOWK Jowkar 1st round 2025

Sheet Trade History
A1: Brandon Ingram | B1: =COUNTIF('2023'!A:A, "*" & A1 & "*") + COUNTIF('2022'!A:A, "*" & A1 & "*") + COUNTIF('2021'!A:A, "*" & A1 & "*") -> 0

Sheet OT-2026
A1: Offseason Topics (OT) 2026 | B1: Subject | C1: Extra thought | D1: Are we voting on this? | E1: Result
B2: Max GP | C2: Vote between 55 and no more Max GP - consideratoin to include 60 but argumentwas made that it's too little to matter No matter what, commissionser will no longer be retroactively editing lineups
B3: Stepien Rule | C3: If we want to have 5 years of picks that's fine, but we could consider putting a limit on this. My proposal is that you must have 1 first round picks pick in the next 3 drafts to be able to trade your deeper picks. What this means practically is that if you don't have any picks for the next 3 seasons, you have to retain your deeper firsts and future unless you gain a first in the next 3 seasons. Any trade that conflicts with the Stepien rule being adhered to would get rejected by the legue office

Sheet OT-2025
B1: Subject | C1: Extra thought | D1: Are we voting on this? | E1: Result
B2: Cup double week | C2: The NBA Cup has the quarter finals/semi-finals/and finals over the course of 2 weeks which creates weird schedules for the week. Better to combine them for increased volume in the week (although variance can be fun!) Idea is to combine the weeks where these events for the NBA cup take place | D2: No | E2: Combining the week (I need to actually remember to do it, we should just allow me to correct the mistake if we realize it in season)
B3: Move from Groupme to Discord | C3: Could allow us to create channels and just has a lot of versatility as an app. Does anyone even use groupme anymore outside of this chat? | D3: Yes
B4: Lower buy in from 100 to 50 | D4: No
B5: Axe weekly highest scorer? | C5: 10 or 0 (fuck 5) | D5: Yes
B6: Maximum GP | C6: Lloyd said 4 per slot on twitter, Trager thinks 5 per slot. That's 40 vs 50 starts per week. Would vote first on if we have a max GP then would vote on what number that would be Look into bench which can be a reserve slot that can be bumped into the scoring Voting on 50 GP for regular season weeks and then playoffs having no cap | D6: Definitely
B7: Shorten the season | C7: Currently 16 periods with ASG week being wild card round and then next month being playoff matchups Things to consider: How to deal with ASG weeks if part of playoffs Total number of regular season periods (currently 16, considering an NFL scheduling model where bottom teams play bottom teams as their duplicate, would get us to 13/14 weeks probably) If we still want 2 week matchups for semis and finals | D7: Voting on moving wild card to week before all star break and then doing a spring break for the wild card week(s) | E7: Axe
A8: Kelvin | B8: Tanking proposal | C8: Lowest average score of players gets highest pick - question becomes where does it stop from there? | E8: 6% per strike
B9: Zujewski proposed changes | C9: Proposed Changes: 1. Waiver Schedule Adjustment: Waiver claims will be processed twice weekly, specifically on Sunday and Wednesday mornings. This change aims to accommodate the increasingly busy schedules of our members, allowing for strategic planning without daily oversight. 2. Introduction of Bidding: Implement a bidding system for waiver claims to introduce an exciting, competitive aspect to acquiring players. 3. Strategic Waiver Days: Setting waiver days to Sunday and Wednesday optimizes flexibility for handling injuries, allowing team owners to respond effectively to player availability and plan for the week ahead, particularly targeting the high-volume game days. 4. Unlimited Pickups: On waiver processing days (Sunday and Wednesday), there will be no limit to the number of pickups a team can make. This measure is to offset the reduced frequency of waiver claims and encourage strategic decision-making on designated days. 5. Unlimited Injured Reserve (IR) Spots: To reduce the impact of injuries on fantasy teams, unlimited IR spots will be introduced. However, to prevent abuse of this system: • Injured players cannot be added directly to the IR upon acquisition. • Players with the Game Time Decision (GTD) status are ineligible for immediate IR placement to prevent games played manipulation. | D9: 1. Discussion 2. Already happening 3. Discussion same as 1 4. Discussion along with 1 5. Discussion | E9: Axe

Sheet OT-2024
B1: Subject | C1: Extra thought | D1: Are we voting on this? | E1: Result
A2: Consensus | B2: IST 2 week matchup | C2: It's a weird week so we should make it 2 weeks to account for this | D2: No | E2: Doing it
A4: Discuss asap | B4: 2x per day FAAB | C4: Fantrax lets us set up FAAB for 2x per day. Could do 9am and 4/5pm to account for daily pickups and injury replacement pickups. Not perfect if a guy is ruled out last second, but better than our current system imo Decision here will inform a vote on if we are keeping the Compensatory round or not. With FAAB, it would be bidding for FA's right when they become available which could be pretty fair. Might also set a date for FA to open post draft instead of opening it right away but that's up for group discussion | D4: Yes | E4: Fantrax didn't allow 2x FAAB per day but we voted this in. Shifted to 1x FAAB per day which will be followed by a free for all free agency system for the rest of the day from the set FAAB time
B5: Slow Draft | C5: The idea is that each pick gets 24 hours to be taken. This will allow for more trading opportunities overall. Drafters should not take the full 24 hours if they do not need it, for the sake of everyone. We'll have to decide if the person picking just sends it in or Trager announces it in the groupme. | D5: Yes | E5: Yes we're doing it
A7: Trager stuff | B7: Reduce IR Spots | C7: Everyone complains about FA, well lets make it better! We can reduce IR from 5 to 4/3 to inject more randomness into the league from injuries. Forces you to be a bit lucky to win. We only went to 5 IR spots due to COVID, so should revert back | D7: Yes | E7: Voting
B8: Reduce number of years of picks | C8: We should consider limiting future picks to 4 years out instead of 5. Would increase their value and not let people throw away their futures as easiliy. If approved, would not be implemented until 2025 offseason by not unlocking 2030 picks that year (would still unlock 2029 picks in 2024 offseason) | D8: Yes | E8: Voting
B9: Add player eligibility | C9: Text Trager and make your argument? Groupchat with Trager and Max? https://www.nba.com/stats/lineups/traditional?slug=traditional - going to use advanced filters on this for all position arguments to see most used lineups and where players play in those lineups | D9: No
A11: Zujewski | B11: G-league call ups | C11: Zujewski - should be once per year, feels too much like a roster spot right now | D11: Maybe | E11: Voting
B12: Bi-weekly FA pickups | C12: Zujewski - Wednesday and Sunday morning | D12: Maybe | E12: Ignore, trying out FAAB first
A14: Gold | B14: Max games played | C14: Feels like it has to be at least 55-60 games | D14: Maybe | E14: Looking into #, will debate in groupchat
A16: Jowkar | B16: Dues for Lawson | C16: Jowkar - we all look for this guys rankings and some pay anyways. Everyone could contribute $5-6 toward dues and we could all just have his stuff as a league | D16: Maybe | E16: Making a sub group if people want it to just be pooled and released to the group that wants in
A18: More Trager | B18: Starting Centers establishment | C18: Going to be sure all 30 starting centers from the league the year prior are marked as a primary center by the keeper deadline. Caveat being if a team has a "major change" losing some players that make it clear a certain player would now be the starting C | D18: No | E18: Just doing it, will go into effect at start of the season
B19: Tanking rules - weekly minimum GP | C19: Still a 3 strike system where the 3rd strike results in loss of furthest out SRP. A 4th strike results in dropping of lottery odds (if team owns their own pick). Weekly minimum is 30 games for all teams so retroactively a team can receive a strike. A team can also still receive a strike by sitting a top player 2x within a week or on the last day of a matchup. Top player will be defined as those averaging 40+ and the league office will differ to the discretion of the manager if they have an explanation as to why they did it or what happened. | D19: No | E19: Just doing it
B20: Draft roster flexibility | C20: During the draft, teams can make trades and be over the 22 player limit. However, once the draft ends there will be a 12 hour period to process the drops to get every team to 22 players or fewer. From there the compensatory round will begin. Compensatory round will be completed in 1 night with 10 min per pick. | D20: No | E20: Just doing it
B21: FAAB time | C21: When should we do FAAB? On the one hand could do 5/6pm so that it's really the FA right before games played. However, when thinking about the league schedule this would be bad for weekend games. Thus 11am might be best. Depends how hte league wants to prioritize the purpose of the FAAB timing whether it's for limiting most pickups to FAAB system or allowing FAAB to basically take the place of overnight/in-game pickups to even the playing field Probably the latter so 11am makes sense | D21: Yes | E21: Noon / 12pm each day

Sheet OT- 2023
A1: Subject | B1: Extra thought | C1: Are we voting on this? | D1: Result
A2: ESPN vs Fantrax | B2: ESPN Pros - people are used to it, same app as their other fantasy (just football) Fantrax Pros - roster pickups once games start, significantly more optionality, DTD can go in IR, notifications to set your lineup & for pickups, automatic lineup setting for the week, trade block that notifies you, 1 week wildcard round | C2: Probably not | D2: Unless someone insists, it has seemed pretty unanimous over the course of the year that Fantrax is the preferred site
A3: If we choose to stay w/Fantrax - vote on G-League | B3: Do we keep this concept? | C3: Probably not | D3: Staying with Fantrax partially just for this (and other flexibility
A4: Vote on roster size | B4: 22 vs 20 | C4: No | D4: Unless someone forces it
A5: Extra wildcard slot | B5: I think we should have the 6th place team make the wild card. Top 2 seeds get byes and 3/4 are in the play in vs 6/5 respectively with a 1 week wild-card round. Also think we should change up payout structure to include playoff teams getting their money back. It would just be top 4 teams (extra $100 out of overall pot, would become 600-200-100-100 probably). Play-in round is for money back and receiving a bye guarentees money back. Change lottery to 4 teams that miss play-in/playoffs. Change odds percentages to 40-30-20-10 for bottom 4 teams. It's a top 2 lottery, so the worst the 40% team can finish is 3rd overall. | C5: Yes
A6: Teams that miss playoffs should have a chance at the #1 pick | B6: Proposing 40/30/20/5/5 , or 35/30/20/10/5 - eliminiates incentive to tank. Last place team can't finish worse than 3rd (same as current). | C6: Yes (if above fails)
A7: G-League: | B7: 1. 164 games played maximum
A8: The Kessler Rule | B8: Players who average 25 FPPG on the season at any point in the season (outside the first week of a small sample size) will lose G-League eligibiligty once it's brought to the Commissioners attention. They must be replaced within 24 hours or will be dropped, this will occur outside of the normal call up/call down periods. | C8: Yes
A9: The Sharpe Rule | B9: If we add an FPPG limit for the G-League, we could remove the FRP restriction for G-League. This would allow people to take "projects" that they feel are highly talented and want to take a chance on with a high pick. | C9: No | D9: Addendum to the Kessler Rule
A10: Conversation on ways to improve Waivers | B10: Reduce IR by 1: We no longer have Covid, with DTD able to enter on Fantrax, it limits waivers even more if everyone is using them all
A11: Draft Day | B11: Within 1-2 weeks of SL ending (2023 example - SL ended July 17th - draft by end of July)
A12: If we choose to stay w/Fantrax - # of starts threshold | B12: Need to get weekly average - 50-55 - 7-8 starts per day
A13: FAAB | B13: 2 FAAB times per day
A14: Tanking rules: Just Lineup Optimization | B14: It's not a sustainable long term strategy to care about people's start/sit decisions. Suggestion is to do a 30+ FPPG player for lineup optimization as the only reason to receive a complaint for lineup optimization. | C14: No | D14: Trager to announce tanking policy
A15: Should Commish be allowed to adjust lineups at all? | B15: I started to adjust lineups midseason in lieu of giving people strikes, to just get the "real" outcomes people wanted/intended Gap - if someone forgets to set their own lineup, I wouldn't offer to adjust it for them. But if someone reports them in as tanking, I would adjust it in leau of a strike. How do we remedy this? Allow someone to have 1-2 "mistakes" per year for lineup adjustments that have to be sent in within 24 hours? | C15: No | D15: Trager to announce tanking policy
A16: Tanking rules: Punishment | B16: I think we should do a 3 strikes = loss of SRP structure. 4th strike = loss of lottery chances (only if you own your own pick) 1 strike can come from not setting your lineup on multiple days in a week, not setting your lineup on a weekend day (Sat/Sun), or not optimizing your lineup for your 35+ FPPG scorers (season average) If this doesn't work, we will have to very seriously consider flat odds for the lottery for all non-playoff participants. You should be able to tank and get into the lottery, but the amount of maneuvering in the past year was frankly absurd and won't be tolerated by me again to deal with. | C16: No | D16: Trager to announce tanking policy
A17: The Spennyian Rule | B17: Roster limit in the offseason - Roster limit will be +4 from whatever we decide the # of keepers are. This dispermits someone from overloading their team soooo much that they drop valuable pieces. (Spencer, summer of 2022) | C17: No
A19: No IR usage in offseason | B19: Kelvins idea - no use of IR in the offseason. Assuming this refers to everything before the start of the season. Need to understand if it is refering to the offseason ending is post-draft or start of NBA season | C19: Yes | D19: Vote occurred before the draft. IR slots are eligible to be used in compensatory round and in the intervening time before the NBA season starts

Sheet OT-2022
A1: Subject | B1: Extra thought | C1: Are we voting on this? | D1: Result
A2: Can an FRP be eligible for g-league on a new team? | B2: If a team drops a player (or they get traded away), are they then eligible for the g-league for any team besides the one that originally drafted them? | C2: Yes | D2: If a player touches a g-league game in the real NBA, they will then become eligible for g-league that year FRP are eligible for g-league if they're dropped (and picked up by the team that did not draft them)
A3: Weekly highest scorer Dues | B3: Get rid of it? Modify? look at end of season results Weekly highest scorer won $20 per week - 17 weeks = $34 per person Adding $10 for Fantrax. | C3: Yes | D3: Dues will be $144, Fantrax dues + weekly highest scorer
A4: Tanking | B4: We now have an ability to set lineups for an entire period ahead of time, so now how do we want to deal with purposefully sitting guys? | C4: Yes | D4: No tanking rules, self-enforcement, that's the point of the lottery
A5: FAAB? | B5: Free agent auction budget? Pro is actually bidding on players, con is no more same day pickups | C5: Yes | D5: No
A6: Player Primary/Secondary Postion Eligibility | B6: Can we trade this if the player starts at a different position than their Primary is? Examples in pre-season would be JJJ and Mobley, once the season starts someone like KAT probably too | C6: No | D6: This just feels fairly easy to me, like if a guy is starting at a position that should be his primary position. For these PF cases, sure maybe they play some C but realistically the starting C on their team is getting 24+ min which means that this player is not playing a majority of the teams Center minutes. Will always be based on the year prior and where they played. Can be adjusted midseason at owners request based on 10+ GP of evidence
A7: Scoring on Fantrax | B7: Keeping ESPN scoring, unless someone has a better option; can consider future scoring changes brought to the league in the offseason | C7: No | D7: I updated it to be what we had with ESPN Scoring
A8: Wild Card round - 1 week | B8: See if Fantrax allows for a 1 week wild card round with 2 week semis and finals | C8: No | D8: I think everyone just wants this, it makes sense to shorten playoffs a little too
A9: Should the regular season go through last week of the regular season? | B9: It has for the past 2 years, did the finalists feel like it effected their players playing games? Has the league become competitive enough with the play-in tournament and seeding that teams were able to still compete at their normal level? | C9: No | D9: Going to end regular season 1-2 weeks before playoffs end depending on NBA schedule timing with all star break and our playoffs
A10: Divisions | B10: Would be cool to set up extra kinds of competition/scheduling, divisions would be MA and outside MA. MA: Trager, Moss, Gold, Zujewski, Jowkar Outside MA: Delaney, Logan, Kelvin, Spencer, Green Even if we don't do divisions, I want to determine some kind of rotational-ish program to give people similar-ish matchups over the course of years | C10: No | D10: These feel kind of out of whack now, regular season will be 14-15 weeks though. So everyone will face each of the previous years playoff or non-playoff teams respective of where they finished (playoff includes wildcard in this definition). So that's 13 weeks of matchups. Remaining 1-2 weeks will come from the opposite group, 6vs1, 7vs2, 8vs3, 9vs4, 10vs5. And 7vs1, 8vs2, 9vs3, 10vs4, 5vs6
A11: Median scoring? | B11: Highest scorers in a week get a win even if they lose their matchup if they are in the top half of the league in scoring | D11: Just an idea as it's now an option
A12: Minor league call-ups | B12: 3 times during the year. 1/3rd of regular season, 2/3rds of regular season, then at playoffs | C12: No | D12: Executive decision on call-ups this year, can be voted on for iterations in future year(s)
A13: Comp rounds go to those who are on the call | B13: Compensatory picks (including moving keepers to IR for FA pickups) are only for owners that show up to the zoom/group call. All others can access free agency as they normally would once all draft results are inputted | C13: No | D13: I'll just be doing this, it's what my football league does. It's meant to be a quick kind of round so texting people for their "picks" or if they're making one becomes arduous
A14: Buy in | B14: Do people actually want to increase it or was that a joke? Lol | C14: Probably no
A15: Non-playoff team pickups during the playoffs | B15: Less free agency, do we want to now allow non-playoff teams to pick up players during the playoffs? | C15: No | D15: Just an idea because it's an option, probably shouldn't happen, but lmk if people feel otherwise

Sheet OT-2021
A1: Subject | B1: Problem | C1: Ideas people have | D1: Ansillary Piece | E1: Conclusion | G1: Order | H1: Consolidated Topics | J1: Discussion Results
A2: Roster size | B2: They feel too small, people can't keep their second round picks if they want to be competitive with add/drops throughout the season | C2: Trager wants it to get to 20 roster spots | D2: Increase # of centers to 5 | E2: Executive order to increase spots from 18 to 20 | G2: 1 | H2: Trading policy | J2: Statement
A3: IR Slots | B3: People felt like they had a lot of injuries this year, is this due to weird COVID season? Has to be thought of in conjunction with roster size question | C3: Zujew: Unlimited IR Max G: Designate one player as a long term IR that others cannot pick up, can only be used in the case of season-long injury, must be chosen as a keeper for said team | G3: 2 | H3: How do people feel about Dynasty vs a 10 man keeper? (Moss) | J3: at least 5 want dynasty, we can vote in future if needed
A4: Draft lottery | B4: The NBA makes it so every team that misses the playoffs gets put in the lottery, why don't we do the same? | C4: 5% odds for 4th and 5th to last | G4: 3 | H4: Minor league slots (20 + 2) [G-League] | K4: Voted in
A5: Tanking | B5: People intentionaly leaving players out of their lineup | C5: Fine? 2nd rounder taken away? Warning system? | D5: What to do when people forget to set their lineup? Is there a warning system in place? etc | G5: 4 | H5: Tanking policy? (may lead into auto-set lineups) (automation options - espn chrome estension, yahoo [full week], fantrax [daily]) | J5: Vote in chat
A6: Trading policy | B6: It's annoying receiving text from multiple people about things/things not being confirmed | C6: Text Trager and Max in a group chat with the people making the trade to announce it, include who you will be dropping (how it will work), WHEN you want trade to process | G6: 5 | H6: IR slots (number needed per team, IR+ at Yahoo?, long term vs short term IR?) | I6: Scoring in general is different on different sites | J6: Majority 5 slots
A7: Position limits | B7: It sucks being capped at Centers (would move from 4 to 5 due to roster size increase) | C7: No limits on player positions | G7: 6 | H7: Center position limit? (increasing to 5 automatically due to 20 roster spots)
A8: IR slots (again) | B8: DTD sucks to not be able to pick someone up and place them in somewhere | C8: Yahoo allows for an IR+ which seems to work for this well | G8: 7 | H8: In person draft next yeat? | J8: Keep in mind
A9: G-League | B9: Most rookies don't get real playing time in the NBA, thus it is important to have a place to put those rookies so people can draft and stash them | C9: 2-3 g-league spots, eligible only to rookies and sophomores, designated at beginning of the season, could be adjusted at all star break, cannot be used in starting lineup | D9: On ESPN this may just be "locked" players in Free Agency | G9: 8 | H9: Weekly highest scorer? (Gold) | J9: Majority | K9: Passed | L9: $20 win per weekly highest scorer | M9: increases dues by $36 per person | N9: $136 charge if doing dues for next year
A10: Yahoo | C10: "Start active players" button
A11: In-person draft? | B11: Do we want to try and coordinate drafting in person next year? If so, where would we want to go?
A12: Should it be a dynasty? | B12: For competitiveness year to year, could 10 keepers work better? More roster turnover?

Sheet Offseason PPG Projection
A1: 2022 offseason | B1: 20+ Scorers | C1: 25+ Scorers | D1: 30+ Scorers | E1: 35+ Scorers | F1: 40+ Scorers
A2: Trager | B2: 18 | C2: 12 | D2: 9 | E2: 3 | F2: 0
A3: Moss | B3: 23 | C3: 16 | D3: 13 | E3: 7 | F3: 5
A4: Zujewski | B4: 15 | C4: 13 | D4: 5 | E4: 4 | F4: 3
A5: Berke | B5: 17 | C5: 11 | D5: 6 | E5: 5 | F5: 5
A6: Green | B6: 19 | C6: 13 | D6: 8 | E6: 5 | F6: 2
A7: Gold | B7: 18 | C7: 12 | D7: 7 | E7: 4 | F7: 1
A8: Delaney | B8: 22 | C8: 14 | D8: 10 | E8: 7 | F8: 5
A9: Vlandis | B9: 20 | C9: 18 | D9: 14 | E9: 8 | F9: 2
A10: Jowkar | B10: 13 | C10: 9 | D10: 7 | E10: 5 | F10: 3
A11: Kelvin | B11: 22 | C11: 17 | D11: 13 | E11: 7 | F11: 6

Sheet OG 2020 Draft
A1: Round | B1: Pick | C1: Pick (Overall) | D1: Team Selecting
A2: 1 | B2: 1 | C2: 1 | D2: Delaney | E2: Luka Doncic
B3: 2 | C3: 2 | D3: Berke | E3: Giannis Antetokounmpo | I3: Sex Land | M3: Herro Ball | Q3: Washed Kings
B4: 3 | C4: 3 | D4: Moss | E4: Jayson Tatum | I4: NO. | J4: PLAYER | K4: ROUND | M4: NO. | N4: PLAYER | O4: ROUND | Q4: NO. | R4: PLAYER | S4: ROUND
B5: 4 | C5: 4 | D5: Zujewski | E5: Anthony Davis | I5: 10 | J5: James Harden Bkn, SG | K5: 1 | M5: 7 | N5: Zion Williamson NO, PF | O5: 1 | Q5: 1 | R5: Luka Doncic Dal, PG | S5: 1
B6: 5 | C6: 5 | D6: Peterson | E6: Nikola Jokic | I6: 11 | J6: Joel Embiid Phi, C | K6: 2 | M6: 14 | N6: Damian Lillard Por, PG | O6: 2 | Q6: 20 | R6: LeBron James LAL, SF | S6: 2
B7: 6 | C7: 6 | D7: Vlandis | E7: Karl-Anthony Towns | I7: 30 | J7: De'Aaron Fox Sac, PG | K7: 3 | M7: 27 | N7: Kyrie Irving Bkn, PG | O7: 3 | Q7: 21 | R7: Kevin Durant Bkn, SF | S7: 3
B8: 7 | C8: 7 | D8: Jowkar | E8: Zion Williamson | I8: 31 | J8: John Collins Atl, PF | K8: 4 | M8: 34 | N8: Michael Porter Jr. Den, SF | O8: 4 | Q8: 40 | R8: Nikola Vucevic Orl, C | S8: 4
B9: 8 | C9: 8 | D9: Green | E9: Trae Young | I9: 50 | J9: Christian Wood Hou, C | K9: 5 | M9: 47 | N9: Buddy Hield Sac, SG | O9: 5 | Q9: 41 | R9: Kelly Oubre Jr. GS, PF | S9: 5
B10: 9 | C10: 9 | D10: Gold | E10: Devin Booker | I10: 51 | J10: Lonzo Ball NO, PG | K10: 6 | M10: 54 | N10: Tyler Herro Mia, SG | O10: 6 | Q10: 60 | R10: Dennis Schroder LAL, PG | S10: 6
B11: 10 | C11: 10 | D11: Trager | E11: James Harden | I11: 70 | J11: DeMar DeRozan SA, SG | K11: 7 | M11: 67 | N11: Lauri Markkanen Chi, PF | O11: 7 | Q11: 61 | R11: Steven Adams NO, C | S11: 7
A12: 2 | B12: 1 | C12: 11 | D12: Trager | E12: Joel Embiid | I12: 71 | J12: Mitchell Robinson NY, C | K12: 8 | M12: 74 | N12: Aaron Gordon Orl, PF | O12: 8 | Q12: 80 | R12: Jerami Grant Det, SF | S12: 8
B13: 2 | C13: 12 | D13: Gold | E13: Ben Simmons | I13: 90 | J13: Marcus Smart Bos, SG | K13: 9 | M13: 87 | N13: Montrezl Harrell LAL, C | O13: 9 | Q13: 81 | R13: Collin Sexton Cle, SG | S13: 9
B14: 3 | C14: 13 | D14: Green | E14: Bradley Beal | I14: 91 | J14: Wendell Carter Jr. Chi, C | K14: 10 | M14: 94 | N14: Jordan Clarkson Utah, SG | O14: 10 | Q14: 100 | R14: Eric Bledsoe NO, PG | S14: 10
B15: 4 | C15: 14 | D15: Jowkar | E15: Damian Lillard | I15: 110 | J15: Miles Bridges Cha, SF | K15: 11 | M15: 107 | N15: Klay Thompson GS, SG | O15: 11 | Q15: 101 | R15: Richaun Holmes Sac, C | S15: 11
B16: 5 | C16: 15 | D16: Vlandis | E16: Stephen Curry | I16: 111 | J16: Al Horford OKC, PF | K16: 12 | M16: 114 | N16: Seth Curry Phi, SG | O16: 12 | Q16: 120 | R16: Lou Williams LAC, SG | S16: 12
B17: 6 | C17: 16 | D17: Peterson | E17: Deandre Ayton | I17: 130 | J17: Donte DiVincenzo Mil, SG | K17: 13 | M17: 127 | N17: Mike Conley Utah, PG | O17: 13 | Q17: 121 | R17: Serge Ibaka LAC, C | S17: 13
B18: 7 | C18: 17 | D18: Zujewski | E18: Pascal Siakam | I18: 131 | J18: Deni Avdija Wsh, SF | K18: 14 | M18: 134 | N18: DeMarcus Cousins Hou, C | O18: 14 | Q18: 140 | R18: Tim Hardaway Jr. Dal, SG | S18: 14
B19: 8 | C19: 18 | D19: Moss | E19: Bam Adebayo | I19: 150 | J19: Darius Garland Cle, PG | K19: 15 | M19: 147 | N19: Joe Ingles Utah, SF | O19: 15 | Q19: 141 | R19: Derrick Rose NY, PG | S19: 15
B20: 9 | C20: 19 | D20: Berke | E20: Brandon Ingram | I20: 151 | J20: Darius Bazley OKC, SF | K20: 16 | M20: 154 | N20: Rudy Gay SA, PF | O20: 16 | Q20: 160 | R20: Jarrett Culver Min, SG | S20: 16
B21: 10 | C21: 20 | D21: Delaney | E21: LeBron James | I21: 170 | J21: Aleksej Pokusevski OKC, PF | K21: 17 | M21: 167 | N21: Onyeka Okongwu Atl, C | O21: 17 | Q21: 161 | R21: Dario Saric Phx, PF | S21: 17
A22: 3 | B22: 1 | C22: 21 | D22: Delaney | E22: Kevin Durant
B23: 2 | C23: 22 | D23: Berke | E23: Shai Gilgeous-Alexander | I23: Ice Trae ❄️ | M23: Morey Ball | Q23: Always Droppin Dimes
B24: 3 | C24: 23 | D24: Moss | E24: Ja Morant | I24: NO. | J24: PLAYER | K24: ROUND | M24: NO. | N24: PLAYER | O24: ROUND | Q24: NO. | R24: PLAYER | S24: ROUND
B25: 4 | C25: 24 | D25: Zujewski | E25: Kawhi Leonard | I25: 8 | J25: Trae Young Atl, PG | K25: 1 | M25: 3 | N25: Jayson Tatum Bos, PF | O25: 1 | Q25: 5 | R25: Nikola Jokic Den, C | S25: 1
B26: 5 | C26: 25 | D26: Peterson | E26: Donovan Mitchell | I26: 13 | J26: Bradley Beal Wsh, SG | K26: 2 | M26: 18 | N26: Bam Adebayo Mia, C | O26: 2 | Q26: 16 | R26: Deandre Ayton Phx, C | S26: 2
B27: 6 | C27: 26 | D27: Vlandis | E27: D'Angelo Russell | I27: 28 | J27: Domantas Sabonis Ind, PF | K27: 3 | M27: 23 | N27: Ja Morant Mem, PG | O27: 3 | Q27: 25 | R27: Donovan Mitchell Utah, SG | S27: 3
B28: 7 | C28: 27 | D28: Jowkar | E28: Kyrie Irving | I28: 33 | J28: Zach LaVine Chi, SG | K28: 4 | M28: 38 | N28: Rudy Gobert Utah, C | O28: 4 | Q28: 36 | R28: Jimmy Butler Mia, SF | S28: 4
B29: 8 | C29: 28 | D29: Green | E29: Domantas Sabonis | I29: 48 | J29: Jaren Jackson Jr. Mem, PF | K29: 5 | M29: 43 | N29: Khris Middleton Mil, SF | O29: 5 | Q29: 45 | R29: CJ McCollum Por, SG | S29: 5
B30: 9 | C30: 29 | D30: Gold | E30: Jamal Murray | I30: 53 | J30: Jusuf Nurkic Por, C | K30: 6 | M30: 58 | N30: Malcolm Brogdon Ind, PG | O30: 6 | Q30: 56 | R30: Victor Oladipo Hou, SG | S30: 6
B31: 10 | C31: 30 | D31: Trager | E31: De'Aaron Fox | I31: 68 | J31: RJ Barrett NY, SG | K31: 7 | M31: 63 | N31: Tobias Harris Phi, SF | O31: 7 | Q31: 65 | R31: Myles Turner Ind, C | S31: 7
A32: 4 | B32: 1 | C32: 31 | D32: Trager | E32: John Collins | I32: 73 | J32: Killian Hayes Det, PG | K32: 8 | M32: 78 | N32: Duncan Robinson Mia, SG | O32: 8 | Q32: 76 | R32: Devonte' Graham Cha, PG | S32: 8
B33: 2 | C33: 32 | D33: Gold | E33: Kristaps Porzingis | I33: 88 | J33: Marvin Bagley III Sac, PF | K33: 9 | M33: 83 | N33: OG Anunoby Tor, SF | O33: 9 | Q33: 85 | R33: Clint Capela Atl, C | S33: 9
B34: 3 | C34: 33 | D34: Green | E34: Zach LaVine | I34: 93 | J34: Anthony Edwards Min, SG | K34: 10 | M34: 98 | N34: Jonas Valanciunas Mem, C | O34: 10 | Q34: 96 | R34: Kemba Walker Bos, PG | S34: 10
B35: 4 | C35: 34 | D35: Jowkar | E35: Michael Porter Jr. | I35: 108 | J35: Mikal Bridges Phx, SF | K35: 11 | M35: 103 | N35: Dejounte Murray SA, PG | O35: 11 | Q35: 105 | R35: LaMarcus Aldridge SA, PF | S35: 11
B36: 5 | C36: 35 | D36: Vlandis | E36: Russell Westbrook | I36: 113 | J36: Spencer Dinwiddie Bkn, PG | K36: 12 | M36: 118 | N36: Tyrese Haliburton Sac, PG | O36: 12 | Q36: 116 | R36: Otto Porter Jr. Chi, SF | S36: 12
B37: 6 | C37: 36 | D37: Peterson | E37: Jimmy Butler | I37: 128 | J37: Jonathan Isaac Orl, SF | K37: 13 | M37: 123 | N37: Patrick Williams Chi, SF | O37: 13 | Q37: 125 | R37: Danilo Gallinari Atl, PF | S37: 13
B38: 7 | C38: 37 | D38: Zujewski | E38: Paul George | I38: 133 | J38: Thomas Bryant Wsh, C | K38: 14 | M38: 138 | N38: Ivica Zubac LAC, C | O38: 14 | Q38: 136 | R38: Kendrick Nunn Mia, SG | S38: 14
B39: 8 | C39: 38 | D39: Moss | E39: Rudy Gobert | I39: 148 | J39: Norman Powell Tor, SG | K39: 15 | M39: 143 | N39: Matisse Thybulle Phi, SF | O39: 15 | Q39: 145 | R39: Kevin Huerter Atl, SG | S39: 15
B40: 9 | C40: 39 | D40: Berke | E40: Jrue Holiday | I40: 153 | J40: Bol Bol Den, C | K40: 16 | M40: 158 | N40: Nemanja Bjelica Sac, PF | O40: 16 | Q40: 156 | R40: Elfrid Payton NY, PG | S40: 16
B41: 10 | C41: 40 | D41: Delaney | E41: Nikola Vucevic | I41: 168 | J41: Kira Lewis Jr. NO, PG | K41: 17 | M41: 163 | N41: Tyrese Maxey Phi, SG | O41: 17 | Q41: 165 | R41: Larry Nance Jr. Cle, PF | S41: 17
A42: 5 | B42: 1 | C42: 41 | D42: Delaney | E42: Kelly Oubre Jr.
B43: 2 | C43: 42 | D43: Berke | E43: Fred VanVleet | I43: Kelvin Got No Dimes | M43: Deepwater LaVert ✊ | Q43: Minnesota TimberWobs
B44: 3 | C44: 43 | D44: Moss | E44: Khris Middleton | I44: NO. | J44: PLAYER | K44: ROUND | M44: NO. | N44: PLAYER | O44: ROUND | Q44: NO. | R44: PLAYER | S44: ROUND
B45: 4 | C45: 44 | D45: Zujewski | E45: Andre Drummond | I45: 2 | J45: Giannis Antetokounmpo Mil, PF | K45: 1 | M45: 9 | N45: Devin Booker Phx, SG | O45: 1 | Q45: 6 | R45: Karl-Anthony Towns Min, C | S45: 1
B46: 5 | C46: 45 | D46: Peterson | E46: CJ McCollum | I46: 19 | J46: Brandon Ingram NO, SF | K46: 2 | M46: 12 | N46: Ben Simmons Phi, PG | O46: 2 | Q46: 15 | R46: Stephen Curry GS, PG | S46: 2
B47: 6 | C47: 46 | D47: Vlandis | E47: LaMelo Ball | I47: 22 | J47: Shai Gilgeous-Alexander OKC, SG | K47: 3 | M47: 29 | N47: Jamal Murray Den, PG | O47: 3 | Q47: 26 | R47: D'Angelo Russell Min, PG | S47: 3
B48: 7 | C48: 47 | D48: Jowkar | E48: Buddy Hield | I48: 39 | J48: Jrue Holiday Mil, PG | K48: 4 | M48: 32 | N48: Kristaps Porzingis Dal, PF | O48: 4 | Q48: 35 | R48: Russell Westbrook Wsh, PG | S48: 4
B49: 8 | C49: 48 | D49: Green | E49: Jaren Jackson Jr. | I49: 42 | J49: Fred VanVleet Tor, SG | K49: 5 | M49: 49 | N49: Jaylen Brown Bos, SG | O49: 5 | Q49: 46 | R49: LaMelo Ball Cha, PG | S49: 5
B50: 9 | C50: 49 | D50: Gold | E50: Jaylen Brown | I50: 59 | J50: Chris Paul Phx, PG | K50: 6 | M50: 52 | N50: T.J. Warren Ind, SF | O50: 6 | Q50: 55 | R50: Brandon Clarke Mem, PF | S50: 6
B51: 10 | C51: 50 | D51: Trager | E51: Christian Wood | I51: 62 | J51: Gordon Hayward Cha, SF | K51: 7 | M51: 69 | N51: James Wiseman GS, C | O51: 7 | Q51: 66 | R51: Rui Hachimura Wsh, PF | S51: 7
A52: 6 | B52: 1 | C52: 51 | D52: Trager | E52: Lonzo Ball | I52: 79 | J52: Kyle Lowry Tor, PG | K52: 8 | M52: 72 | N52: Caris LeVert Ind, SG | O52: 8 | Q52: 75 | R52: Coby White Chi, PG | S52: 8
B53: 2 | C53: 52 | D53: Gold | E53: T.J. Warren | I53: 82 | J53: Hassan Whiteside Sac, C | K53: 9 | M53: 89 | N53: Davis Bertans Wsh, PF | O53: 9 | Q53: 86 | R53: Obi Toppin NY, PF | S53: 9
B54: 3 | C54: 53 | D54: Green | E54: Jusuf Nurkic | I54: 99 | J54: Andrew Wiggins GS, SF | K54: 10 | M54: 92 | N54: Bogdan Bogdanovic Atl, SG | O54: 10 | Q54: 95 | R54: P.J. Washington Cha, PF | S54: 10
B55: 4 | C55: 54 | D55: Jowkar | E55: Tyler Herro | I55: 102 | J55: Julius Randle NY, PF | K55: 11 | M55: 109 | N55: Blake Griffin Det, PF | O55: 11 | Q55: 106 | R55: Malik Beasley Min, SG | S55: 11
B56: 5 | C56: 55 | D56: Vlandis | E56: Brandon Clarke | I56: 119 | J56: Kevin Love Cle, PF | K56: 12 | M56: 112 | N56: Bojan Bogdanovic Utah, SF | O56: 12 | Q56: 115 | R56: Delon Wright Det, SG | S56: 12
B57: 6 | C57: 56 | D57: Peterson | E57: Victor Oladipo | I57: 122 | J57: Harrison Barnes Sac, SF | K57: 13 | M57: 129 | N57: Luke Kennard LAC, SG | O57: 13 | Q57: 126 | R57: Devin Vassell SA, SG | S57: 13
B58: 7 | C58: 57 | D58: Zujewski | E58: John Wall | I58: 139 | J58: Joe Harris Bkn, SG | K58: 14 | M58: 132 | N58: Brook Lopez Mil, C | O58: 14 | Q58: 135 | R58: Dillon Brooks Mem, SG | S58: 14
B59: 8 | C59: 58 | D59: Moss | E59: Malcolm Brogdon | I59: 142 | J59: Ricky Rubio Min, PG | K59: 15 | M59: 149 | N59: Harry Giles III Por, PF | O59: 15 | Q59: 146 | R59: Daniel Theis Bos, C | S59: 15
B60: 9 | C60: 59 | D60: Berke | E60: Chris Paul | I60: 159 | J60: DeAndre Jordan Bkn, C | K60: 16 | M60: 152 | N60: Kyle Kuzma LAL, PF | O60: 16 | Q60: 155 | R60: Isaac Okoro Cle, SF | S60: 16
B61: 10 | C61: 60 | D61: Delaney | E61: Dennis Schroder | I61: 162 | J61: Nerlens Noel NY, C | K61: 17 | M61: 169 | N61: Cole Anthony Orl, PG | O61: 17 | Q61: 166 | R61: Willie Cauley-Stein Dal, C | S61: 17
A62: 7 | B62: 1 | C62: 61 | D62: Delaney | E62: Steven Adams
B63: 2 | C63: 62 | D63: Berke | E63: Gordon Hayward | I63: Z Man The Juice
B64: 3 | C64: 63 | D64: Moss | E64: Tobias Harris | I64: NO. | J64: PLAYER | K64: ROUND
B65: 4 | C65: 64 | D65: Zujewski | E65: Robert Covington | I65: 4 | J65: Anthony Davis LAL, PF | K65: 1
B66: 5 | C66: 65 | D66: Peterson | E66: Myles Turner | I66: 17 | J66: Pascal Siakam Tor, PF | K66: 2
B67: 6 | C67: 66 | D67: Vlandis | E67: Rui Hachimura | I67: 24 | J67: Kawhi Leonard LAC, SF | K67: 3
B68: 7 | C68: 67 | D68: Jowkar | E68: Lauri Markkanen | I68: 37 | J68: Paul George LAC, SF | K68: 4
B69: 8 | C69: 68 | D69: Green | E69: RJ Barrett | I69: 44 | J69: Andre Drummond Cle, C | K69: 5
B70: 9 | C70: 69 | D70: Gold | E70: James Wiseman | I70: 57 | J70: John Wall Hou, PG | K70: 6
B71: 10 | C71: 70 | D71: Trager | E71: DeMar DeRozan | I71: 64 | J71: Robert Covington Por, PF | K71: 7
A72: 8 | B72: 1 | C72: 71 | D72: Trager | E72: Mitchell Robinson | I72: 77 | J72: Draymond Green GS, PF | K72: 8
B73: 2 | C73: 72 | D73: Gold | E73: Caris LeVert | I73: 84 | J73: Josh Richardson Dal, SG | K73: 9
B74: 3 | C74: 73 | D74: Green | E74: Killian Hayes | I74: 97 | J74: Markelle Fultz Orl, PG | K74: 10
B75: 4 | C75: 74 | D75: Jowkar | E75: Aaron Gordon | I75: 104 | J75: Jarrett Allen Cle, C | K75: 11
B76: 5 | C76: 75 | D76: Vlandis | E76: Coby White | I76: 117 | J76: Evan Fournier Orl, SG | K76: 12
B77: 6 | C77: 76 | D77: Peterson | E77: Devonte' Graham | I77: 124 | J77: Terry Rozier Cha, PG | K77: 13
B78: 7 | C78: 77 | D78: Zujewski | E78: Draymond Green | I78: 137 | J78: Goran Dragic Mia, PG | K78: 14
B79: 8 | C79: 78 | D79: Moss | E79: Duncan Robinson | I79: 144 | J79: Chris Boucher Tor, PF | K79: 15
B80: 9 | C80: 79 | D80: Berke | E80: Kyle Lowry | I80: 157 | J80: Aaron Nesmith Bos, SF | K80: 16
B81: 10 | C81: 80 | D81: Delaney | E81: Jerami Grant | I81: 164 | J81: Josh Hart NO, SG | K81: 17
A82: 9 | B82: 1 | C82: 81 | D82: Delaney | E82: Collin Sexton
B83: 2 | C83: 82 | D83: Berke | E83: Hassan Whiteside
B84: 3 | C84: 83 | D84: Moss | E84: OG Anunoby
B85: 4 | C85: 84 | D85: Zujewski | E85: Josh Richardson
B86: 5 | C86: 85 | D86: Peterson | E86: Clint Capela
B87: 6 | C87: 86 | D87: Vlandis | E87: Obi Toppin
B88: 7 | C88: 87 | D88: Jowkar | E88: Montrezl Harrell
B89: 8 | C89: 88 | D89: Green | E89: Marvin Bagley III
B90: 9 | C90: 89 | D90: Gold | E90: Davis Bertans
B91: 10 | C91: 90 | D91: Trager | E91: Marcus Smart
A92: 10 | B92: 1 | C92: 91 | D92: Trager | E92: Wendell Carter Jr.
B93: 2 | C93: 92 | D93: Gold | E93: Bogdan Bogdanovic
B94: 3 | C94: 93 | D94: Green | E94: Anthony Edwards
B95: 4 | C95: 94 | D95: Jowkar | E95: Jordan Clarkson
B96: 5 | C96: 95 | D96: Vlandis | E96: PJ Washington
B97: 6 | C97: 96 | D97: Peterson | E97: Kemba Walker
B98: 7 | C98: 97 | D98: Zujewski | E98: Markelle Fultz
B99: 8 | C99: 98 | D99: Moss | E99: Jonas Valanciunas
B100: 9 | C100: 99 | D100: Berke | E100: Andrew Wiggins
...

Sheet 2026 Redistribution Draft
A1: 2026 Redistribution Draft | F1: # | G1: Players available (From Teams) | H1: Dynasty Rank (Lawson) | I1: Players available (FA) | K1: Draft - __/__/26 | L1: Pick | M1: Team 1 (Logan's) | N1: Team 2 (Moss's)
E2: Picks available | F2: 1 | G2: Giannis Antetokounmpo | H2: =VLOOKUP(G2, 'Player rankings (Lawson Ranks)'!A:B, 2, FALSE) -> 10 | I2: Goga Bitadze | J2: =VLOOKUP(I2, 'Player rankings (Lawson Ranks)'!A:B, 2, FALSE) -> 163 | L2: 1
A3: Must select: | E3: Green 2029 1st round | F3: 2 | G3: Jayson Tatum | H3: =VLOOKUP(G3, 'Player rankings (Lawson Ranks)'!A:B, 2, FALSE) -> 12 | I3: Josh Minott | J3: =VLOOKUP(I3, 'Player rankings (Lawson Ranks)'!A:B, 2, FALSE) -> 191 | L3: 2
A4: 22 players (maybe 20?) | F4: 3 | G4: Tyrese Haliburton | H4: =VLOOKUP(G4, 'Player rankings (Lawson Ranks)'!A:B, 2, FALSE) -> 13 | I4: Jaylen Wells | J4: =VLOOKUP(I4, 'Player rankings (Lawson Ranks)'!A:B, 2, FALSE) -> 195 | L4: 3
F5: 4 | G5: De'Aaron Fox | H5: =VLOOKUP(G5, 'Player rankings (Lawson Ranks)'!A:B, 2, FALSE) -> 31 | I5: Rui Hachimura | J5: =VLOOKUP(I5, 'Player rankings (Lawson Ranks)'!A:B, 2, FALSE) -> 203 | L5: 4
A6: Team 1 (Logan) pick situation: | F6: 5 | G6: Brandon Miller | H6: =VLOOKUP(G6, 'Player rankings (Lawson Ranks)'!A:B, 2, FALSE) -> 40 | I6: Keon Ellis | J6: =VLOOKUP(I6, 'Player rankings (Lawson Ranks)'!A:B, 2, FALSE) -> 210 | L6: 5
A7: Team 1 enters with only their 2030 1st round pick, all of their firsts are owned by other teams | F7: 6 | G7: Tyler Herro | H7: =VLOOKUP(G7, 'Player rankings (Lawson Ranks)'!A:B, 2, FALSE) -> 62 | I7: Obi Toppin | J7: =VLOOKUP(I7, 'Player rankings (Lawson Ranks)'!A:B, 2, FALSE) -> 211 | L7: 6
A8: For the years 2026-29 drafts they will get the pick just below their 1st round pick unless their pick is top 3 in which case it will be above their pick. (could also consider always below the 1st but a top 3 pick is an extra high 2nd rounder, or nothing) | F8: 7 | G8: Ja Morant | H8: =VLOOKUP(G8, 'Player rankings (Lawson Ranks)'!A:B, 2, FALSE) -> 63 | I8: Jake LaRavia | J8: =VLOOKUP(I8, 'Player rankings (Lawson Ranks)'!A:B, 2, FALSE) -> 212 | L8: 7
A9: 2026, 2027, 2028, and 2029 draft. Team 1 cannot move their 2030/31 1sts as a result | F9: 8 | G9: Kevin Durant | H9: =VLOOKUP(G9, 'Player rankings (Lawson Ranks)'!A:B, 2, FALSE) -> 66 | I9: Jase Richardson | J9: =VLOOKUP(I9, 'Player rankings (Lawson Ranks)'!A:B, 2, FALSE) -> 220 | L9: 8
A10: Team 1 does not own any of their 2nds in 26-30, if their pick falls top 3 could consider giving them a high 2nd back instead of the higher of the top picks | F10: 9 | G10: Donovan Clingan | H10: =VLOOKUP(G10, 'Player rankings (Lawson Ranks)'!A:B, 2, FALSE) -> 67 | I10: Quinten Post | J10: =VLOOKUP(I10, 'Player rankings (Lawson Ranks)'!A:B, 2, FALSE) -> 222 | L10: 9
F11: 10 | G11: OG Anunoby | H11: =VLOOKUP(G11, 'Player rankings (Lawson Ranks)'!A:B, 2, FALSE) -> 82 | I11: Jamal Shead | J11: =VLOOKUP(I11, 'Player rankings (Lawson Ranks)'!A:B, 2, FALSE) -> 229 | L11: 10
A12: Team 2 (Moss) pick situation | F12: 11 | G12: Brandon Ingram | H12: =VLOOKUP(G12, 'Player rankings (Lawson Ranks)'!A:B, 2, FALSE) -> 88 | I12: Kyle Kuzma | J12: =VLOOKUP(I12, 'Player rankings (Lawson Ranks)'!A:B, 2, FALSE) -> 230 | L12: 11
A13: Team 2 enters with their 29&30 1st & 2nd round picks along with a 2027 1st with lesser swap rights between it and a bottom half team | F13: 12 | G13: Jalen Green | H13: =VLOOKUP(G13, 'Player rankings (Lawson Ranks)'!A:B, 2, FALSE) -> 89 | I13: Alex Caruso | J13: =VLOOKUP(I13, 'Player rankings (Lawson Ranks)'!A:B, 2, FALSE) -> 231 | L13: 12
A14: In 2026 & 2028 team 2 would get to pick adjacent to their own pick, if it's top 3 then could do higher pick or provide an extra 2nd as compensation or nothing | F14: 13 | G14: LeBron James | H14: =VLOOKUP(G14, 'Player rankings (Lawson Ranks)'!A:B, 2, FALSE) -> 94 | I14: Justin Champagnie | J14: =VLOOKUP(I14, 'Player rankings (Lawson Ranks)'!A:B, 2, FALSE) -> 235 | L14: 13
A15: Team 2's 2029/30 1st round picks are frozen unelss they get another 1st round pick | F15: 14 | G15: Mikal Bridges | H15: =VLOOKUP(G15, 'Player rankings (Lawson Ranks)'!A:B, 2, FALSE) -> 100 | I15: Tre Mann | J15: =VLOOKUP(I15, 'Player rankings (Lawson Ranks)'!A:B, 2, FALSE) -> 236 | L15: 14
F16: 15 | G16: Joel Embiid | H16: =VLOOKUP(G16, 'Player rankings (Lawson Ranks)'!A:B, 2, FALSE) -> 102 | I16: Mouhamed Gueye | J16: =VLOOKUP(I16, 'Player rankings (Lawson Ranks)'!A:B, 2, FALSE) -> 239 | L16: 15
A17: Evening out?: | F17: 16 | G17: Josh Hart | H17: =VLOOKUP(G17, 'Player rankings (Lawson Ranks)'!A:B, 2, FALSE) -> 108 | I17: Lonzo Ball | J17: =VLOOKUP(I17, 'Player rankings (Lawson Ranks)'!A:B, 2, FALSE) -> 241 | L17: 16
A18: Consider giving Team 1 compensatory 2nds (mid-round?) in 29/30 to match with what Team 2 enters the redistribution draft with | F18: 17 | G18: Jimmy Butler III | H18: =VLOOKUP(G18, 'Player rankings (Lawson Ranks)'!A:B, 2, FALSE) -> 116 | I18: Isaiah Joe | J18: =VLOOKUP(I18, 'Player rankings (Lawson Ranks)'!A:B, 2, FALSE) -> 242 | L18: 17
F19: 18 | G19: Jakob Poeltl | H19: =VLOOKUP(G19, 'Player rankings (Lawson Ranks)'!A:B, 2, FALSE) -> 118 | I19: Rasheer Fleming | J19: =VLOOKUP(I19, 'Player rankings (Lawson Ranks)'!A:B, 2, FALSE) -> 244 | L19: 18
F20: 19 | G20: Myles Turner | H20: =VLOOKUP(G20, 'Player rankings (Lawson Ranks)'!A:B, 2, FALSE) -> 119 | I20: Andre Drummond | J20: =VLOOKUP(I20, 'Player rankings (Lawson Ranks)'!A:B, 2, FALSE) -> 253 | L20: 19
A21: Note: | F21: 20 | G21: Zach LaVine | H21: =VLOOKUP(G21, 'Player rankings (Lawson Ranks)'!A:B, 2, FALSE) -> 127 | I21: Jaylin Williams | J21: =VLOOKUP(I21, 'Player rankings (Lawson Ranks)'!A:B, 2, FALSE) -> 254 | L21: 20
A22: This feels needed because there can be such a difference between the top level guys and ones below them, so some compensation when their pick lands in lottery or top 3 makes some sense | F22: 21 | G22: Ronald Holland II | H22: =VLOOKUP(G22, 'Player rankings (Lawson Ranks)'!A:B, 2, FALSE) -> 136 | I22: Marcus Smart | J22: =VLOOKUP(I22, 'Player rankings (Lawson Ranks)'!A:B, 2, FALSE) -> 255 | L22: 21
A23: What to do with the awkward Green 2029 FRP? Lol | F23: 22 | G23: Jerami Grant | H23: =VLOOKUP(G23, 'Player rankings (Lawson Ranks)'!A:B, 2, FALSE) -> 143 | I23: Max Strus | J23: =VLOOKUP(I23, 'Player rankings (Lawson Ranks)'!A:B, 2, FALSE) -> 257 | L23: 22
F24: 23 | G24: Nikola Vučević | H24: =VLOOKUP(G24, 'Player rankings (Lawson Ranks)'!A:B, 2, FALSE) -> 147 | I24: Steven Adams | J24: =VLOOKUP(I24, 'Player rankings (Lawson Ranks)'!A:B, 2, FALSE) -> 259
A25: Draft Outcome: | F25: 24 | G25: Aaron Wiggins | H25: =VLOOKUP(G25, 'Player rankings (Lawson Ranks)'!A:B, 2, FALSE) -> 158 | I25: Tristan da Silva | J25: =VLOOKUP(I25, 'Player rankings (Lawson Ranks)'!A:B, 2, FALSE) -> 261
A26: Either way, that will create 12 1st round picks as the redistribution teams will get a first to use those years no matter what. | F26: 25 | G26: Rudy Gobert | H26: =VLOOKUP(G26, 'Player rankings (Lawson Ranks)'!A:B, 2, FALSE) -> 160 | I26: Trendon Watford | J26: =VLOOKUP(I26, 'Player rankings (Lawson Ranks)'!A:B, 2, FALSE) -> 267
F27: 26 | G27: Jared McCain | H27: =VLOOKUP(G27, 'Player rankings (Lawson Ranks)'!A:B, 2, FALSE) -> 167 | I27: Caris LeVert | J27: =VLOOKUP(I27, 'Player rankings (Lawson Ranks)'!A:B, 2, FALSE) -> 269
F28: 27 | G28: Jrue Holiday | H28: =VLOOKUP(G28, 'Player rankings (Lawson Ranks)'!A:B, 2, FALSE) -> 176 | I28: Tyler Kolek | J28: =VLOOKUP(I28, 'Player rankings (Lawson Ranks)'!A:B, 2, FALSE) -> 274
F29: 28 | G29: Scotty Pippen Jr. | H29: =VLOOKUP(G29, 'Player rankings (Lawson Ranks)'!A:B, 2, FALSE) -> 182 | I29: Cole Anthony | J29: =VLOOKUP(I29, 'Player rankings (Lawson Ranks)'!A:B, 2, FALSE) -> 275
F30: 29 | G30: Dillon Brooks | H30: =VLOOKUP(G30, 'Player rankings (Lawson Ranks)'!A:B, 2, FALSE) -> 196 | I30: Johnny Furphy | J30: =VLOOKUP(I30, 'Player rankings (Lawson Ranks)'!A:B, 2, FALSE) -> 278
F31: 30 | G31: DeMar DeRozan | H31: =VLOOKUP(G31, 'Player rankings (Lawson Ranks)'!A:B, 2, FALSE) -> 200 | I31: Dru Smith | J31: =VLOOKUP(I31, 'Player rankings (Lawson Ranks)'!A:B, 2, FALSE) -> 279
F32: 31 | G32: Kelly Oubre Jr. | H32: =VLOOKUP(G32, 'Player rankings (Lawson Ranks)'!A:B, 2, FALSE) -> 202 | I32: Johni Broome | J32: =VLOOKUP(I32, 'Player rankings (Lawson Ranks)'!A:B, 2, FALSE) -> 280
F33: 32 | G33: Luguentz Dort | H33: =VLOOKUP(G33, 'Player rankings (Lawson Ranks)'!A:B, 2, FALSE) -> 207 | I33: Pelle Larsson | J33: =VLOOKUP(I33, 'Player rankings (Lawson Ranks)'!A:B, 2, FALSE) -> 284
F34: 33 | G34: Adem Bona | H34: =VLOOKUP(G34, 'Player rankings (Lawson Ranks)'!A:B, 2, FALSE) -> 216 | I34: Kris Dunn | J34: =VLOOKUP(I34, 'Player rankings (Lawson Ranks)'!A:B, 2, FALSE) -> 287
F35: 34 | G35: Dennis Schröder | H35: =VLOOKUP(G35, 'Player rankings (Lawson Ranks)'!A:B, 2, FALSE) -> 233 | I35: Brooks Barnhizer | J35: =VLOOKUP(I35, 'Player rankings (Lawson Ranks)'!A:B, 2, FALSE) -> 288
F36: 35 | G36: Dominick Barlow | H36: =VLOOKUP(G36, 'Player rankings (Lawson Ranks)'!A:B, 2, FALSE) -> 234 | I36: Adou Thiero | J36: =VLOOKUP(I36, 'Player rankings (Lawson Ranks)'!A:B, 2, FALSE) -> 290
F37: 36 | G37: Sam Merrill | H37: =VLOOKUP(G37, 'Player rankings (Lawson Ranks)'!A:B, 2, FALSE) -> 237 | I37: Khris Middleton | J37: =VLOOKUP(I37, 'Player rankings (Lawson Ranks)'!A:B, 2, FALSE) -> 291
F38: 37 | G38: Jordan Walsh | H38: =VLOOKUP(G38, 'Player rankings (Lawson Ranks)'!A:B, 2, FALSE) -> 238 | I38: Moritz Wagner | J38: =VLOOKUP(I38, 'Player rankings (Lawson Ranks)'!A:B, 2, FALSE) -> 293
... F50: 49 | G50: Tim Hardaway Jr. | H50: =VLOOKUP(G50, 'Player rankings (Lawson Ranks)'!A:B, 2, FALSE) -> 368 | I50: Will Richard | J50: =VLOOKUP(I50, 'Player rankings (Lawson Ranks)'!A:B, 2, FALSE) -> 311
I51: Klay Thompson | J51: =VLOOKUP(I51, 'Player rankings (Lawson Ranks)'!A:B, 2, FALSE) -> 312
I52: Brook Lopez | J52: =VLOOKUP(I52, 'Player rankings (Lawson Ranks)'!A:B, 2, FALSE) -> 314
I53: Tyrese Proctor | J53: =VLOOKUP(I53, 'Player rankings (Lawson Ranks)'!A:B, 2, FALSE) -> 316
I54: Guerschon Yabusele | J54: =VLOOKUP(I54, 'Player rankings (Lawson Ranks)'!A:B, 2, FALSE) -> 317
I55: Micah Peavy | J55: =VLOOKUP(I55, 'Player rankings (Lawson Ranks)'!A:B, 2, FALSE) -> 318
I56: Julian Strawther | J56: =VLOOKUP(I56, 'Player rankings (Lawson Ranks)'!A:B, 2, FALSE) -> 319
I57: AJ Green | J57: =VLOOKUP(I57, 'Player rankings (Lawson Ranks)'!A:B, 2, FALSE) -> 321
I58: Jarred Vanderbilt | J58: =VLOOKUP(I58, 'Player rankings (Lawson Ranks)'!A:B, 2, FALSE) -> 322
I59: Drake Powell | J59: =VLOOKUP(I59, 'Player rankings (Lawson Ranks)'!A:B, 2, FALSE) -> 323
I60: Kevon Looney | J60: =VLOOKUP(I60, 'Player rankings (Lawson Ranks)'!A:B, 2, FALSE) -> 325
I61: Terance Mann | J61: =VLOOKUP(I61, 'Player rankings (Lawson Ranks)'!A:B, 2, FALSE) -> 326
I62: Justin Edwards | J62: =VLOOKUP(I62, 'Player rankings (Lawson Ranks)'!A:B, 2, FALSE) -> 327
... I200: Koby Brea | J200: =VLOOKUP(I200, 'Player rankings (Lawson Ranks)'!A:B, 2, FALSE) -> #N/A

Sheet 2020-2021 All Stars
A1: 2020-2021 All Stars on Each Roster
I4: Total All Stars on Roster
A5: East Starters | F5: West Starters | I5: Delaney | J5: 4
A6: Kyrie Irving | B6: Jowkar | C6: -->Zujewski | F6: Steph Curry | G6: Spencer | H6: ---> Kelvin | I6: Kelvin | J6: 3
A7: Bradley Beal | B7: Green | F7: Luka Doncic | G7: Delaney | I7: Logan | J7: 3
A8: Giannis Atetokounmpo | B8: Logan | F8: Lebron James | G8: Delaney | I8: Zujewski | J8: 3
A9: Kevin Durant | B9: Delaney | F9: Kawhi Leonard | G9: Zujewski | I9: Green | J9: 3
A10: Joel Embiid | B10: Kelvin | F10: Nikola Jokic | G10: Kelvin | H10: --> Jowkar | I10: Jowkar | J10: 3
I11: Gold | J11: 3
A12: East Reserves | F12: West Reserves | I12: Moss | J12: 2
A13: Jaylen Brown | B13: Gold | F13: Anthony Davis | G13: Zujewski | I13: Spencer | J13: 1
A14: James Harden | B14: Trager | C14: -->Logan | F14: Paul George | G14: Zujewski | H14: ---> Kelvin | I14: Trager | J14: 1
A15: Zach Lavine | B15: Green | F15: Rudy Gobert | G15: Kelvin
A16: Julius Randle | B16: Logan | F16: Damian Lillard | G16: Jowkar | H16: ---> Kelvin
A17: Ben Simmons | B17: Gold | F17: Donovan Mitchell | G17: Moss | H17: ---> Spencer
A18: Jayson Tatum | B18: Moss | F18: Chris Paul | G18: Logan
A19: Nikola Vucevic | B19: Delaney | F19: Zion Williamson | G19: Jowkar
A20: Damontas Sabonis | B20: Green | F20: Devin Booker | G20: Gold
F21: Mike Conley | G21: Kelvin

Sheet Player rankings (Lawson Ranks)
A1: Jan 1, 2026 ranks | D1: 45962 | G1: 45901 | J1: 45839 | M1: 45778 | P1: 45717 | S1: 45658 | V1: 45627 | Y1: 45597 | AB1: October 2024 rnaks 2.0 | AE1: October 2024 ranks | AH1: July Ranks | AK1: June Ranks | AN1: April Ranks (w/Rookies) | AQ1: March Ranks (w/Rookies) | AT1: Trade Deadline Rank (w/Rookies) | AW1: February Player Rank (w/Rookies) | AZ1: January Player Rank (w/Rookies) | BC1: December (2) Player Rank | BF1: December Player Rank | BI1: November Player Rank | BL1: October Player Rank | BM1: Rank
A2: Victor Wembanyama | B2: 1 | D2: Victor Wembanyama | E2: 1 | G2: Victor Wembanyama | H2: 1 | J2: Victor Wembanyama | K2: 1 | M2: Victor Wembanyama | N2: 1 | P2: Victor Wembanyama | Q2: 1 | S2: Victor Wembanyama | T2: 1 | V2: Victor Wembanyama | W2: 1 | Y2: Victor Wembanyama | Z2: 1 | AB2: Victor Wembanyama | AC2: 1 | AE2: Victor Wembanyama | AF2: 1 | AH2: Victor Wembanyama | AI2: 1 | AK2: Victor Wembanyama | AL2: 1 | AN2: Victor Wembanyama | AO2: 1 | AQ2: Victor Wembanyama | AR2: 1 | AT2: Victor Wembanyama | AU2: 1 | AW2: Victor Wembanyama | AX2: 1 | AZ2: Victor Wembanyama | BA2: 1 | BC2: Victor Wembanyama | BD2: 1 | BF2: Luka Dončić | BG2: 1 | BI2: Luka Dončić | BJ2: 1 | BL2: Luka Dončić | BM2: 1
A3: Luka Dončić | B3: 2 | D3: Nikola Jokić | E3: 2 | G3: Nikola Jokić | H3: 2 | J3: Nikola Jokić | K3: 2 | M3: Nikola Jokić | N3: 2 | P3: Nikola Jokić | Q3: 2 | S3: Nikola Jokić | T3: 2 | V3: Nikola Jokić | W3: 2 | Y3: Luka Dončić | Z3: 2 | AB3: Luka Dončić | AC3: 2 | AE3: Luka Dončić | AF3: 2 | AH3: Luka Dončić | AI3: 2 | AK3: Luka Dončić | AL3: 2 | AN3: Luka Dončić | AO3: 2 | AQ3: Luka Dončić | AR3: 2 | AT3: Luka Dončić | AU3: 2 | AW3: Luka Dončić | AX3: 2 | AZ3: Luka Dončić | BA3: 2 | BC3: Luka Dončić | BD3: 2 | BF3: Nikola Jokić | BG3: 2 | BI3: Nikola Jokić | BJ3: 2 | BL3: Nikola Jokić | BM3: 2
A4: Nikola Jokić | B4: 3 | D4: Luka Dončić | E4: 3 | G4: Luka Dončić | H4: 3 | J4: Shai Gilgeous-Alexander | K4: 3 | M4: Luka Dončić | N4: 3 | P4: Luka Dončić | Q4: 3 | S4: Luka Dončić | T4: 3 | V4: Luka Dončić | W4: 3 | Y4: Nikola Jokić | Z4: 3 | AB4: Nikola Jokić | AC4: 3 | AE4: Nikola Jokić | AF4: 3 | AH4: Nikola Jokić | AI4: 3 | AK4: Nikola Jokić | AL4: 3 | AN4: Nikola Jokić | AO4: 3 | AQ4: Nikola Jokić | AR4: 3 | AT4: Nikola Jokić | AU4: 3 | AW4: Nikola Jokić | AX4: 3 | AZ4: Nikola Jokić | BA4: 3 | BC4: Nikola Jokić | BD4: 3 | BF4: Victor Wembanyama | BG4: 3 | BI4: Victor Wembanyama | BJ4: 3 | BL4: Victor Wembanyama | BM4: 3
A5: Shai Gilgeous-Alexander | B5: 4 | D5: Shai Gilgeous-Alexander | E5: 4 | G5: Shai Gilgeous-Alexander | H5: 4 | J5: Luka Dončić | K5: 4 | M5: Shai Gilgeous-Alexander | N5: 4 | P5: Shai Gilgeous-Alexander | Q5: 4 | S5: Shai Gilgeous-Alexander | T5: 4 | V5: Shai Gilgeous-Alexander | W5: 4 | Y5: Shai Gilgeous-Alexander | Z5: 4 | AB5: Shai Gilgeous-Alexander | AC5: 4 | AE5: Shai Gilgeous-Alexander | AF5: 4 | AH5: Shai Gilgeous-Alexander | AI5: 4 | AK5: Shai Gilgeous-Alexander | AL5: 4 | AN5: Shai Gilgeous-Alexander | AO5: 4 | AQ5: Shai Gilgeous-Alexander | AR5: 4 | AT5: Tyrese Haliburton | AU5: 4 | AW5: Tyrese Haliburton | AX5: 4 | AZ5: Joel Embiid | BA5: 4 | BC5: Joel Embiid | BD5: 4 | BF5: Joel Embiid | BG5: 4 | BI5: Joel Embiid | BJ5: 4 | BL5: Shai Gilgeous-Alexander | BM5: 4
A6: Cade Cunningham | B6: 5 | D6: Cade Cunningham | E6: 5 | G6: Cade Cunningham | H6: 5 | J6: Cade Cunningham | K6: 5 | M6: Cade Cunningham | N6: 5 | P6: Cade Cunningham | Q6: 5 | S6: Jayson Tatum | T6: 5 | V6: Giannis Antetokounmpo | W6: 5 | Y6: Giannis Antetokounmpo | Z6: 5 | AB6: Tyrese Haliburton | AC6: 5 | AE6: Tyrese Haliburton | AF6: 5 | AH6: Tyrese Haliburton | AI6: 5 | AK6: Tyrese Haliburton | AL6: 5 | AN6: Tyrese Haliburton | AO6: 5 | AQ6: Tyrese Haliburton | AR6: 5 | AT6: Shai Gilgeous-Alexander | AU6: 5 | AW6: Shai Gilgeous-Alexander | AX6: 5 | AZ6: Tyrese Haliburton | BA6: 5 | BC6: Tyrese Haliburton | BD6: 5 | BF6: Tyrese Haliburton | BG6: 5 | BI6: Giannis Antetokounmpo | BJ6: 5 | BL6: Giannis Antetokounmpo | BM6: 5
A7: Cooper Flagg | B7: 6 | D7: Giannis Antetokounmpo | E7: 6 | G7: Giannis Antetokounmpo | H7: 6 | J7: Giannis Antetokounmpo | K7: 6 | M7: Giannis Antetokounmpo | N7: 6 | P7: Giannis Antetokounmpo | Q7: 6 | S7: Giannis Antetokounmpo | T7: 6 | V7: LaMelo Ball | W7: 6 | Y7: Anthony Edwards | Z7: 6 | AB7: Giannis Antetokounmpo | AC7: 6 | AE7: Giannis Antetokounmpo | AF7: 6 | AH7: Giannis Antetokounmpo | AI7: 6 | AK7: Giannis Antetokounmpo | AL7: 6 | AN7: Giannis Antetokounmpo | AO7: 6 | AQ7: Giannis Antetokounmpo | AR7: 6 | AT7: Giannis Antetokounmpo | AU7: 6 | AW7: Joel Embiid | AX7: 6 | AZ7: Shai Gilgeous-Alexander | BA7: 6 | BC7: Shai Gilgeous-Alexander | BD7: 6 | BF7: Shai Gilgeous-Alexander | BG7: 6 | BI7: Jayson Tatum | BJ7: 6 | BL7: Joel Embiid | BM7: 6
A8: Alperen Şengün | B8: 7 | D8: Cooper Flagg | E8: 7 | G8: Cooper Flagg | H8: 7 | J8: Cooper Flagg | K8: 7 | M8: Jayson Tatum | N8: 7 | P8: Jayson Tatum | Q8: 7 | S8: Cade Cunningham | T8: 7 | V8: Jayson Tatum | W8: 7 | Y8: LaMelo Ball | Z8: 7 | AB8: Anthony Edwards | AC8: 7 | AE8: Anthony Edwards | AF8: 7 | AH8: Scottie Barnes | AI8: 7 | AK8: Jayson Tatum | AL8: 7 | AN8: Jayson Tatum | AO8: 7 | AQ8: Jayson Tatum | AR8: 7 | AT8: Jayson Tatum | AU8: 7 | AW8: Giannis Antetokounmpo | AX8: 7 | AZ8: Giannis Antetokounmpo | BA8: 7 | BC8: Giannis Antetokounmpo | BD8: 7 | BF8: Giannis Antetokounmpo | BG8: 7 | BI8: Shai Gilgeous-Alexander | BJ8: 7 | BL8: Jayson Tatum | BM8: 7
A9: Jalen Johnson | B9: 8 | D9: Alperen Şengün | E9: 8 | G9: Amen Thompson | H9: 8 | J9: Alperen Şengün | K9: 8 | M9: Cooper Flagg | N9: 8 | P9: Chet Holmgren | Q9: 8 | S9: Paolo Banchero | T9: 8 | V9: Paolo Banchero | W9: 8 | Y9: Jayson Tatum | Z9: 8 | AB9: Paolo Banchero | AC9: 8 | AE9: Paolo Banchero | AF9: 8 | AH9: Anthony Edwards | AI9: 8 | AK9: Scottie Barnes | AL9: 8 | AN9: Scottie Barnes | AO9: 8 | AQ9: Scottie Barnes | AR9: 8 | AT9: Joel Embiid | AU9: 8 | AW9: Jayson Tatum | AX9: 8 | AZ9: Jayson Tatum | BA9: 8 | BC9: Jayson Tatum | BD9: 8 | BF9: Jayson Tatum | BG9: 8 | BI9: LaMelo Ball | BJ9: 8 | BL9: LaMelo Ball | BM9: 8
A10: Tyrese Maxey | B10: 9 | D10: Amen Thompson | E10: 9 | G10: Anthony Edwards | H10: 9 | J10: Anthony Edwards | K10: 9 | M10: Chet Holmgren | N10: 9 | P10: Alperen Şengün | Q10: 9 | S10: LaMelo Ball | T10: 9 | V10: Cade Cunningham | W10: 9 | Y10: Paolo Banchero | Z10: 9 | AB10: Scottie Barnes | AC10: 9 | AE10: Scottie Barnes | AF10: 9 | AH10: Jayson Tatum | AI10: 9 | AK10: Anthony Edwards | AL10: 9 | AN10: Anthony Edwards | AO10: 9 | AQ10: Joel Embiid | AR10: 9 | AT10: Scottie Barnes | AU10: 9 | AW10: Scottie Barnes | AX10: 9 | AZ10: Scottie Barnes | BA10: 9 | BC10: Scottie Barnes | BD10: 9 | BF10: Anthony Edwards | BG10: 9 | BI10: Tyrese Haliburton | BJ10: 9 | BL10: Anthony Edwards | BM10: 9
A11: Giannis Antetokounmpo | B11: 10 | D11: Anthony Edwards | E11: 10 | G11: Alperen Şengün | H11: 10 | J11: Chet Holmgren | K11: 10 | M11: Alperen Şengün | N11: 10 | P11: Anthony Edwards | Q11: 10 | S11: Anthony Edwards | T11: 10 | V11: Anthony Edwards | W11: 10 | Y11: Tyrese Haliburton | Z11: 10 | AB11: Jayson Tatum | AC11: 10 | AE11: Jayson Tatum | AF11: 10 | AH11: Alperen Şengün | AI11: 10 | AK11: Alperen Şengün | AL11: 10 | AN11: Alperen Şengün | AO11: 10 | AQ11: Alperen Şengün | AR11: 10 | AT11: LaMelo Ball | AU11: 10 | AW11: LaMelo Ball | AX11: 10 | AZ11: Anthony Edwards | BA11: 10 | BC11: Anthony Edwards | BD11: 10 | BF11: LaMelo Ball | BG11: 10 | BI11: Anthony Edwards | BJ11: 10 | BL11: Tyrese Haliburton | BM11: 10
A12: Anthony Edwards | B12: 11 | D12: Evan Mobley | E12: 11 | G12: Paolo Banchero | H12: 11 | J12: Paolo Banchero | K12: 11 | M12: Anthony Edwards | N12: 11 | P12: Cooper Flagg | Q12: 11 | S12: Chet Holmgren | T12: 11 | V12: Chet Holmgren | W12: 11 | Y12: Chet Holmgren | Z12: 11 | AB12: LaMelo Ball | AC12: 11 | AE12: Alperen Şengün | AF12: 11 | AH12: Paolo Banchero | AI12: 11 | AK12: Joel Embiid | AL12: 11 | AN12: Joel Embiid | AO12: 11 | AQ12: Paolo Banchero | AR12: 11 | AT12: Alperen Şengün | AU12: 11 | AW12: Alperen Şengün | AX12: 11 | AZ12: Alperen Şengün | BA12: 11 | BC12: Chet Holmgren | BD12: 11 | BF12: Scottie Barnes | BG12: 11 | BI12: Scottie Barnes | BJ12: 11 | BL12: Cade Cunningham | BM12: 11
A13: Jayson Tatum | B13: 12 | D13: Tyrese Maxey | E13: 12 | G13: Jalen Johnson | H13: 12 | J13: Jalen Johnson | K13: 12 | M13: Paolo Banchero | N13: 12 | P13: LaMelo Ball | Q13: 12 | S13: Cooper Flagg | T13: 12 | V13: Jalen Johnson | W13: 12 | Y13: Cade Cunningham | Z13: 12 | AB13: Alperen Şengün | AC13: 12 | AE13: Chet Holmgren | AF13: 12 | AH13: Chet Holmgren | AI13: 12 | AK13: Paolo Banchero | AL13: 12 | AN13: Paolo Banchero | AO13: 12 | AQ13: Chet Holmgren | AR13: 12 | AT13: Paolo Banchero | AU13: 12 | AW13: Paolo Banchero | AX13: 12 | AZ13: Chet Holmgren | BA13: 12 | BC13: LaMelo Ball | BD13: 12 | BF13: Alperen Şengün | BG13: 12 | BI13: Cade Cunningham | BJ13: 12 | BL13: Paolo Banchero | BM13: 12
... A302: Kam Jones | B302: 301 | D302: Tyrese Proctor | E302: 301 | G302: Terance Mann | H302: 301 | J302: Paul Reed | K302: 301 | M302: Tristan Vukčević | N302: 301 | P302: Baylor Scheierman | Q302: 301 | S302: Simone Fontecchio | T302: 301 | V302: Jamal Shead | W302: 301 | Y302: Charles Bassey | Z302: 301 | AB302: Julian Champagnie | AC302: 301 | AE302: Christian Wood | AF302: 301 | AH302: James Wiseman | AI302: 301 | AK302: David Roddy | AL302: 301 | AN302: Max Christie Jr. | AO302: 301 | AQ302: Jae Crowder | AR302: 301 | AT302: Emoni Bates | AU302: 301 | AW302: Jae Crowder | AX302: 301 | AZ302: Kris Murray | BA302: 301 | BC302: Reggie Jackson | BD302: 301 | BF302: Colby Jones | BG302: 301 | BI302: Josh Okogie | BJ302: 301 | BL302: Adama Sanogo | BM302: 301
A303: Julian Champagnie | B303: 302 | D303: Guerschon Yabusele | E303: 302 | G303: Tristan da Silva | H303: 302 | J303: Nick Richards | K303: 302 | M303: Dalano Banton | N303: 302 | P303: Luke Kennard | Q303: 302 | S303: Jose Alvarado | T303: 302 | V303: Zach Collins | W303: 302 | Y303: Oso Ighodaro | Z303: 302 | AB303: Duop Reath | AC303: 302 | AF303: 302 | AH303: Matisse Thybulle | AI303: 302 | AK303: Simone Fontecchio | AL303: 302 | AN303: Delon Wright | AO303: 302 | AQ303: Emoni Bates | AR303: 302 | AT303: Ochai Agbaji | AU303: 302 | AW303: Emoni Bates | AX303: 302 | AZ303: Pat Connaughton | BA303: 302 | BC303: Bismack Biyombo | BD303: 302 | BF303: Noah Clowney | BG303: 302 | BI303: Thomas Bryant | BJ303: 302 | BL303: Eric Gordon | BM303: 302
A304: Sion James | B304: 303 | D304: Andre Drummond | E304: 303 | G304: Kris Dunn | H304: 303 | J304: Jay Huff | K304: 303 | M304: Malcolm Brogdon | N304: 303 | P304: Ousmane Dieng | Q304: 303 | S304: Quinten Post | T304: 303 | W304: 303 | Y304: Jordan Miller | Z304: 303 | AB304: Kobe Brown | AC304: 303 | AF304: 303 | AH304: Dariq Whitehead | AI304: 303 | AK304: Ziaire Williams | AL304: 303 | AN304: T.J. McConnell | AO304: 303 | AQ304: Ochai Agbaji | AR304: 303 | AT304: Sam Hauser | AU304: 303 | AW304: Sam Hauser | AX304: 303 | AZ304: Jaylin Williams | BA304: 303 | BC304: Zeke Nnaji | BD304: 303 | BF304: Gary Payton II | BG304: 303 | BI304: Dominick Barlow | BJ304: 303 | BL304: Jae Crowder | BM304: 303
A305: Jonathan Mogbo | B305: 304 | D305: Micah Peavy | E305: 304 | G305: Julian Champagnie | H305: 304 | J305: Sandro Mamukelashvili | K305: 304 | M305: Isaac Okoro | N305: 304 | P305: Luke Kornet | Q305: 304 | S305: Karlo Matković | T305: 304 | W305: 304 | Y305: Ricky Council IV | Z305: 304 | AB305: Christian Wood | AC305: 304 | AF305: 304 | AH305: Ziaire Williams | AI305: 304 | AK305: Larry Nance Jr. | AL305: 304 | AN305: Gabe Vincent | AO305: 304 | AQ305: Sam Hauser | AR305: 304 | AT305: Pat Connaughton | AU305: 304 | AW305: Pat Connaughton | AX305: 304 | AZ305: Robert Covington | BA305: 304 | BC305: Trey Lyles | BD305: 304 | BF305: Kira Lewis Jr. | BG305: 304 | BI305: Kenneth Lofton Jr. | BJ305: 304 | BL305: Naji Marshall | BM305: 304
A306: Trayce Jackson-Davis | B306: 305 | D306: Julian Strawther | E306: 305 | G306: Chaz Lanier | H306: 305 | J306: Sion James | K306: 305 | M306: Craig Porter Jr. | N306: 305 | P306: Ochai Agbaji | Q306: 305 | S306: Jalen Wilson | T306: 305 | W306: 305 | Y306: Kris Dunn | Z306: 305 | AB306: Delon Wright | AC306: 305 | AF306: 305 | AH306: Ben Sheppard | AI306: 305 | AK306: Jevon Carter | AL306: 305 | AN306: Kevin Love | AO306: 305 | AQ306: Pat Connaughton | AR306: 305 | AT306: Jaylin Williams | AU306: 305 | AW306: Jaylin Williams | AX306: 305 | AZ306: Chris Boucher | BA306: 305 | BC306: Jaxson Hayes | BD306: 305 | BF306: KJ Martin | BG306: 305 | BI306: Cam Reddish | BJ306: 305 | BL306: Chris Duarte | BM306: 305
A307: Jose Alvarado | B307: 306 | D307: Leonard Miller | E307: 306 | G307: Dillon Jones | H307: 306 | J307: Chris Paul | K307: 306 | M307: Ryan Rollins | N307: 306 | P307: Simone Fontecchio | Q307: 306 | S307: Malaki Branham | T307: 306 | W307: 306 | Y307: Jaden Springer | Z307: 306 | AB307: Dario Šarić | AC307: 306 | AF307: 306 | AH307: AJ Griffin | AI307: 306 | AK307: Matisse Thybulle | AL307: 306 | AN307: Alec Burks | AO307: 306 | AQ307: Jaylin Williams | AR307: 306 | AT307: Robert Covington | AU307: 306 | AW307: Robert Covington | AX307: 306 | AZ307: Simone Fontecchio | BA307: 306 | BC307: Torrey Craig | BD307: 306 | BF307: Vasilije Micić | BG307: 306 | BI307: Mo Bamba | BJ307: 306 | BL307: Jaxson Hayes | BM307: 306
A308: Ben Saraf | B308: 307 | D308: Ja'Kobe Walter | E308: 307 | G308: Jonas Valančiūnas | H308: 307 | J308: Xavier Tillman Sr. | K308: 307 | M308: Jett Howard | N308: 307 | P308: Jose Alvarado | Q308: 307 | S308: Adem Bona | T308: 307 | W308: 307 | Y308: Tim Hardaway Jr. | Z308: 307 | AB308: Larry Nance Jr. | AC308: 307 | AF308: 307 | AH308: Kris Dunn | AI308: 307 | AK308: Dennis Smith Jr. | AL308: 307 | AN308: Taurean Prince | AO308: 307 | AQ308: Robert Covington | AR308: 307 | AT308: Chris Boucher | AU308: 307 | AW308: Chris Boucher | AX308: 307 | AZ308: Charles Bassey | BA308: 307 | BC308: Trendon Watford | BD308: 307 | BF308: Craig Porter Jr. | BG308: 307 | BI308: T.J. McConnell | BJ308: 307 | BL308: Nick Smith Jr. | BM308: 307
A309: Buddy Hield | B309: 308 | D309: Dru Smith | E309: 308 | G309: Kentavious Caldwell-Pope | H309: 308 | J309: Caleb Martin | K309: 308 | M309: Zach Collins | N309: 308 | P309: Davion Mitchell | Q309: 308 | S309: Spencer Dinwiddie | T309: 308 | W309: 308 | Y309: Davion Mitchell | Z309: 308 | AB309: Naji Marshall | AC309: 308 | AF309: 308 | AH309: Dante Exum | AI309: 308 | AK309: Cam Reddish | AL309: 308 | AN309: Jae Crowder | AO309: 308 | AQ309: Chris Boucher | AR309: 308 | AT309: Charles Bassey | AU309: 308 | AW309: Charles Bassey | AX309: 308 | AZ309: Reggie Jackson | BA309: 308 | BC309: Dean Wade | BD309: 308 | BF309: Johnny Davis | BG309: 308 | BI309: Ochai Agbaji | BJ309: 308 | BL309: Isaiah Livers | BM309: 308
A310: Harrison Barnes | B310: 309 | D310: AJ Green | E310: 309 | G310: Marcus Sasser | H310: 309 | J310: Grant Williams | K310: 309 | M310: Moritz Wagner | N310: 309 | P310: Jordan Miller | Q310: 309 | S310: Bones Hyland | T310: 309 | W310: 309 | Y310: Ben Sheppard | Z310: 309 | AB310: Bobi Klintman | AC310: 309 | AF310: 309 | AH310: Jalen Pickett | AI310: 309 | AK310: Cody Martin | AL310: 309 | AN310: Emoni Bates | AO310: 309 | AQ310: Charles Bassey | AR310: 309 | AT310: Reggie Jackson | AU310: 309 | AW310: Reggie Jackson | AX310: 309 | AZ310: Zeke Nnaji | BA310: 309 | BC310: Shake Milton | BD310: 309 | BF310: Mason Plumlee | BG310: 309 | BI310: Dariq Whitehead | BJ310: 309 | BL310: Blake Wesley | BM310: 309
A311: Corey Kispert | B311: 310 | D311: Jarred Vanderbilt | E311: 310 | G311: Jordan Clarkson | H311: 310 | J311: Jonas Valančiūnas | K311: 310 | M311: Harrison Barnes | N311: 310 | P311: Mouhamed Gueye | Q311: 310 | S311: Matisse Thybulle | T311: 310 | W311: 310 | Y311: Johnny Furphy | Z311: 310 | AB311: Taurean Prince | AC311: 310 | AF311: 310 | AH311: Ricky Council IV | AI311: 310 | AK311: Dorian Finney-Smith | AL311: 310 | AN311: Sam Hauser | AO311: 310 | AQ311: Reggie Jackson | AR311: 310 | AT311: Zeke Nnaji | AU311: 310 | AW311: Zeke Nnaji | AX311: 310 | AZ311: Trey Lyles | BA311: 310 | BC311: Colby Jones | BD311: 310 | BF311: Sam Hauser | BG311: 310 | BI311: Cedi Osman | BJ311: 310 | BL311: Jae'Sean Tate | BM311: 310
A312: Will Richard | B312: 311 | D312: Kevon Looney | E312: 311 | G312: Justin Edwards | H312: 311 | J312: Tyrese Proctor | K312: 311 | M312: Jarred Vanderbilt | N312: 311 | P312: Jalen Wilson | Q312: 311 | S312: Jamal Shead | T312: 311 | W312: 311 | Y312: Jaylen Wells | Z312: 311 | AB312: Drew Eubanks | AC312: 311 | AF312: 311 | AH312: Julian Champagnie | AI312: 311 | AK312: Kevon Looney | AL312: 311 | AN312: Dario Šarić | AO312: 311 | AQ312: Zeke Nnaji | AR312: 311 | AU312: 311 | AW312: Trey Lyles | AX312: 311 | AZ312: Jaxson Hayes | BA312: 311 | BC312: Noah Clowney | BD312: 311 | BF312: Ömer Yurtseven | BG312: 311 | BI312: Taurean Prince | BJ312: 311 | BL312: Isaac Okoro | BM312: 311
A313: Klay Thompson | B313: 312 | D313: Dalton Knecht | E313: 312 | G313: Nick Richards | H313: 312 | J313: Isaiah Joe | K313: 312 | M313: Andre Jackson Jr. | N313: 312 | P313: Malaki Branham | Q313: 312 | S313: Zach Collins | T313: 312 | W313: 312 | Y313: Duop Reath | Z313: 312 | AB313: Luke Kornet | AC313: 312 | AF313: 312 | AH313: Lonnie Walker IV | AI313: 312 | AK313: Kris Dunn | AL313: 312 | AN313: Pat Connaughton | AO313: 312 | AQ313: Trey Lyles | AR313: 312 | AU313: 312 | AW313: Jaxson Hayes | AX313: 312 | AZ313: Dominick Barlow | BA313: 312 | BC313: Gary Payton II | BD313: 312 | BF313: Davion Mitchell | BG313: 312 | BI313: Reggie Jackson | BJ313: 312 | BL313: Ben Sheppard | BM313: 312
A314: Bogdan Bogdanović | B314: 313 | D314: Oso Ighodaro | E314: 313 | G314: Ben Simmons | H314: 313 | J314: Kentavious Caldwell-Pope | K314: 313 | M314: Marcus Sasser | N314: 313 | P314: Adem Bona | Q314: 313 | S314: Oso Ighodaro | T314: 313 | W314: 313 | Y314: Kobe Brown | Z314: 313 | AB314: Mo Bamba | AC314: 313 | AF314: 313 | AH314: Larry Nance Jr. | AI314: 313 | AK314: Jalen McDaniels | AL314: 313 | AN314: Jaylin Williams | AO314: 313 | AQ314: Jaxson Hayes | AR314: 313 | AU314: 313 | AW314: Dominick Barlow | AX314: 313 | AZ314: Malachi Flynn | BA314: 313 | BC314: Kira Lewis Jr. | BD314: 313 | BF314: Jae'Sean Tate | BG314: 313 | BI314: Duncan Robinson | BJ314: 313 | BL314: Christian Koloko | BM314: 313
A315: Brook Lopez | B315: 314 | D315: Terance Mann | E315: 314 | G315: Sion James | H315: 314 | J315: Josh Green | K315: 314 | M315: Baylor Scheierman | N315: 314 | P315: Spencer Dinwiddie | Q315: 314 | S315: Moussa Diabaté | T315: 314 | W315: 314 | Y315: Christian Wood | Z315: 314 | AB315: Pelle Larsson | AC315: 314 | AF315: 314 | AH315: Max Christie Jr. | AI315: 314 | AK315: Dante Exum | AL315: 314 | AN315: Robert Covington | AO315: 314 | AQ315: Dominick Barlow | AR315: 314 | AU315: 314 | AW315: Malachi Flynn | AX315: 314 | AZ315: Torrey Craig | BA315: 314 | BC315: KJ Martin | BD315: 314 | BF315: Josh Okogie | BG315: 314 | BI315: Adama Sanogo | BJ315: 314 | BL315: Andre Jackson Jr. | BM315: 314
A316: Gradey Dick | B316: 315 | D316: Chaz Lanier | E316: 315 | G316: Ochai Agbaji | H316: 315 | J316: Hugo González | K316: 315 | M316: Luke Kennard | N316: 315 | P316: Matisse Thybulle | Q316: 315 | S316: Jordan Miller | T316: 315 | W316: 315 | Y316: Dario Šarić | Z316: 315 | AB316: Jose Alvarado | AC316: 315 | AF316: 315 | AH316: Gordon Hayward | AI316: 315 | AK316: Ben Sheppard | AL316: 315 | AN316: Chris Boucher | AO316: 315 | AQ316: Aaron Wiggins | AR316: 315 | AU316: 315 | AW316: Torrey Craig | AX316: 315 | AZ316: Trendon Watford | BA316: 315 | BC316: Johnny Davis | BD316: 315 | BF316: Thomas Bryant | BG316: 315 | BI316: Eric Gordon | BJ316: 315 | BL316: Zeke Nnaji | BM316: 315
A317: Tyrese Proctor | B317: 316 | D317: Tidjane Salaün | E317: 316 | G317: Jarred Vanderbilt | H317: 316 | J317: Duncan Robinson | K317: 316 | M317: Jaden Hardy | N317: 316 | P317: Jamal Shead | Q317: 316 | S317: Larry Nance Jr. | T317: 316 | W317: 316 | Y317: Larry Nance Jr. | Z317: 316 | AB317: AJ Johnson | AC317: 316 | AF317: 316 | AH317: Drew Eubanks | AI317: 316 | AK317: Monte Morris | AL317: 316 | AN317: Charles Bassey | AO317: 316 | AQ317: Torrey Craig | AR317: 316 | AU317: 316 | AW317: Ben Sheppard | AX317: 316 | AZ317: Dean Wade | BA317: 316 | BC317: Mason Plumlee | BD317: 316 | BF317: Dominick Barlow | BG317: 316 | BI317: Jae Crowder | BJ317: 316 | BL317: Kris Dunn | BM317: 316
A318: Guerschon Yabusele | B318: 317 | D318: Jonathan Isaac | E318: 317 | G318: Sam Merrill | H318: 317 | J318: Dorian Finney-Smith | K318: 317 | M318: Ousmane Dieng | N318: 317 | P318: KJ Martin | Q318: 317 | S318: Ricky Council IV | T318: 317 | W318: 317 | Y318: Marvin Bagley III | Z318: 317 | AB318: Gabe Vincent | AC318: 317 | AF318: 317 | AH318: Jalen McDaniels | AI318: 317 | AK318: Jalen Pickett | AL318: 317 | AN318: Reggie Jackson | AO318: 317 | AQ318: Ben Sheppard | AR318: 317 | AU318: 317 | AW318: Trendon Watford | AX318: 317 | AZ318: Shake Milton | BA318: 317 | BC318: Ömer Yurtseven | BD318: 317 | BF318: Kenneth Lofton Jr. | BG318: 317 | BI318: Naji Marshall | BJ318: 317 | BL318: Kira Lewis Jr. | BM318: 317
A319: Micah Peavy | B319: 318 | D319: Vít Krejčí | E319: 318 | G319: Johnny Furphy | H319: 318 | J319: Brandon Williams | K319: 318 | M319: Luke Kornet | N319: 318 | P319: Oso Ighodaro | Q319: 318 | S319: Kris Dunn | T319: 318 | W319: 318 | Y319: Bobi Klintman | Z319: 318 | AB319: Josh Richardson | AC319: 318 | AF319: 318 | AH319: Kris Murray | AI319: 318 | AK319: Jose Alvarado | AL319: 318 | AN319: Zeke Nnaji | AO319: 318 | AQ319: Trendon Watford | AR319: 318 | AU319: 318 | AW319: Shake Milton | AX319: 318 | AZ319: Hunter Tyson | BA319: 318 | BC319: Davion Mitchell | BD319: 318 | BF319: Mo Bamba | BG319: 318 | BI319: Chris Duarte | BJ319: 318 | BL319: Trendon Watford | BM319: 318
A320: Julian Strawther | B320: 319 | D320: Jonas Valančiūnas | E320: 319 | G320: Matisse Thybulle | H320: 319 | J320: Drake Powell | K320: 319 | M320: Ochai Agbaji | N320: 319 | P320: Moussa Diabaté | Q320: 319 | S320: Jaden Springer | T320: 319 | W320: 319 | Y320: Jaxson Hayes | Z320: 319 | AB320: Ja'Kobe Walter | AC320: 319 | AF320: 319 | AH320: Cody Martin | AI320: 319 | AK320: Jalen Hood-Schifino | AL320: 319 | AN320: Trey Lyles | AO320: 319 | AQ320: James Nnaji | AR320: 319 | AU320: 319 | AW320: Hunter Tyson | AX320: 319 | AZ320: Colby Jones | BA320: 319 | BC320: Jae'Sean Tate | BD320: 319 | BF320: Ochai Agbaji | BG320: 319 | BI320: Jaxson Hayes | BJ320: 319 | BL320: Ziaire Williams | BM320: 319
A321: Leonard Miller | B321: 320 | D321: Marcus Sasser | E321: 320 | G321: Tyrese Proctor | H321: 320 | J321: Trendon Watford | K321: 320 | M321: Simone Fontecchio | N321: 320 | P321: Larry Nance Jr. | Q321: 320 | S321: Tim Hardaway Jr. | T321: 320 | W321: 320 | Y321: Taurean Prince | Z321: 320 | AB321: Georges Niang | AC321: 320 | AF321: 320 | AH321: Dennis Smith Jr. | AI321: 320 | AK321: Orlando Robinson | AL321: 320 | AN321: Jaxson Hayes | AO321: 320 | AQ321: Hunter Tyson | AR321: 320 | AU321: 320 | AW321: Colby Jones | AX321: 320 | AZ321: Noah Clowney | BA321: 320 | BC321: Josh Okogie | BD321: 320 | BF321: Dariq Whitehead | BG321: 320 | BI321: Nick Smith Jr. | BJ321: 320 | BL321: John Konchar | BM321: 320
A322: AJ Green | B322: 321 | D322: Jordan Clarkson | E322: 321 | G322: Cam Spencer | H322: 321 | J322: Bol Bol | K322: 321 | M322: Jordan Miller | N322: 321 | P322: Ricky Council IV | Q322: 321 | S322: Davion Mitchell | T322: 321 | W322: 321 | Y322: Drew Eubanks | Z322: 321 | AB322: Kyshawn George | AC322: 321 | AF322: 321 | AH322: Dean Wade | AI322: 321 | AK322: Sam Merrill | AL322: 321 | AN322: Dominick Barlow | AO322: 321 | AQ322: Colby Jones | AR322: 321 | AU322: 321 | AW322: Gary Payton II | AX322: 321 | AZ322: Gary Payton II | BA322: 321 | BC322: Thomas Bryant | BD322: 321 | BF322: Aleksandar Vezenkov | BG322: 321 | BI322: Isaiah Livers | BJ322: 321 | BL322: Nassir Little | BM322: 321
A323: Jarred Vanderbilt | B323: 322 | D323: Justin Edwards | E323: 322 | G323: Jusuf Nurkić | H323: 322 | J323: Jordan Clarkson | K323: 322 | M323: Jalen Wilson | N323: 322 | P323: Tim Hardaway Jr. | Q323: 322 | S323: Ben Sheppard | T323: 322 | W323: 322 | Y323: Luke Kornet | Z323: 322 | AB323: Tim Hardaway Jr. | AC323: 322 | AF323: 322 | AH323: Jalen Hood-Schifino | AI323: 322 | AK323: Julian Champagnie | AL323: 322 | AN323: Vasilije Micić | AO323: 322 | AQ323: Gary Payton II | AR323: 322 | AU323: 322 | AW323: Kira Lewis Jr. | AX323: 322 | AZ323: Kira Lewis Jr. | BA323: 322 | BC323: Dominick Barlow | BD323: 322 | BF323: Daniel Theis | BG323: 322 | BI323: Blake Wesley | BJ323: 322 | BL323: Devonte' Graham | BM323: 322
... A401: Tony Bradley | B401: 400 | D401: Kyle Anderson | E401: 400 | G401: Gui Santos | H401: 400 | J401: Richaun Holmes | K401: 400 | M401: PJ Hall | N401: 400 | P401: Mason Plumlee | Q401: 400 | S401: KJ Simpson | T401: 400 | W401: 400 | Y401: Bruno Fernando | Z401: 400 | AB401: Juan Núñez | AC401: 400 | AF401: 400 | AH401: Josh Okogie | AI401: 400 | AK401: Shake Milton | AL401: 400 | AN401: Jordan McLaughlin | AO401: 400 | AQ401: Wendell Moore Jr. | AR401: 400 | AU401: 400 | AW401: Wendell Moore Jr. | AX401: 400 | AZ401: Jordan Walsh | BA401: 400 | BC401: Joe Ingles | BD401: 400 | BF401: Otto Porter Jr. | BG401: 400 | BI401: Ąžuolas Tubelis | BJ401: 400 | BL401: D'Moi Hodge | BM401: 400
B402: 401 | E402: 401 | G402: Julian Phillips | H402: 401 | J402: Chris Boucher | K402: 401 | M402: Kevon Looney | N402: 401 | Q402: 401 | T402: 401 | W402: 401 | Z402: 401 | AB402: Sidy Cissoko | AC402: 401 | AF402: 401 | AH402: Keita Bates-Diop | AI402: 401 | AK402: Malachi Flynn | AL402: 401 | AN402: JaVale McGee | AO402: 401 | AQ402: Usman Garuba | AR402: 401 | AU402: 401 | AW402: Usman Garuba | AX402: 401 | AZ402: Marcus Morris Sr. | BA402: 401 | BC402: Collin Gillespie | BD402: 401 | BF402: Joe Ingles | BG402: 401 | BI402: J.D. Davison | BJ402: 401 | BL402: Damian Jones | BM402: 401
B403: 402 | E403: 402 | G403: Kyle Anderson | H403: 402 | J403: Sam Hauser | K403: 402 | M403: Nicolas Batum | N403: 402 | Q403: 402 | T403: 402 | W403: 402 | Z403: 402 | AB403: Colby Jones | AC403: 402 | AF403: 402 | AH403: Kevin McCullar Jr. | AI403: 402 | AK403: Troy Brown Jr. | AL403: 402 | AN403: Luke Kornet | AO403: 402 | AQ403: Jalen Slawson | AR403: 402 | AU403: 402 | AW403: Jalen Slawson | AX403: 402 | AZ403: Wendell Moore Jr. | BA403: 402 | BC403: Théo Maledon | BD403: 402 | BF403: Collin Gillespie | BG403: 402 | BI403: Josh Christopher | BJ403: 402 | BL403: Jalen Slawson | BM403: 402
B404: 403 | E404: 403 | G404: Jamison Battle | H404: 403 | J404: Dean Wade | K404: 403 | N404: 403 | Q404: 403 | T404: 403 | W404: 403 | Z404: 403 | AB404: Josh Christopher | AC404: 403 | AF404: 403 | AH404: Pelle Larsson | AI404: 403 | AK404: Jericho Sims | AL404: 403 | AN404: Sandro Mamukelashvili | AO404: 403 | AQ404: Oshae Brissett | AR404: 403 | AU404: 403 | AW404: Oshae Brissett | AX404: 403 | AZ404: Usman Garuba | BA404: 403 | BC404: Ty Jerome | BD404: 403 | BF404: Théo Maledon | BG404: 403 | BI404: Damion Lee | BJ404: 403 | BL404: Ish Wainright | BM404: 403
B405: 404 | E405: 404 | G405: Jared Butler | H405: 404 | J405: Svi Mykhailiuk | K405: 404 | N405: 404 | Q405: 404 | T405: 404 | W405: 404 | Z405: 404 | AB405: Emoni Bates | AC405: 404 | AF405: 404 | AH405: Thomas Bryant | AI405: 404 | AK405: Neemias Queta | AL405: 404 | AN405: Jeremiah Robinson-Earl | AO405: 404 | AQ405: Chris Livingston | AR405: 404 | AU405: 404 | AW405: Chris Livingston | AX405: 404 | AZ405: Oshae Brissett | BA405: 404 | BC405: Jacob Gilyard | BD405: 404 | BF405: Ty Jerome | BG405: 404 | BI405: Vlatko Čančar | BJ405: 404 | BL405: Toumani Camara | BM405: 404
B406: 405 | E406: 405 | G406: Bronny James | H406: 405 | J406: Taelon Peter | K406: 405 | N406: 405 | Q406: 405 | T406: 405 | W406: 405 | Z406: 405 | AB406: Chris Livingston | AC406: 405 | AF406: 405 | AH406: Mo Bamba | AI406: 405 | AL406: 405 | AN406: Jordan Walsh | AO406: 405 | AR406: 405 | AU406: 405 | AW406: Landry Shamet | AX406: 405 | AZ406: Chris Livingston | BA406: 405 | BC406: J.D. Davison | BD406: 405 | BF406: Jacob Gilyard | BG406: 405 | BI406: Kevin Porter Jr. | BJ406: 405 | BL406: Mike Muscala | BM406: 405
B407: 406 | E407: 406 | H407: 406 | J407: Tony Bradley | K407: 406 | N407: 406 | Q407: 406 | T407: 406 | W407: 406 | Z407: 406 | AB407: Daniss Jenkins | AC407: 406 | AF407: 406 | AH407: Antonio Reeves | AI407: 406 | AL407: 406 | AN407: Wendell Moore Jr. | AO407: 406 | AR407: 406 | AU407: 406 | AW407: Otto Porter Jr. | AX407: 406 | AZ407: Landry Shamet | BA407: 406 | BC407: Josh Christopher | BD407: 406 | BF407: J.D. Davison | BG407: 406 | BI407: Bryce McGowens | BJ407: 406 | BL407: Isaiah Roby | BM407: 406
B408: 407 | E408: 407 | H408: 407 | K408: 407 | N408: 407 | Q408: 407 | T408: 407 | W408: 407 | Z408: 407 | AB408: Jalen Pickett | AC408: 407 | AF408: 407 | AH408: Rayan Rupert | AI408: 407 | AL408: 407 | AN408: Usman Garuba | AO408: 407 | AR408: 407 | AU408: 407 | AW408: Joe Ingles | AX408: 407 | AZ408: Otto Porter Jr. | BA408: 407 | BC408: Damion Lee | BD408: 407 | BF408: Josh Christopher | BG408: 407 | BI408: Simone Fontecchio | BJ408: 407 | BL408: Darius Bazley | BM408: 407
B409: 408 | E409: 408 | H409: 408 | K409: 408 | N409: 408 | Q409: 408 | T409: 408 | W409: 408 | Z409: 408 | AB409: Sandro Mamukelashvili | AC409: 408 | AF409: 408 | AH409: Bronny James | AI409: 408 | AL409: 408 | AN409: Jalen Slawson | AO409: 408 | AR409: 408 | AU409: 408 | AW409: Olivier Sarr | AX409: 408 | AZ409: Joe Ingles | BA409: 408 | BC409: Vlatko Čančar | BD409: 408 | BF409: Damion Lee | BG409: 408 | BI409: Ish Wainright | BJ409: 408 | BL409: Evan Fournier | BM409: 408
B410: 409 | E410: 409 | H410: 409 | K410: 409 | N410: 409 | Q410: 409 | T410: 409 | W410: 409 | Z410: 409 | AB410: Caleb Houstan | AC410: 409 | AF410: 409 | AH410: Justin Edwards | AI410: 409 | AL410: 409 | AN410: Oshae Brissett | AO410: 409 | AR410: 409 | AU410: 409 | AW410: Collin Gillespie | AX410: 409 | AZ410: Olivier Sarr | BA410: 409 | BC410: Bryce McGowens | BD410: 409 | BF410: Vlatko Čančar | BG410: 409 | BI410: D'Moi Hodge | BJ410: 409 | BL410: Dante Exum | BM410: 409
B411: 410 | E411: 410 | H411: 410 | K411: 410 | N411: 410 | Q411: 410 | T411: 410 | W411: 410 | Z411: 410 | AB411: Zeke Nnaji | AC411: 410 | AF411: 410 | AH411: Sasha Vezenkov | AI411: 410 | AL411: 410 | AN411: Jared Butler | AO411: 410 | AR411: 410 | AU411: 410 | AW411: Théo Maledon | AX411: 410 | AZ411: Collin Gillespie | BA411: 410 | BC411: Ish Wainright | BD411: 410 | BF411: Kevin Porter Jr. | BG411: 410 | BI411: Damian Jones | BJ411: 410 | BL411: Craig Porter Jr. | BM411: 410
B412: 411 | E412: 411 | H412: 411 | K412: 411 | N412: 411 | Q412: 411 | T412: 411 | W412: 411 | Z412: 411 | AB412: AJ Green | AC412: 411 | AF412: 411 | AI412: 411 | AL412: 411 | AN412: Scotty Pippen Jr. | AO412: 411 | AR412: 411 | AU412: 411 | AW412: Ty Jerome | AX412: 411 | AZ412: Théo Maledon | BA412: 411 | BC412: D'Moi Hodge | BD412: 411 | BF412: Bryce McGowens | BG412: 411 | BI412: Jalen Slawson | BJ412: 411 | BL412: Brandon Boston Jr. | BM412: 411
B413: 412 | E413: 412 | H413: 412 | K413: 412 | N413: 412 | Q413: 412 | T413: 412 | W413: 412 | Z413: 412 | AB413: Nikola Đurišić | AC413: 412 | AF413: 412 | AI413: 412 | AL413: 412 | AO413: 412 | AR413: 412 | AU413: 412 | AW413: Jacob Gilyard | AX413: 412 | AZ413: Ty Jerome | BA413: 412 | BC413: Damian Jones | BD413: 412 | BF413: Ish Wainright | BG413: 412 | BI413: Mike Muscala | BJ413: 412 | BL413: Jalen Wilson | BM413: 412
B414: 413 | E414: 413 | H414: 413 | K414: 413 | N414: 413 | Q414: 413 | T414: 413 | W414: 413 | Z414: 413 | AB414: Olivier-Maxence Prosper | AC414: 413 | AF414: 413 | AI414: 413 | AL414: 413 | AO414: 413 | AR414: 413 | AU414: 413 | AW414: J.D. Davison | AX414: 413 | AZ414: Jacob Gilyard | BA414: 413 | BC414: Jalen Slawson | BD414: 413 | BF414: D'Moi Hodge | BG414: 413 | BI414: Evan Fournier | BJ414: 413 | BL414: JT Thor | BM414: 413
B415: 414 | E415: 414 | H415: 414 | K415: 414 | N415: 414 | Q415: 414 | T415: 414 | W415: 414 | Z415: 414 | AB415: Keon Johnson | AC415: 414 | AF415: 414 | AI415: 414 | AL415: 414 | AO415: 414 | AR415: 414 | AU415: 414 | AX415: 414 | AZ415: J.D. Davison | BA415: 414 | BC415: Mike Muscala | BD415: 414 | BF415: Damian Jones | BG415: 414 | BI415: Dante Exum | BJ415: 414 | BL415: Wenyen Gabriel | BM415: 414
B416: 415 | E416: 415 | H416: 415 | K416: 415 | N416: 415 | Q416: 415 | T416: 415 | W416: 415 | Z416: 415 | AB416: Jay Huff | AC416: 415 | AF416: 415 | AI416: 415 | AL416: 415 | AO416: 415 | AR416: 415 | AU416: 415 | AX416: 415 | AZ416: Damion Lee | BA416: 415 | BC416: Evan Fournier | BD416: 415 | BF416: Jalen Slawson | BG416: 415 | BI416: Brandon Boston Jr. | BJ416: 415 | BL416: Tristan Vukčević | BM416: 415
B417: 416 | E417: 416 | H417: 416 | K417: 416 | N417: 416 | Q417: 416 | T417: 416 | W417: 416 | Z417: 416 | AB417: Ariel Hukporti | AC417: 416 | AF417: 416 | AI417: 416 | AL417: 416 | AO417: 416 | AR417: 416 | AU417: 416 | AX417: 416 | AZ417: Vlatko Čančar | BA417: 416 | BC417: Brandon Boston Jr. | BD417: 416 | BF417: Mike Muscala | BG417: 416 | BI417: Jalen Wilson | BJ417: 416 | BL417: Jamal Cain | BM417: 416
B418: 417 | E418: 417 | H418: 417 | K418: 417 | N418: 417 | Q418: 417 | T418: 417 | W418: 417 | Z418: 417 | AB418: Monte Morris | AC418: 417 | AF418: 417 | AI418: 417 | AL418: 417 | AO418: 417 | AR418: 417 | AU418: 417 | AX418: 417 | AZ418: Damian Jones | BA418: 417 | BC418: Jalen Wilson | BD418: 417 | BF418: Evan Fournier | BG418: 417 | BI418: JT Thor | BJ418: 417 | BL418: Yuta Watanabe | BM418: 417
B419: 418 | E419: 418 | H419: 418 | K419: 418 | N419: 418 | Q419: 418 | T419: 418 | W419: 418 | Z419: 418 | AB419: Dante Exum | AC419: 418 | AF419: 418 | AI419: 418 | AL419: 418 | AO419: 418 | AR419: 418 | AU419: 418 | AX419: 418 | AZ419: Jalen Slawson | BA419: 418 | BC419: JT Thor | BD419: 418 | BF419: Dante Exum | BG419: 418 | BI419: Tristan Vukčević | BJ419: 418 | BL419: R.J. Hampton | BM419: 418
B420: 419 | E420: 419 | H420: 419 | K420: 419 | N420: 419 | Q420: 419 | T420: 419 | W420: 419 | Z420: 419 | AB420: Jalen Bridges | AC420: 419 | AF420: 419 | AI420: 419 | AL420: 419 | AO420: 419 | AR420: 419 | AU420: 419 | AX420: 419 | AZ420: Mike Muscala | BA420: 419 | BC420: Tristan Vukčević | BD420: 419 | BF420: Brandon Boston Jr. | BG420: 419 | BI420: Yuta Watanabe | BJ420: 419 | BL420: Doug McDermott | BM420: 419
B421: 420 | E421: 420 | H421: 420 | K421: 420 | N421: 420 | Q421: 420 | T421: 420 | W421: 420 | Z421: 420 | AB421: Alec Burks | AC421: 420 | AF421: 420 | AI421: 420 | AL421: 420 | AO421: 420 | AR421: 420 | AU421: 420 | AX421: 420 | AZ421: Evan Fournier | BA421: 420 | BC421: Yuta Watanabe | BD421: 420 | BF421: Jalen Wilson | BG421: 420 | BI421: R.J. Hampton | BJ421: 420 | BL421: Lindy Waters III | BM421: 420
B422: 421 | E422: 421 | H422: 421 | K422: 421 | N422: 421 | Q422: 421 | T422: 421 | W422: 421 | Z422: 421 | AB422: Reggie Jackson | AC422: 421 | AF422: 421 | AI422: 421 | AL422: 421 | AO422: 421 | AR422: 421 | AU422: 421 | AX422: 421 | AZ422: Brandon Boston Jr. | BA422: 421 | BC422: R.J. Hampton | BD422: 421 | BF422: JT Thor | BG422: 421 | BI422: Doug McDermott | BJ422: 421 | BL422: Derrick Rose | BM422: 421
B423: 422 | E423: 422 | H423: 422 | K423: 422 | N423: 422 | Q423: 422 | T423: 422 | W423: 422 | Z423: 422 | AB423: Jesse Edwards | AC423: 422 | AF423: 422 | AI423: 422 | AL423: 422 | AO423: 422 | AR423: 422 | AU423: 422 | AX423: 422 | AZ423: Jalen Wilson | BA423: 422 | BC423: Doug McDermott | BD423: 422 | BF423: Tristan Vukčević | BG423: 422 | BI423: Lindy Waters III | BJ423: 422 | BL423: Neemias Queta | BM423: 422
B424: 423 | E424: 423 | H424: 423 | K424: 423 | N424: 423 | Q424: 423 | T424: 423 | W424: 423 | Z424: 423 | AB424: Jae'Sean Tate | AC424: 423 | AF424: 423 | AI424: 423 | AL424: 423 | AO424: 423 | AR424: 423 | AU424: 423 | AX424: 423 | AZ424: JT Thor | BA424: 423 | BC424: Lindy Waters III | BD424: 423 | BF424: Yuta Watanabe | BG424: 423 | BI424: Derrick Rose | BJ424: 423 | BL424: Luka Garza | BM424: 423
B425: 424 | E425: 424 | H425: 424 | K425: 424 | N425: 424 | Q425: 424 | T425: 424 | W425: 424 | Z425: 424 | AB425: Chris Duarte | AC425: 424 | AF425: 424 | AI425: 424 | AL425: 424 | AO425: 424 | AR425: 424 | AU425: 424 | AX425: 424 | AZ425: Tristan Vukčević | BA425: 424 | BC425: Derrick Rose | BD425: 424 | BF425: R.J. Hampton | BG425: 424 | BI425: Neemias Queta | BJ425: 424 | BL425: Danilo Gallinari | BM425: 424
B426: 425 | E426: 425 | H426: 425 | K426: 425 | N426: 425 | Q426: 425 | T426: 425 | W426: 425 | Z426: 425 | AB426: Isaac Jones | AC426: 425 | AF426: 425 | AI426: 425 | AL426: 425 | AO426: 425 | AR426: 425 | AU426: 425 | AX426: 425 | AZ426: Luka Garza | BA426: 425 | BC426: Luka Garza | BD426: 425 | BF426: Doug McDermott | BG426: 425 | BI426: Luka Garza | BJ426: 425 | BL426: Darius Days | BM426: 425
... B428: 427 | E428: 427 | H428: 427 | K428: 427 | N428: 427 | Q428: 427 | T428: 427 | W428: 427 | Z428: 427 | AB428: Johnny Juzang | AC428: 427 | AF428: 427 | AI428: 427 | AL428: 427 | AO428: 427 | AR428: 427 | AU428: 427 | AX428: 427 | AZ428: Markquis Nowell | BA428: 427 | BC428: Markquis Nowell | BD428: 427 | BF428: Derrick Rose | BG428: 427 | BI428: Darius Days | BJ428: 427 | BL428: Dalano Banton | BM428: 427
AB429: Alex Ducas | AZ429: Dalano Banton | BF429: Luka Garza | BG429: 428 | BI429: Markquis Nowell | BJ429: 428 | BL429: Oscar Tshiebwe | BM429: 428
AB430: Jordan Walsh | AZ430: Ibou Badji | BF430: Danilo Gallinari | BG430: 429 | BI430: Dalano Banton | BJ430: 429 | BL430: Dru Smith | BM430: 429
AB431: Patrick Baldwin Jr. | AZ431: Oscar Tshiebwe | BF431: Markquis Nowell | BG431: 430 | BI431: Oscar Tshiebwe | BJ431: 430 | BL431: Ibou Badji | BM431: 430
AB432: Ulrich Chomche | AZ432: Joshua Primo | BF432: Dalano Banton | BG432: 431 | BI432: Dru Smith | BJ432: 431 | BL432: Joshua Primo | BM432: 431
AB433: Alex Len | AZ433: Thaddeus Young | BF433: Ibou Badji | BG433: 432 | BI433: Joshua Primo | BJ433: 432 | BL433: Thaddeus Young | BM433: 432
AB434: Kevin Love | AZ434: Saben Lee | BF434: Oscar Tshiebwe | BG434: 433 | BI434: Thaddeus Young | BJ434: 433 | BL434: Vince Williams Jr. | BM434: 433
AB435: Armel Traoré | AZ435: Ron Harper Jr. | BF435: Joshua Primo | BG435: 434 | BI435: Vince Williams Jr. | BJ435: 434 | BL435: Saben Lee | BM435: 434
AB436: Rayan Rupert | AZ436: Cory Joseph | BF436: Thaddeus Young | BG436: 435 | BI436: Saben Lee | BJ436: 435 | BL436: Ron Harper Jr. | BM436: 435
AB437: Jaylen Martin | AZ437: Garrison Mathews | BF437: Saben Lee | BG437: 436 | BI437: Ron Harper Jr. | BJ437: 436 | BL437: Cory Joseph | BM437: 436
AB438: Kevin McCullar Jr. | AZ438: Isaiah Wong | BF438: Ron Harper Jr. | BG438: 437 | BI438: Cory Joseph | BJ438: 437 | BL438: Garrison Mathews | BM438: 437
AB439: Gui Santos | AZ439: Javon Freeman-Liberty | BF439: Cory Joseph | BG439: 438 | BI439: Garrison Mathews | BJ439: 438 | BL439: Isaiah Wong | BM439: 438
AB440: Jeremiah Robinson-Earl | AZ440: Svi Mykhailiuk | BF440: Garrison Mathews | BG440: 439 | BI440: Isaiah Wong | BJ440: 439 | BL440: Daniel Theis | BM440: 439
... AB501: Alondes Williams | AZ501: Justin Minaya | BF501: Jacob Toppin | BG501: 500 | BI501: Markieff Morris | BJ501: 500 | BL501: Joey Hauser | BM501: 500
AZ502: Daishen Nix | BF502: Greg Brown III | BG502: 501 | BI502: Boban Marjanović | BJ502: 501 | BL502: Kaiser Gates | BM502: 501
AZ503: Xavier Moon | BF503: Justin Holiday | BI503: Tristan Thompson | BL503: Jeremy Lamb
AZ504: Trevelin Queen | BF504: Jaylen Martin | BI504: Jermaine Samuels Jr. | BL504: Jordan Ford
AZ505: Charlie Brown Jr. | BF505: Cole Swider | BI505: Jerome Robinson | BL505: Kevin Knox II
AZ506: Nate Hinton | BF506: Justin Minaya | BI506: Harry Giles III | BL506: RJ Hunter
AZ507: Boban Marjanović | BF507: Duop Reath | BI507: JaMychal Green | BL507: Markieff Morris
AZ508: Tristan Thompson | BF508: Daishen Nix | BI508: Terry Taylor | BL508: Boban Marjanović
AZ509: Jermaine Samuels Jr. | BF509: Xavier Moon | BI509: Olivier Sarr | BL509: Tristan Thompson
AZ510: Jerome Robinson | BF510: Trevelin Queen | BI510: Ricky Council IV | BL510: Jermaine Samuels Jr.
BF511: Charlie Brown Jr. | BI511: Isaiah Todd | BL511: Jerome Robinson
BF512: Javonte Smart | BI512: Wesley Matthews | BL512: Harry Giles III
BF513: Nate Hinton | BI513: Leaky Black | BL513: Terry Taylor
BF514: Boban Marjanović | BI514: Dereon Seabron | BL514: Olivier Sarr
BF515: Tristan Thompson | BI515: Carlik Jones | BL515: Mike Miles Jr.
BF516: Jermaine Samuels Jr. | BI516: Jacob Gilyard | BL516: Quenton Jackson
BF517: Jerome Robinson | BI517: Lindell Wigginton | BL517: Ricky Council IV
BF518: Harry Giles III | BI518: A.J. Green | BL518: Wesley Matthews
BF519: JaMychal Green | BI519: Braxton Key | BL519: Jeenathan Williams Jr.
BF520: Terry Taylor | BI520: Matt Ryan | BL520: Leaky Black
BF521: Olivier Sarr | BI521: Micah Potter | BL521: Dereon Seabron
BF522: Jeenathan Williams Jr. | BI522: Udoka Azubuike | BL522: Carlik Jones
... BF530: A.J. Green | BI530: DeAndre Jordan | BL530: Udoka Azubuike
BF531: Matt Ryan | BL531: Collin Gillespie
BF532: Micah Potter | BL532: Jared Rhoden
BF533: Ish Smith | BL533: Jack White
...
